Workbook

Sheet 目录
H4: 明日之星华南价格表入仓执行日期2025/1/27
B5: 浙江明日之星供应链（深圳分公司）价格表一览表
B6: 区域 | C6: 省份 | D6: 城市 | E6: 仓库地址/联系人 | K6: 备注
B7: 华东仓 | C7: 浙江 | D7: 义乌(明星仓1号仓) | E7: 义乌仓：诸暨市安华镇万宏路2号万纬绍兴诸暨园区一楼2号库2分区2-06号门收货 联系方式：18749171088 程主管 | K7: 未贴标货物入库
D8: 义乌(明星仓2号仓) | E8: 义乌仓：诸暨市安华镇万宏路2号万纬绍兴诸暨园区一楼2号库2分区2-06号门收货 联系方式：18749171088 程主管 | K8: 已贴标货物入库
C9: 福建 | D9: 泉州(明星仓3号仓) | E9: 泉州仓：福建省泉州市晋江市法藏路11号（万纬泉州晋江冷链物流园） 联系方式：13110972302 张经理 | K9: 已贴标货物入库
D10: 厦门（明星仓7号仓） | E10: 厦门仓：厦门市海沧区港南路336号之30-31号中远海运仓库 联系方式：18060171990 张经理 | K10: 已贴标货物入库
B11: 华南仓 | C11: 广东 | D11: 东莞(明星仓5号仓) | E11: 东莞仓： 东莞市凤岗镇三联村三联路19号 (进园区左手边) 联系方式：17607947904 席经理 | K11: 已贴标货物入库
D12: 福永（明星仓6号仓） | E12: 深圳市宝安区沙井街道和旺一路2号仓库3栋一层（导航：和旺产业园）联系方式: 15096566889 曹经理 | K12: 已贴标货物入库
B14: MRZX-赔偿说明及发货须知 | C14: 点击进入
B15: 明日之星下单渠道明细归类 | C15: 点击进入
B16: MXD-美国华南海派全渠道 | C16: 点击进入报价 | D16: 2026-1-27价格更新 | E16: 分别14/16/18/23天左右提取 | F16: CLX/MAX/EXX/ZIM/OA | H16: 7截3开/7截4开 | I16: 7截3开/7截4开 | J16: 体积/6000
B17: MXD-华南明星达14T卡派 | C17: 点击进入报价 | D17: 2026-1-27价格更新 | E17: 性价比高/16天左右签收 | F17: CLX | H17: 7截3开 | I17: 7截3开 | J17: 体积/6000
B18: MXD-华南明星达16T卡派 | C18: 点击进入报价 | D18: 2026-1-27价格更新 | E18: 性价比高/18天左右签收 | F18: MAX | H18: 7截4开 | I18: 7截4开 | J18: 体积/6000
B19: MXD-华南明星达18T卡派 | C19: 点击进入报价 | D19: 2026-1-27价格更新 | E19: 性价比高/20天左右签收 | F19: EXX/ZEX/HDS3 | H19: 7截4开 | I19: 7截4开 | J19: 体积/6000
B20: MXD-华南明星达20T卡派 | C20: 点击进入报价 | D20: 2026-1-27价格更新 | E20: 性价比高/25天左右签收 | F20: HDS3 | H20: 7截4开 | I20: 7截4开 | J20: 体积/6000
B21: MXD-华南OA普船卡派 | C21: 点击进入报价 | D21: 2026-1-27价格更新 | E21: 性价比高/28天左右签收 | F21: 精品OA-SEA/SEA3 | H21: 7截4开 | I21: 7截4开 | J21: 体积/6000
B22: MXD-华南特惠普船卡派 | C22: 点击进入报价 | D22: 2026-1-27价格更新 | E22: 性价比高/30天左右签收 | F22: SML/HMM/WHL/YMM/TSL/SLS/ONE/CUL统配 | H22: 7截6开 | I22: 2截6开 | J22: 体积/6000
B23: MXD-华南西雅图普船卡派 | C23: 点击进入报价 | D23: 2026-1-27价格更新 | E23: 性价比高/35天左右签收 | F23: OA/SML | H23: 7截2开 | I23: 6截2开 | J23: 体积/6000
B24: MXD-华南奥克兰普船卡派 | C24: 点击进入报价 | D24: 2026-1-27价格更新 | E24: 性价比高/30天左右签收 | F24: EXX航线/CMA/EMC | H24: 7截4开 | I24: 1截4开 | J24: 体积/6000
B25: MXD-华南芝加哥普船卡派 | C25: 点击进入报价 | D25: 2026-1-27价格更新 | E25: 性价比高/35天左右签收 | F25: EXX航线/OA/SML | H25: 7截4开 | I25: 6截4开 | J25: 体积/6000
B26: MXD-华南休斯顿普船卡派 | C26: 点击进入报价 | D26: 2026-1-27价格更新 | E26: 性价比高/35天左右签收 | F26: COSCO | H26: 7截2开 | I26: 6截2开 | J26: 体积/6000
B27: MXD-华南萨凡纳普船卡派 | C27: 点击进入报价 | D27: 2026-1-27价格更新 | E27: 性价比高/40天左右签收 | F27: OA/SML | H27: 7截2开 | I27: 6截2开 | J27: 体积/6000
... B33: MXD-华南全美商私卡 | C33: 点击进入报价 | D33: 2026-1-27价格更新 | E33: 性价比高16/18/20/25/30天左右签收 | F33: CLX/MAX/EXX/ZIM/HDS3/OA | H33: 7截2开 | I33: 5截2开 | J33: 体积/6000
B34: 美国亚马逊常见偏远地址 | C34: 点击进入
B35: 美国海运偏远邮编 | C35: 点击进入
B36: 夏威夷&阿拉斯加邮编无服务 | C36: 点击进入
B37: 美国亚马逊仓库 | C37: 点击进入
B38: 发票模版 | C38: 点击进入

Sheet 价格查询表
E2: =目录!H4 -> 明日之星华南价格表入仓执行日期2025/1/27
B3: 请输入查询仓库
B4: iust
B6: 渠道 | C6: 小货价 | D6: 大货价 | E6: 义乌按方 | F6: 起收重量 | G6: 时效
B7: 华南明星达14T卡派 | C7: {=IFERROR(VLOOKUP("*"&$B$4&"*",INDIRECT("'"&B7&"'!B:K"),{2,3,4,5,6},0),"无")} -> 无
B8: 华南明星达16T卡派 | C8: {=IFERROR(VLOOKUP("*"&$B$4&"*",INDIRECT("'"&B8&"'!B:K"),{2,3,4,5,6},0),"无")} -> 无
B9: 华南明星达18T卡派 | C9: {=IFERROR(VLOOKUP("*"&$B$4&"*",INDIRECT("'"&B9&"'!c:K"),{2,3,4,5,6},0),"无")} -> 10 | D9: 9 | E9: 1800 | F9: 12KG+/1CBM+ | G9: 25-29天左右签收
B10: 华南明星达20T卡派 | C10: {=IFERROR(VLOOKUP("*"&$B$4&"*",INDIRECT("'"&B10&"'!c:K"),{2,3,4,5,6},0),"无")} -> 9.3 | D10: 8.3 | E10: 1660 | F10: 12KG+/1CBM+ | G10: 25-29天左右签收
B11: 华南OA普船卡派 | C11: {=IFERROR(VLOOKUP("*"&$B$4&"*",INDIRECT("'"&B11&"'!c18:K100"),{2,3,4,5,6},0),"无")} -> 8.6 | D11: 7.6 | E11: 1520 | F11: 12KG+/1CBM+ | G11: 27-35天签收
B12: 华南OA卡派直送 | C12: {=IFERROR(VLOOKUP("*"&$B$4&"*",INDIRECT("'"&B11&"'!c11:K12"),{2,3,4,5,6},0),"无")} -> 无
B13: 华南特惠普船卡派 | C13: {=IFERROR(VLOOKUP("*"&$B$4&"*",INDIRECT("'"&B13&"'!C15:K53"),{2,3,4,5,6},0),"无")} -> 8.3 | D13: 7.3 | E13: 1460 | F13: 12KG+/1CBM+ | G13: 27-36天左右签收
B14: 华南特惠普船直送卡派 | C14: {=IFERROR(VLOOKUP("*"&$B$4&"*",INDIRECT("'"&B13&"'!C11:K112"),{2,3,4,5,6},0),"无")} -> 8.3 | D14: 7.3 | E14: 1460 | F14: 12KG+/1CBM+ | G14: 27-36天左右签收
B15: 华南奥克兰普船卡派 | C15: {=IFERROR(VLOOKUP("*"&$B$4&"*",INDIRECT("'"&B15&"'!B:P"),{3,4,5,6,6},0),"无")} -> 无
B16: 华南奥克兰直送卡派 | C16: {=IFERROR(VLOOKUP("*"&$B$4&"*",INDIRECT("'"&B15&"'!C:P"),{3,4,5,6,7},0),"无")} -> 无
B17: 华南芝加哥普船卡派 | C17: {=IFERROR(VLOOKUP("*"&$B$4&"*",INDIRECT("'"&B17&"'!C11:P100"),{2,3,4,5,6},0),"无")} -> 无
B18: 华南芝加哥普船直送卡派 | C18: {=IFERROR(VLOOKUP("*"&$B$4&"*",INDIRECT("'"&B17&"'!C9:P10"),{2,3,4,5,6},0),"无")} -> 无
B19: 华南纽约海铁卡派 | C19: {=IFERROR(VLOOKUP("*"&$B$4&"*",INDIRECT("'"&B19&"'!B:K"),{2,3,4,5,6},0),"无")} -> 10 | D19: 9 | E19: 1800 | F19: 12kg+/1CBM | G19: 25-30天左右签收
B20: 华南纽约普船卡派 | C20: {=IFERROR(VLOOKUP("*"&$B$4&"*",INDIRECT("'"&B20&"'!B:K"),{2,3,4,5,6},0),"无")} -> 6.4 | D20: 5.4 | E20: 1080 | F20: 12kg+/1CBM | G20: 40-45天左右签收
B21: 华南纽约经济普船卡派 | C21: {=IFERROR(VLOOKUP("*"&$B$4&"*",INDIRECT("'"&B21&"'!B:K"),{2,3,4,5,6},0),"无")} -> 6.3 | D21: 5.3 | E21: 1060 | F21: 12kg+/1CBM | G21: 42-48天左右签收
B22: 华南萨凡纳普船卡派 | C22: {=IFERROR(VLOOKUP("*"&$B$4&"*",INDIRECT("'"&B22&"'!B:K"),{2,3,4,5,6},0),"无")} -> 无
B23: 华南休斯顿普船卡派 | C23: {=IFERROR(VLOOKUP("*"&$B$4&"*",INDIRECT("'"&B23&"'!C:K"),{2,3,4,5,5},0),"无")} -> 无
B24: 华南西雅图普船卡派 | C24: {=IFERROR(VLOOKUP("*"&$B$4&"*",INDIRECT("'"&B24&"'!B:K"),{2,3,4,5,6},0),"无")} -> 无

Sheet 船期表
A1: 浙江明日之星供应链管理有限公司(深圳分公司）
A2: 美线船期计划表(预计船期，请以实际开船到港时间为准）
K3: =目录!H4 -> 明日之星华南价格表入仓执行日期2025/1/27
A5: 产品渠道 | B5: 船公司 | C5: 航线 | D5: 船名航次 | E5: 始发港 | F5: 目的港 | G5: ETD船期 | H5: ETA时间 | I5: 航程 | J5: 到货日期 | K5: 下一水预配船期 | L5: 报关行信息
A6: 华南-明星达卡派14T/海派14T | B6: 美森 | C6: CLX | D6: KAIMANA HILA 070E | E6: 宁波 | F6: 长滩 | G6: 46055 | H6: 46068 | I6: 11 | J6: 46053 | K6: LURLINE 097E 预计开船时间 2-9 | L6: 义乌市乐通报关代理有限公司 海关代码331898008Q
A7: 华南-明星达海卡 16T/海派16T | B7: 美森 | C7: MAX | D7: MATSON MAUI 035E | E7: 宁波 | F7: 长滩 | G7: 46056 | H7: 46069 | I7: 11 | J7: 46053 | K7: MATSON LANAI 052E 预计开船时间 2-10 | L7: 义乌市乐通报关代理有限公司 海关代码331898008Q
A8: 华南-明星达18T/海派18T | B8: 以星 | C8: ZEX | D8: COLORADO 14E | E8: 盐田 | F8: 洛杉矶 | G8: 46057 | H8: 46070 | I8: 12.5 | J8: 46054 | K8: ZIM MOONSTONE5E 预计开船时间 2-11 | L8: 深圳市一路通达报关服务有限公司 海关代码4403980A0V
B9: 合德快提 | C9: HDS3 | D9: PORTO 2602E | E9: 南沙 | F9: 洛杉矶 | G9: 46057 | H9: 46071 | I9: 14 | J9: 46054 | K9: PONTRESINA 2602E 预计开船时间2-11 | L9: 广州华博国际货运有限公司 海关代码4430980A74
A10: 华南-明星达海卡 20T/海派20T | B10: 合德普提 | C10: HDS3 | D10: PORTO 2602E | E10: 南沙 | F10: 洛杉矶 | G10: 46057 | H10: 46071 | I10: 14 | J10: 46054 | K10: PONTRESINA 2602E 预计开船时间2-11 | L10: 广州华博国际货运有限公司 海关代码4430980A74
A11: 华南-OA普船卡派/海派 | B11: 中远 | C11: SEA | D11: COSCO SHIPPING DENALI 051E | E11: 盐田 | F11: 长滩 | G11: 46058 | H11: 46075 | I11: 15 | J11: 46054 | K11: COSCO SPAIN 077E 预计开船时间 2-12 | L11: 深圳市一路通达报关服务有限公司 海关代码4403980A0V
B12: 中远 | C12: SEA3 | D12: OOCL ROTTERDAM 161E | E12: 盐田 | F12: 长滩 | G12: 46063 | H12: 46077 | I12: 14 | J12: 46059 | K12: OOCL UTAH 082E 预计开船时间 2-17 | L12: 深圳市一路通达报关服务有限公司 海关代码4403980A0V
B13: 长荣 | C13: HTW | D13: EVER MAGUS 1439-005E | E13: 盐田 | F13: 洛杉矶 | G13: 46062 | H13: 46076 | I13: 13 | J13: 46059 | K13: EVER MAGNA 1440-003E 预计开船时间 2-17 | L13: 深圳市一路通达报关服务有限公司 海关代码4403980A0V
A14: 华南-特惠线普船卡派 | B14: WHL | C14: AP1 | D14: WAN HAI A05 E014 | E14: 蛇口 | F14: 洛杉矶 | G14: 46064 | H14: 45715 | I14: 18 | J14: 46059 | K14: HYUNDAI NEPTUNE 042E 预计开船时间 2-19 | L14: 深圳市一路通达报关服务有限公司 海关代码4403980A0V
A15: 华南-西雅图普船卡派 暂停本渠道 | B15: YML | C15: PN1 | D15: / | E15: 宁波 | F15: 塔科马 | G15: / | H15: / | I15: / | J15: / | K15: / | L15: /
A16: 华南-奥克兰普船卡派 | B16: 长荣 | C16: HTW | D16: EVER MAGUS 1439-005E | E16: 盐田 | F16: 洛杉矶 | G16: 46062 | H16: 46081 | I16: 20 | J16: 46059 | K16: EVER MAGNA 1440-003E 预计开船时间 2-17 | L16: 深圳市一路通达报关服务有限公司 海关代码4403980A0V
A17: 华南-芝加哥普船卡派 （OA/EXX/ZIM/SML统配） | B17: 达飞 | C17: EXX | D17: CMA CGM TARPON 0GVLUE1MA | E17: 上海 | F17: 芝加哥 | G17: 46058 | H17: 46079 | I17: 21 | J17: 46054 | K17: CMA CGM SWORDFISH 0GVLWE1MA 预计开船时间 2-12 | L17: 义乌市乐通报关代理有限公司 海关代码331898008Q
B18: 长荣 | C18: HTW | D18: EVER MAGUS 1439-005E | E18: 盐田 | F18: 洛杉矶 | G18: 46062 | H18: 3月3 | I18: 24 | J18: 46059 | K18: EVER MAGNA 1440-003E 预计开船时间 2-17 | L18: 深圳市一路通达报关服务有限公司 海关代码4403980A0V
B19: 以星 | C19: ZX2 | D19: PELICAN I 10E | E19: 宁波 | F19: 芝加哥 | G19: 46058 | H19: 46076 | I19: 18 | J19: 46054 | K19: GANGES 16E 预计开船时间 2-12 | L19: 义乌市乐通报关代理有限公司 海关代码331898008Q
A20: 华南-休斯顿普船卡派 | B20: COSCO | C20: GME | D20: XIN DA YANG ZHOU 106E | E20: 盐田 | F20: 休斯顿 | G20: 46063 | H20: 46087 | I20: 26 | J20: 46058 | K20: XIN YA ZHOU174E 预计开船时间 2-16 | L20: 深圳市一路通达报关服务有限公司 海关代码4403980A0V
A21: 华南-萨凡纳普船卡派 | B21: COSCO | C21: AWE3 | D21: EVER MAST 1344-009E | E21: 盐田 | F21: 萨凡纳 | G21: 46062 | H21: 46093 | I21: 31 | J21: 46058 | K21: EVER MACRO 1345-007E 预计开船时间 2-16 | L21: 深圳市一路通达报关服务有限公司 海关代码4403980A0V
A22: 华南-纽约经济普船卡派 | B22: ZIM | C22: ZXB | D22: ZIM SCORPIO 8E | E22: 盐田 | F22: 纽约 | G22: 46060 | H22: 46092 | I22: 32 | J22: 46056 | K22: ZIM CORAL 10E 预计开船时间 2-11 | L22: 深圳市一路通达报关服务有限公司 海关代码4403980A0V
A23: 华南-纽约普船卡派 | B23: COSCO | C23: AWE4 | D23: 072E OOCL Egypt | E23: 盐田 | F23: 纽约 | G23: 46061 | H23: 46091 | I23: 30 | J23: 46057 | K23: OOCL LILAC 003E 预计开船时间 2-15 | L23: 深圳市一路通达报关服务有限公司 海关代码4403980A0V
A24: 报关行——深圳市一路通达报关服务有限公司 海关代码4403980A0V 出境关别 ：5316（大鹏海关） 离境口岸：470601（盐田）
A25: 报关行——深圳市一路通达报关服务有限公司 海关代码4403980A0V 出境关别 ：5304（蛇口海关） 离境口岸：选择SCT（蛇口）
A26: 报关行——广州华博国际货运有限公司 海关代码4430980A74 出境关别 ：5166（南沙新港） 离境口岸：443404一期/443405二期/443417三期
A27: 报关行——义乌市乐通报关代理有限公司 海关代码331898008Q 出境关别：2225（上海），离境口岸：外高桥（310701） 离境口岸：宁波北仑港港区（380101） 出境关别：3104（北仑）
A28: 报关行——易豹网络科技有限公司 海关代码3302480076 出境关别：2225（上海）离境口岸：外高桥（310701） 离境口岸：宁波北仑港港区（380101） 出境关别：3104（北仑）

Sheet MXD-赔偿说明及发货须知
B4: 赔偿标准和免赔声明 | N4: =目录!H4 -> 明日之星华南价格表入仓执行日期2025/1/27
B6: 一、时效赔付界定：以不同渠道时效说明为准 | J6: 美国专线发货须知
B8: 二、时效免赔说明 | J8: 发 货 须 知
B10: 1、船公司船期/航线变更/延迟到港，自然灾害、天气原因，如台风、地震、洪水、冰雹,，暴风雪，雾；政府行为，社会异常事件包括战争，罢工等； | J10: 1、以上价格为普货产品到最终Amazon仓库的全部价格。
B11: 2、海关查验； | J11: 2、FBA货物每件货物需贴2个以上合格的FBA标签,货物尺寸
B12: 3、亚马逊拒收或者亚马逊更改预约时间； | J12: 3、此价格只收普货。带电产品只接内置纽扣电池 仿牌，液体，粉末，美国对华反倾销产品等敏感货物不接。不接收食品类，医疗类产品类，汽车灯、化妆品类（含纹身美妆产品），电子烟及烟草相关产品，动物皮毛制品类，激光产品类，成人用品类，管制刀具和警棍、电棒类，植物种子类，强磁类（磁铁、冰箱贴等），灭蚊、捕鼠、杀虫类产品，杂志书籍出版物，如发现冲货或者带电不备注行为没收货物并罚款RMB1000-RMB50000元：不接收原木
B13: 4、亚马逊爆仓及预约困难； | J13: 4、海关要求如实申报，否则造成延误和丢失以及扣关我司一概不负责
B14: 5、客户FBA ID & 内部编码失误等相关原因； | J14: 5、订舱需提供出货模块资料，模块资料需提供详细品名，海关编码，材质，用途
B15: 6、客户要求扣货后派送或者因客户自身原因导致的延误； | J15: 6、因客户，亚马逊，UPS等海外服务商原因产生海外退件，退件运费及相关退件费用将无条件由发件人支付
B16: 7、由于疫情，国内仓库无法出货，船公司卸船效率慢，预约困难，拒收等不可抗力导致的延迟交仓,不在赔偿范围,此项如与具体渠道的时效赔付标准有区分，则与具体渠道的标准为准； | J16: 7、资料要求：按要求提供货物的真实信息，提供准确的美国的海关编码，如不能提供准确的美国的海关编码,我司清关行会根据实际品名,材质和用途申报，最终产生的关税以海关提供的税金单为准，不得争议。实际货物必须如实申报，货物信息要与发票资料一致，不可瞒报漏报（例如：有牌子申报无牌）和申报不符，如因申报不符导致海关扣货等后果及产生的所有费用由发货人承担
J17: 8、儿童用品出货标准： 1.儿童用品，限时达渠道不接，其他渠道必须提供cpc、cpsc、英文标签。 2.如遇海关查验，产品与认证问题导致后果，以海关查验处理为最终依据，如产生罚款，客人承担。 3.如因产品或认证问题，导致的产品罚没，我司不承担任何责任；如被海关销毁，销毁费用及罚款由客人承担；罚没或销毁无赔偿。 (注：目前国内外海关对于儿童用品进行布控，查验率增加，一旦被海关查验，查验的周期会非常久，望慎重）
B18: 三、赔偿标准（所有赔偿只有一种，不能多种赔偿同时赔付）
B20: 1、在运输过程中如是我司原因导致货物丢失，损坏,经我司确认后按货物申报货值赔偿，最高不超40RMB/KG赔偿，不免相关物流费用。理赔需要提供采购发票等相关资料，以便对货值的合理性进行评估。即40RMB/KG，采购货值，申报货值三者取低赔偿 ；
B21: 2、高货值产品及易碎品建议客人购买保险并打好包装，我司亦可提供购买保险服务；如若在运输过程中出因现包装原因而造成的损失而客人没有购买保险，我司概不负责； | J21: 9、根据现场查验情况，海关针对电池产品(充电宝，锂电池组，储能电源，工具电池，蓄电池等纯电产品)以及电动车类产品(电动滑板车，电动自行车，平衡车等)开展专项指令查验，如遇. 上述产品查验布控指令带“核验是否含有电池等维修货物”、“核验危险品”、“取样送检”等指令,查验需要核查产品上的标签标识是否合格、运输包装是否合格,核验是否有相关检测证书，是否提前规范申报危险品货物信息;并且会有.上报海事部门的风险，还可能会暂扣相关货物送检。由此可能会影响到整个柜子的放行时间，请大家合理安排此类产品的出货计划，避免不必要的损失。凡遇到相关布控指令，我司不承担相关查验费用。（*带电池产品，提供MSDS+货物鉴定书给报关行，报关行给船公司审核，审核通过后可以出）
B22: 3、卡派货交亚马逊仓库，POD（预约号与FBA ID无法对应），但是整票未上架的，我司接受理赔申请，赔偿金额按照我司合同条款 ；（不包括FBA号过期导致的亚马逊拒收和不上架 ；FBA号过期后客户仍然要求我们派送，导致的亚马逊拒收和不上架） | J22: 10、如美国海关认定货物涉及品牌侵权或蓝牙、HDMI、FCC、UL、FDA,DOT，EPA等认证问题，客户需按要求提供相关认证和品牌授权书等文件，如因无法提供或者提供的文件得不到美国海关及相关部门的认可而导致扣货或者退运，所有责任和费用由该发货人承担
B23: 4、快递货交私人仓库/商业地址/亚马逊仓库，如若是整票未提取，我司接受理赔申请，赔偿金额按照我司合同条款（不包括FBA号过期导致的亚马逊拒收和不上架 ；FBA号过期后客户仍然要求我们派送，导致的亚马逊拒收和不上架）； | J23: 11、此上包含海关查验及查验引起的费用（含查验费指普通进口美国查验产生的费用，查验结果最后海关放行且不产生扣货/退运等结果的普通查验费。若查验原因是因为客户的产品及相关证明文件引起的海关查验、扣货、退运等结果产生的所有相关费用由发货方承担)及亚马逊爆仓引起的仓租/柜租以及亚马逊拒收产生的相关费用； 不可抗力因素造成的时效延误不在赔偿范围内，如（包括但不限于）：自然灾害、如台风、地震、洪水、冰雹,，暴风雪；政府行为，社会异常事件，如罢工、码头停摆，骚乱三方面，疫情原因等。如因报关资料问题引起的出口查验由客户承担所有相关费用（如仓租，柜租，改船费等）
B24: 5、快递货交私人仓库/商业地址/亚马逊仓库，快递显示部分未提取+部分已经签收，收货人反馈未收到货物或收到部分货物，我司能够接受理赔，但是私人仓库和商业地址需要签收人提供相应的情况说明书签字（需要显示个人Passport No.）； | J24: 12、以下情况，我司会协助处理，不承担任何责任 A.产品如需要FCC,CE,FDA,TSCA,DOT，CPSC,CPC，EPA等认证而客户无法提供有效证明及文件，导致海关扣货等后果 B.产品不符合美国当地法规的，如反倾销，侵权且无法提供有效证及及文件，导致海关扣货等后果 如因以上情况而产生的退运，销毁，仓租等一切费用，由发货方自行承担
B25: 6、卡派货交亚马逊仓库，POD（预约号与FBA ID无法对应），但是部分上架或部分不上架，未上架部分我司根据具体情况给出处理方案。如若确认理赔，赔偿金额按照我司合同条款标准（不包括FBA号过期导致的亚马逊拒收和不上架 ；FBA号过期后客户仍然要求我们派送，导致的亚马逊拒收和不上架）；丢件赔偿标准如下： 一.快递派标准 （1） 提取前任何形式的丢件 按货值赔偿（提供货值证明）最高不超过40/kg 不退运费 （2）提取上网后丢件 统一按照每件100美金赔偿 不退运费 二.卡派标准 （包含任何形式的丢件） （1）按公斤计费的丢件 按货值赔偿（提供货值证明）最高不超过40RMB/kg 不退运费 （2）按方计费的丢件 按货值赔偿（提供货值证明）最高不超过600RMB/件 不退运费 | J25: 13、请留意，按照美国海关要求，所有中国出口美国货物的外包装及货物内包装（或者货物本身）必须有MADE IN CHINA的标记，否则一旦被查到将会被要求在美国海关的监管下逐件贴标，限期未完成者将会被处以至少为发票金额的6倍的罚款，由此导致的时效延误及一切费用概由客户承担
J26: 14、P.O.BOX军方地址不接（以上价格不含阿拉斯加，夏威夷，波多黎各，关岛及各岛屿，以上城市来电询价）
J27: 15、如亚马逊拒收货件，私人地址拒收货物，产生的退回运费以及其他任何额外费用，客户自理,因客户产品问题导致海关扣关，我司会负责协助清关处理，但不承担任何责任
J28: 16、因美国本地费用变化频繁且即时生效，我司保留即时更改价格的权利（包括在途中的货物）
J29: 特别提示：如客户一旦交货到我司，我司默认为客户已详细阅读过此价格表备注内容及其说明，并接受其条款的约束。 最终解释权归本司所有
B31: 四、免赔声明 | J31: 拒接违禁品
B33: 1、 货物本身侵权问题，货物没按实际价值申报问题、当地禁止进口问题，货物本身质量问题以及涉及到具体的认证问题等导致的海关查验、扣货、退运等情况; | J33: 1、易爆物品：如烟火制品（礼花、鞭炮、摔炮、拉炮等）发令纸、干冰、打火机、煤气炉、煤气罐、火柴、火药，点火器等
B34: 2、如遇自然灾害（火灾、水灾、地震等）或当地罢工等不可抗因素导致货物丢失的； | J34: 2、气体、粉末状物品（有刺激异味伤害皮肤的化工粉末）、膏状物品（如锡膏等）、白色晶状物品
B35: 3、外包装无损情况下，内包装产品数量缺少、部份丢失/损坏； | J35: 3、液体(不论是否易燃)：如汽油、煤油、柴油、苯、酒精、油漆、涂料、油墨、去光液等化学液体
B36: 4、尾端快递派免赔说明： *货交私人仓库/商业地址，快递已经全部显示签收，但是反馈并未收到货物/ 部分未签收； *货交私人仓库/商业地址，快递显示部分递送中+部分已经签收，收货人反馈未收到货物或收到部分货物 *货交私人仓库/商业地址，签收后以签收单上面标注的为准（例如标注了少货或货损），我司协助推进快递服务商开查，不承担其它责任。 *货交亚马逊仓库，快递已经全部显示签收，但是客户亚马逊后台未上架 **货交亚马逊仓库，快递显示部分递送中+部分已经签收，客户反馈亚马逊后台未上架 （递送中迟迟未更新状态） | J36: 4、易燃固体、自燃物品和遇湿易燃物品：如煤、松香、石蜡、活性碳、白磷、黄磷、油麻、金属钠、镁铝粉、锂电、蓄电池等
J37: 5、化学品：如氧化氢、过氧化钠、次氯酸钙、氯酸钾、硝酸钾、不明化学物品等
J38: 6、毒害品和感染性物品。指在流通过程中容易发生中毒和感染的物品 ，如杀虫剂、灭草剂、砷及其化合物、汞及其化合物、氰及其化合物、哥罗芳、苯铵、生漆、血液、尿液、体液、炭疽、危险性病菌等
J39: 7、腐蚀品，能灼烧人体组织，并对金属等物品造成损坏的固体和液体 ，如硫酸、硝酸、 盐酸、氯磺酸、冰醋酸、烧碱、双氧 等
B40: 5. 尾端卡派免赔说明： *私人仓库/商业地址，卡派POD已经显示签收，但是反馈并未收到货物/ 部分未签收； *私人仓库/商业地址，签收后签收单上面未注明有少货或货损 *货送亚马逊，有签名的POD，同一票货，部分货物已经上架不再接受理赔. | J40: 8、化妆品、护肤品、洗漱用品，食品，药品（如牙膏、洗面乳、 护手霜、沫浴露、洗发水等）
J41: 9、各种货币；
B42: 6、申请UPS/FEDEX索赔期限及规则：追诉期从打单之日起算100个自然日内，且快递轨迹停更之日起算45个自然日内，同时满足两个条件可发起开查申请，逾期将不予以受理开查申请，产生的相应责任及损失由客户自行承担。船期超过50天以上的，将在目的港更换UPS面单。 ①未提取的 ，快递官方不受理索赔申请，请按“五、申请索赔期限及规则”中第2条标准处理；②若提取后迟迟未有动态，请在快递轨迹停更后7个工作日向我司客服人员发起开查申请，同时提供快递开查相关资料，最晚发起时间应当在快递轨迹停更之日(含停更当天)起45个自然日内提供完整资料，逾期我司将不再接受理赔申请。 申请索赔需要提供如下资料：①已提取未有动态的：开查的UPS/FEDEX模板+INV+未上架截图(需带有电脑屏幕右下角当下真实时间)；②未提取的：未提取开查表+未上架截图(需带有电脑屏幕右下角当下真实时间) （索赔资料可能会有变动，具体以我司/快递公司要求为准） 注：若逾期未提供完整相应索赔资料导致超期申请索赔，则相应责任由客户自行承担，我司不再接受理赔申请。 | J42: 10、容易腐烂的物品
J43: 11、仿牌商品
J44: 12、医疗用品
J45: 13、各类食品
B46: 7、漏报关赔偿：按3倍报关费赔偿，则3*350元 | J46: 14、各类放射性元素及容器
B47: 8、如出现未上架情况，请按要求提供相关资料进行索赔，如未上架截图，形式发票/装箱单/采购发票等 | J47: 15、各类武器、弹药或者盛装的容器，
J48: 16、管制器具：任何刀刃超过9CM的刀具，或者具备人身攻击的用品
B49: 五、申请索赔期限及规则： | J49: 17、贵金属或者高价值无牌
J50: 18、点火器，打火器
B51: 1、卡派索赔程序：请客户在签收后10个工作日内查询FBA后台是否上架，签收后30天内提供货物未上架后台截图(需带有电脑屏幕右下角当下真实时间)至我司方可进入索赔程序，超过60个工作日未提供完整资料的，我司将不再接受理赔申请；
B52: 2、快递派索赔程序： ①未提取的，请在打单日起算最早第30个自然日向我司客服人员发起开查申请，同时提供快递开查相关资料，最晚发起时间应当在打单日（含打单当天）起第60个自然日内提供完整资料，逾期我司将不再接受理赔申请。 ②已提取未签收的以快递开查结果为准，不在我司索赔责任范围内； 注：若逾期未提供完整相应索赔资料，则相应责任由客户自行承担，我司不再接受理赔申请。 | J52: 美国出货部分货物所需认证
J54: 认证 | L54: 范围 | N54: 监管部门/机构 | O54: 图标 | Q54: 范例
J55: FCC | L55: 电子产品 | N55: 美国联邦通信委员会 | O55: =_xlfn.DISPIMG("ID_8D91B8F11D73406ABD751062014F6BCC",1) -> =DISPIMG("ID_8D91B8F11D73406ABD751062014F6BCC",1) | Q55: 通信电源、开关电源、充电器、显示器电源、LED电源、LCD电源、不间断电源UPS 蓝牙BT产品、平板电脑、无线键盘、无线鼠标、无线读写器、无线收发器、无线对讲机，手机，无线操控设备或者无牌
J56: FDA | L56: 食品、化妆品、药物、生物制剂、医疗设备和放射产品 | N56: 美国食品和药物管理局 | O56: =_xlfn.DISPIMG("ID_AA0128AE29C44DEAA98A2FC10B96C2E1",1) -> =DISPIMG("ID_AA0128AE29C44DEAA98A2FC10B96C2E1",1) | Q56: 食品、药品（包括兽药）、带激光类的产品；医疗器械、食品添加剂、化妆品、动物食品及药品、 酒精含量低于7％的葡萄酒饮料以及电子产品的监督检验
J57: CPC | L57: 儿童用品 | N57: 美国消费品安全委员会 | O57: =_xlfn.DISPIMG("ID_E2682683CC0742A893980876872F70A8",1) -> =DISPIMG("ID_E2682683CC0742A893980876872F70A8",1) | Q57: 玩具产品 儿童用品，儿童护理产品 婴儿奶嘴或杯子，各类消费品 各类专门用于12周岁以下的儿童用品
J58: DOT | L58: 各种机动交通工具及其零部件 | N58: 美国交通部 | O58: =_xlfn.DISPIMG("ID_BA0AC3C66741485D99C67E316E3A31E2",1) -> =DISPIMG("ID_BA0AC3C66741485D99C67E316E3A31E2",1) | Q58: 车 辆：摩托车、电动车、客车、卡车、公共汽车、拖车、挂车等; 零配件：车辆灯具、灯泡、反射器、后视镜、制动软管、轮胎、轮辋、三角警示牌、儿童安全座椅、汽车安全带、玻璃、摩托车安全帽、后保险杠等。
J59: UL/ETL | L59: 电气、电子设备、机械产品、灯具、建材、防火器材及化学品及家用电器 | N59: UL实验室/天祥实验室 | O59: =_xlfn.DISPIMG("ID_E1BE6DC002D5465C895859D261A9E88A",1) -> =DISPIMG("ID_E1BE6DC002D5465C895859D261A9E88A",1) | Q59: 视听设备，汽车，电子元器件，家用电器工业控制设备，信息技术设备 灯具，医疗器械 资讯设备，电线电缆
J60: UL/ETL | O60: =_xlfn.DISPIMG("ID_AC64653285DC455D828952CC6327259E",1) -> =DISPIMG("ID_AC64653285DC455D828952CC6327259E",1)
J61: EPA | L61: 气体排放设备，杀消毒产品.有毒有害产品 | N61: 美国环境保护署 | O61: =_xlfn.DISPIMG("ID_6FE9DA6579CC4929A3838C222F96DD96",1) -> =DISPIMG("ID_6FE9DA6579CC4929A3838C222F96DD96",1) | Q61: 柴油 / 汽油发动机设备、零售汽车部件气体、水处理设备、 农药，LED灭菌灯，紫外线杀菌灯等
J62: BQB | L62: 蓝牙产品 | N62: 蓝牙认证团体 | O62: =_xlfn.DISPIMG("ID_E82205A3DF1D4A5981DAB1AC70B76697",1) -> =DISPIMG("ID_E82205A3DF1D4A5981DAB1AC70B76697",1) | Q62: 蓝牙耳机,蓝牙音箱，手机等

Sheet 明日之星下单渠道明细归类
H3: =目录!H4 -> 明日之星华南价格表入仓执行日期2025/1/27
B4: 浙江明日之星供应链管理有限公司(深圳分公司）
B6: 明日之星下单渠道明细归类
B8: 序号 | C8: 下单渠道名 | D8: 船司 | E8: 参考时效：开船后 | G8: 序号 | H8: 下单渠道名 | I8: 船司 | J8: 参考时效：开船后
B9: 1 | C9: MXD-华南明星达海派14T | D9: MATSON-CLX | E9: 11-14天提取 | G9: 28 | H9: MXD-华南普船特惠线海派 | I9: SML/CUL/OA | J9: 25-28天入仓
B10: 2 | C10: MXD-华南明星达卡派14T | D10: MATSON-CLX | E10: 13-15天入仓 | G10: 29 | H10: MXD-华南普船特惠线卡派按方包税 | I10: SML/CUL/OA | J10: 25-28天入仓
B11: 3 | C11: MXD-华南明星达14T私人卡派 | D11: MATSON-CLX | E11: 提柜之后3-5天 | G11: 30 | H11: MXD-华南普船特惠线留仓自提 | I11: SML/CUL/OA | J11: 提柜之后3-5天
B12: 4 | C12: MXD-华南明星达14T留仓自提 | D12: MATSON-CLX | E12: 提柜之后3-5天 | G12: 31 | H12: MXD-华南普船特惠线私人卡派 | I12: SML/CUL/OA | J12: 提柜之后3-5天
B13: 5 | C13: MXD-华南明星达14T按方卡派 | D13: MATSON-CLX | E13: 13-15天入仓 | G13: 32 | H13: MXD-华南西雅图普船私卡 | I13: SML | J13: 提柜之后5-7天
B14: 6 | C14: MXD-华南明星达海派16T | D14: MATSON-MAX | E14: 12-15天提取 | G14: 33 | H14: MXD-华南西雅图普船卡派 | I14: SML | J14: 35-40天入仓
B15: 7 | C15: MXD-华南明星达卡派16T | D15: MATSON-MAX | E15: 14-16天入仓 | G15: 34 | H15: MXD-华南西雅图普船按方包税 | I15: SML | J15: 35-40天入仓
B16: 8 | C16: MXD-华南明星达16T私人卡派 | D16: MATSON-MAX | E16: 提柜之后3-5天 | G16: 35 | H16: MXD-华南西雅图普船留仓自提 | I16: SML | J16: 提柜之后5-7天
B17: 9 | C17: MXD-华南明星达16T留仓自提 | D17: MATSON-MAX | E17: 提柜之后3-5天 | G17: 36 | H17: MXD-华南奥克兰普船私卡 | I17: CMA/EMC | J17: 提柜之后5-7天
B18: 10 | C18: MXD-华南明星达16T按方卡派 | D18: MATSON-MAX | E18: 12-15天提取 | G18: 37 | H18: MXD-华南奥克兰普船卡派 | I18: CMA/EMC | J18: 25-30天入仓
B19: 11 | C19: MXD-华南明星达海派18T | D19: CMA/ZIM | E19: 13-16天提取 | G19: 38 | H19: MXD-华南奥克兰普船按方包税 | I19: CMA/EMC | J19: 25-30天入仓
B20: 12 | C20: MXD-华南明星达卡派18T | D20: CMA/ZIM | E20: 15-18天入仓 | G20: 39 | H20: MXD-华南奥克兰普船留仓自提 | I20: CMA/EMC | J20: 提柜之后5-7天
... B35: 27 | C35: MXD-华南普船特惠线直送卡派 | D35: SML/CUL/OA | E35: 26-33天入仓 | G35: 54 | H35: MXD-华南纽约普船按方包税 | I35: COSCO | J35: 40-45天入仓
G36: 55 | H36: MXD-华南纽约普船留仓自提 | I36: COSCO | J36: 提柜之后5-7天
G37: 53 | H37: MXD-华南经济纽约普船卡派 | I37: ZIM | J37: 42-48天入仓
G38: 54 | H38: MXD-华南经济纽约普船按方包税 | I38: ZIM | J38: 42-48天入仓
G39: 55 | H39: MXD-华南经济纽约普船留仓自提 | I39: ZIM | J39: 提柜之后5-7天

Sheet MXD-华南海派全渠道
F2: =目录!H4 -> 明日之星华南价格表入仓执行日期2025/1/27
B4: 浙江明日之星供应链管理有限公司(深圳公司）
B6: 华南OA普船海派 （盐田 精品COSCO SEA/SEA3航线)
B7: 100KG+泡重比优惠：1:140减0.5、1:110减1、1:80减1.5
B8: 100KG+实重比优惠：1:190减0.5、1:290减1、1:390减1.5、1:500及以上减2
B9: 国家 | C9: 东莞仓(明星仓5号）福永仓（明星仓6号） | F9: 备注
C10: 12KG+ | D10: 51KG+ | E10: 100KG+
B11: 美东（USE） 邮编0,1,2,3 | C11: 14.9 | D11: 10.9 | E11: 9.9 | F11: 参考时效：开船后25-28天提取 联邦和UPS随机打单 | G11: 报关费：150/票 不同渠道不能合并报关 | H11: 非亚马逊地址+1 偏远3/KG 超偏远4/KG 超极偏远5/KG，如需指定打单+5
B12: 美中（USM） 邮编4,5,6,7 | C12: 14.4 | D12: 10.4 | E12: 9.4
B13: 美西（USW） 邮编8,9 | C13: 12.4 | D13: 8.4 | E13: 7.4
B15: 华南明星达20T海派（精品HDS3航线）
B16: 100KG+泡重比优惠：1:140减0.5、1:110减1、1:80减1.5
B17: 100KG+实重比优惠：1:190减0.5、1:290减1、1:390减1.5、1:500及以上减2
B18: 国家 | C18: 东莞仓(明星仓5号）福永仓（明星仓6号） | F18: 备注
C19: 12KG+ | D19: 51KG+ | E19: 100KG+
B20: 美东（USE） 邮编0,1,2,3 | C20: 15.9 | D20: 11.9 | E20: 10.9 | F20: 1、如遇海关查验，在承诺时效内，不做赔偿;超出承诺时效，退0.5元/KG。其他不可抗力因素无赔偿(如船坏，码头罢工，UPS/FEDEX爆仓等） 2、时效承诺:开船后第二天开始算，21天提取(如遇船舶晚开，晚到港，节假日顺延) 。超21天每天赔付0.5元/kg，最高赔付3元，当天提取不计赔付 | G20: 报关费：150/票 不同渠道不能合并报关 | H20: 非亚马逊地址+1 偏远3/KG 超偏远4/KG 超极偏远5/KG，如需指定打单+5
B21: 美中（USM） 邮编4,5,6,7 | C21: 15.4 | D21: 11.4 | E21: 10.4
B22: 美西（USW） 邮编8,9 | C22: 13.4 | D22: 9.4 | E22: 8.4
B26: 华南明星达18T海派（精品EXX/HDS3快提/ZEX快船航线）
B27: 100KG+泡重比优惠：1:140减0.5、1:110减1、1:80减1.5
B28: 100KG+实重比优惠：1:190减0.5、1:290减1、1:390减1.5、1:500及以上减2
B29: 国家 | C29: 东莞仓(明星仓5号）福永仓（明星仓6号） | F29: 备注
C30: 12KG+ | D30: 51KG+ | E30: 100KG+
B31: 美东（USE） 邮编0,1,2,3 | C31: 16.9 | D31: 12.9 | E31: 11.9 | F31: 1、如遇海关查验，在承诺时效内，不做赔偿;超出承诺时效，退0.5元/KG。其他不可抗力因素无赔偿(如船坏，码头罢工，UPS/FEDEX爆仓等） 2、时效承诺:开船后第二天开始算，19天提取(如遇船舶晚开，晚到港，节假日顺延) 。超19天每天赔付0.5元/kg，最高赔付3元，当天提取不计赔付 | G31: 报关费：150/票 不同渠道不能合并报关 | H31: 非亚马逊地址+1 偏远3/KG 超偏远4/KG 超极偏远5/KG，如需指定打单+5
B32: 美中（USM） 邮编4,5,6,7 | C32: 16.4 | D32: 12.4 | E32: 11.4
B33: 美西（USW） 邮编8,9 | C33: 14.4 | D33: 10.4 | E33: 9.4
B35: 华南明星达16T海派 (美森MAX航线）
B36: 100KG+泡重比优惠：1:140减0.5、1:110减1、1:80减1.5
B37: 100KG+实重比优惠：1:190减0.5、1:290减1、1:390减1.5、1:500及以上减2
B38: 国家 | C38: 东莞仓(明星仓5号）福永仓（明星仓6号） | F38: 备注
C39: 12KG+ | D39: 51KG+ | E39: 100KG+
B40: 美东（USE） 邮编0,1,2,3 | C40: 18.8 | D40: 14.8 | E40: 13.8 | F40: 1、如遇海关查验，在承诺时效内，不做赔偿;超出承诺时效，退0.5元/KG。其他不可抗力因素无赔偿；(如船坏，码头罢工，UPS/FEDEX爆仓等） 2、时效承诺:开船后第二天开始算，17天提取(如遇船舶晚开，晚到港，节假日顺延) 。超17天每天赔付0.5元/kg，最高赔付3元，当天提取不计赔付 | G40: 报关费：150/票 不同渠道不能合并报关 | H40: 非亚马逊地址+1 偏远3/KG 超偏远4/KG 超极偏远5/KG，如需指定打单+5
B41: 美中（USM） 邮编4,5,6,7 | C41: 18.3 | D41: 14.3 | E41: 13.3
B42: 美西（USW） 邮编8,9 | C42: 16.3 | D42: 12.3 | E42: 11.3
B44: 华南明星达14T海派(美森CLX航线）
B45: 100KG+泡重比优惠：1:140减0.5、1:110减1、1:80减1.5
B46: 100KG+实重比优惠：1:190减0.5、1:290减1、1:390减1.5、1:500及以上减2
B47: 国家 | C47: 东莞仓(明星仓5号）福永仓（明星仓6号） | F47: 备注
C48: 12KG+ | D48: 51KG+ | E48: 100KG+
B49: 美东（USE） 邮编0,1,2,3 | C49: 19.1 | D49: 15.1 | E49: 14.1 | F49: 1、如遇海关查验，在承诺时效内，不做赔偿;超出承诺时效，退0.5元/KG。其他不可抗力因素无赔偿(如船坏，码头罢工，UPS/FEDEX爆仓等） 2、时效承诺:开船后第二天开始算，15天提取(如遇船舶晚开，晚到港，节假日顺延) 。超15天每天赔付0.5元/kg，最高赔付3元，当天提取不计赔付 | G49: 报关费：150/票 不同渠道不能合并报关 | H49: 非亚马逊地址+1 偏远3/KG 超偏远4/KG 超极偏远5/KG，如需指定打单+5
B50: 美中（USM） 邮编4,5,6,7 | C50: 18.6 | D50: 14.6 | E50: 13.6
B51: 美西（USW） 邮编8,9 | C51: 16.6 | D51: 12.6 | E51: 11.6
B52: 后续关税每上调1%，将对应增加0.03元/kg的费用，按方对应增加6元/方，反之降关税每下调1%，将对应退0.03元/kg的费用，按方对应退6元/方 发货即默认此条款
B53: 备注：
B54: 必须有MADE IN CHINA的标记，服装类产品需缝纫水洗标，否则一旦被查到将会被要求在美国海关监管仓下逐件贴标；
B55: 贴标费1美金/标签，服装类无水洗标直接销毁，由此导致时效延误，销毁及一切费用由发货人全额承担。
B56: 报关行信息：
B57: 请参考船期表页
B59: 赔偿说明
B61: 1.在运输过程中货物丢失 & UPS/FEDEX整票未提取，丢件赔偿标准如下： 一.快递派标准 （1） 提取前任何形式的丢件 按货值赔偿（提供货值证明）最高不超过40/kg 不退运费 （2）提取上网后丢件 统一按照每件100美金赔偿 不退运费 二.卡派标准 （包含任何形式的丢件） （1）按公斤计费的丢件 按货值赔偿（提供货值证明）最高不超过40RMB/kg 不退运费 （2）按方计费的丢件 按货值赔偿（提供货值证明）最高不超过600RMB/件 不退运费 3.高货值产品及易碎品建议客人购买保险并打好包装，我司亦可提供购买保险服务；如若在运输过程中出因现包装原因而造成的损失而客人没有购买保险，我司概不负责； 4.货物未如实申报、侵权或不符合当地法规禁止进口的导致海关扣货不作赔偿, 并且保留追究发件人因此带来对我司的损失赔偿责任； 5.因船期延误或清关延误的，不作赔偿； 6.易碎品不接受任何损坏赔偿； 7.如客户一旦交货到我司，则默认上述赔款条例，出货前请详细阅读此赔偿标准。
B63: 注意事项
B65: 1.出货前需按我司固定模板填写发票。模块资料需提供详细品名，海关编码，材质，用途，图片，地址栏需认真仔细填写。
B66: 2.以上价格为义乌仓库交货价,材积货算:长*宽*高CM/6000 。只收纸箱包装货物，不接收木箱，木架等其他包装。
B67: 3.单箱最低计费重量12KG，如不足12KG的需按照12KG计费。
... B84: 特别提示：如客户一旦交货到我司，我司默认客户已详细阅读此价格表备注内容及说明，并接受其条款的约束！

Sheet 华南明星达14T卡派
G2: =目录!H4 -> 明日之星华南价格表入仓执行日期2025/1/27
B3: 浙江明日之星供应链管理有限公司(深圳分公司）
B5: 华南明星达14T卡派（美森CLX)
B7: 仓库代码 | C7: 东莞仓(明星仓5号）福永仓（明星仓6号） | F7: 起收重量 | G7: 开船后第二天开始计算 （有赔偿） | H7: 备注
C8: 12KG+ | D8: 50KG+ | E8: 按方包税1CBM+
B9: ONT8/LGB8/LAX9/SBD1 | C9: 9.7 | D9: 8.7 | E9: =D9*200 -> 1740 | F9: 12KG+/1CBM+ | G9: 18天签收入仓 | H9: 此报价只收普货，如发现冲货，瞒报或者带电不备注行为没收货物并罚款1000-50000RMB.
B10: LAS1/GYR3/GYR2/SMF3/ SCK4/VGT2 | C10: 10.2 | D10: 9.2 | E10: =D10*200 -> 1840 | F10: 12KG+/1CBM+ | G10: 19天签收入仓
B11: 开船后第二天开始计算时效，超过承诺时效，按照每天赔偿（退0.5元/KG，80/方），最高理赔（1元/KG，160/cbm）签收当天不计赔偿日。1、如遇船司晚开、晚到、节假日时效顺延。2、如遇海关查验后放行还在承诺时效内，不做赔偿:超出承诺时效,统一退（退0.5元/KG，80/方）不参与时效赔偿承诺。3、码头停摆、罢工、恶劣天气等不可抗拒因素无赔偿，如遇亚马逊删约、跳约等无赔偿。
B13: 华南明星达14T卡派（美森CLX)
B15: 仓库代码 | C15: 东莞仓(明星仓5号）福永仓（明星仓6号） | F15: 起收重量 | G15: 参考时效开船后（无赔偿） | H15: 备注
C16: 12KG+ | D16: 50KG+ | E16: 按方包税1CBM+
B17: POC1/POC3/POC2 | C17: 9.7 | D17: 8.7 | E17: =D17*200 -> 1740 | F17: 12KG+/1CBM+ | G17: 19天左右签收入仓 | H17: 1.拒接一切敏感货物，此报价只收普货，如发现冲货，瞒报或者带电不备注行为在我司仓库查到的没收货物并罚款1万-5万元，若因冲货导致海关查验的罚款20万并追究其法律责任，和一切损失 . 3.按方渠道密度比最高（1CBM：363KGS）M：363KGS）
B18: GEU3/GEU5/GEU2/MIT2/TCY2/TCY1/QXY8/SCK8/MCC1/HLI2 | C18: 9.9 | D18: 8.9 | E18: =D18*200 -> 1780 | F18: 12KG+/1CBM+ | G18: 18-22天左右签收
B19: IUSQ/IUSJ/IUSP/IUSW/IUTI/PSP3 | C19: 9.9 | D19: 8.9 | E19: =D19*200 -> 1780 | F19: 12KG+/1CBM+ | G19: 18-22天左右签收
B20: ABQ2 | C20: 10.9 | D20: 9.9 | E20: =D20*200 -> 1980 | F20: 12KG+/1CBM+ | G20: 18-22天左右签收
B21: PSC2 | C21: 11.7 | D21: 10.7 | E21: =D21*200 -> 2140 | F21: 12KG+/1CBM+ | G21: 18-24天左右签收
B22: FTW1/IAH3/AMA1/DFW6 | C22: 11.8 | D22: 10.8 | E22: =D22*200 -> 2160 | F22: 12KG+/1CBM+ | G22: 18-24天左右签收
B23: FWA4/IND9/MDW2 | C23: 12 | D23: 11 | E23: =D23*200 -> 2200 | F23: 12KG+/1CBM+ | G23: 18-24天左右签收
B24: MEM1/MQJ1/RFD2/SLC2/BNA6 | C24: 12 | D24: 11 | E24: =D24*200 -> 2200 | F24: 12KG+/1CBM+ | G24: 18-24天左右签收
B25: BNA2/DEN8/DEN2 | C25: 12.3 | D25: 11.3 | E25: =D25*200 -> 2260 | F25: 12KG+/1CBM+ | G25: 18-24天左右签收
B26: 仓库代码 | C26: 东莞仓(明星仓5号）福永仓（明星仓6号） | F26: 起收重量 | G26: 参考时效开船后 （无赔偿） | H26: 备注
C27: 12KG+ | D27: 100KG+ | E27: 按方包税1CBM+
B28: ABE8/TEB9/AVP1/CLT2 | C28: 13.7 | D28: 12.7 | E28: =D28*200 -> 2540 | F28: 12KG+/1CBM+ | G28: 20-24天左右签收 | H28: 1.我司拒接一切敏感货物，此报价只收普货，如发现冲货，瞒报或者带电不备注行为在我司仓库查到的没收货物并罚款1万-5万元，若因冲货导致海关查验的罚款20万并追究其法律责任，和一切损失 . 2.不同区不可以合并报关(如：一区不能和二区合并报关) 3.按方渠道密度比最高（1CBM：363KGS）
B29: TEB4/SWF1/SWF2 | C29: 14.3 | D29: 13.3 | E29: =D29*200 -> 2660 | F29: 12KG+/1CBM+ | G29: 22-26天左右签收
B30: ORF2/RMN3/RDU2 | C30: 14.7 | D30: 13.7 | E30: =D30*200 -> 2740 | F30: 12KG+/1CBM+ | G30: 22-26天左右签收
B31: 仓库代码 | C31: 东莞仓(明星仓5号）福永仓（明星仓6号） | F31: 按方包税2CBM+ | H31: 备注
C32: 50KG+ | D32: 100KG+ | E32: 1000KG+
B33: 美西海外仓自提 | C33: 9.4 | D33: 8.7 | E33: 8.7 | F33: =D33*200 -> 1740 | H33: 出库费$15/托，不包含其他费用（如海外仓仓储费，贴标费，派送费等），如有产生实报实销
B34: 90-91商业地址 | C34: 咨询我司客服单独报价 | H34: 不包含其他费用（如海外仓仓储费，贴标费，超时费，二次派送费等额外产生的杂费）如有产生实报实销
B35: 后续关税每上调1%，将对应增加0.03元/kg的费用，按方对应增加6元/方，反之降关税每下调1%，将对应退0.03元/kg的费用，按方对应退6元/方 发货即默认此条款
B36: 50KG+实重比优惠：1:190减0.5、1:250减0.8、1:300减1、1:350减1.3、1:400减1.5、1:450减1.8、1:500及以上减2 比重减后最低1.5/KG
B38: 赔偿说明
B40: 1.提供POD 和预约号后 亚马逊的货物请客户在签收后5个工作日内查询限FBA后台是否上架，签收后15个工作日内提供货物未上架后台截图(需带有电脑屏幕右下角当下真实时间)至我司方可进入开查程序，超过20个工作日反馈不予受理和赔偿。若卡派出现丢件在我司规定时间内调查核实后我司予以赔偿。丢件赔偿标准如下： 一.快递派标准 （1） 提取前任何形式的丢件 按货值赔偿（提供货值证明）最高不超过40/kg 不退运费 （2）提取上网后丢件 统一按照每件100美金赔偿 不退运费 二.卡派标准 （包含任何形式的丢件） （1）按公斤计费的丢件 按货值赔偿（提供货值证明）最高不超过40RMB/kg 不退运费 （2）按方计费的丢件 按货值赔偿（提供货值证明）最高不超过600RMB/件 不退运费 2.货物如因自身包装问题造成破损或数量短少的，不作赔偿； 3.货物未如实申报、侵权或不符合当地法规禁止进口的导致海关扣货不作赔偿, 并且保留追究发件人因此带来对我司的损失赔偿责任； 4.因船期延误或清关延误等不可抗因素，不作赔偿； 5.易碎品不接受任何损坏赔偿； 6.如客户一旦交货到我司，则默认上述赔款条例，出货前请详细阅读此赔偿标准。
B42: 注意事项
B44: 1.以上价格为华南仓库交货价,材积货算:长*宽*高CM/6000 ；
B45: 3.以上价格为普货产品到最终Amazon仓库的全部价格；
B46: 4.可接单独报关件，加收150RMB/票，退税件贸易国只接中国和美国，其他国家或者中国香港无服务；
B47: 5.单票货物超过5个品名，需额外加收30RMB/个；
B48: 6.订舱需提供出货模块资料，模块资料需提供详细品名，海关编码，材质，用途，图片，地址栏需认真仔细填写；
B49: 7.尺寸及重量：实重30-45KG加收1RMB/KG，(150/方）320CM<一长+两宽+两高<410CM加收5RMB/KG（800/方）尺寸及重量规则均叠加收费
B50: 8.FBA货物每件货物需贴2个或以上合格的FBA标签，我司提供贴标增值服务0.5RMB/标签；
... B52: 特别提示：如客户一旦交货到我司，我司默认客户已详细阅读此价格表备注内容及说明，并接受其条款的约束！

Sheet 华南明星达16T卡派
G2: =目录!H4 -> 明日之星华南价格表入仓执行日期2025/1/27
B3: 浙江明日之星供应链管理有限公司(深圳分公司）
B5: 华南明星达16T卡派 (美森MAX航线）
B7: 仓库代码 | C7: 东莞仓(明星仓5号）福永仓（明星仓6号） | F7: 起收重量 | G7: 开船后第二天开始计算 （有赔偿） | H7: 备注
C8: 12KG+ | D8: 50KG+ | E8: 按方包税1CBM+
B9: ONT8/LGB8/LAX9/SBD1 | C9: 9.4 | D9: 8.4 | E9: =D9*200 -> 1680 | F9: 12KG+/1CBM+ | G9: 19天签收入仓 | H9: 此报价只收普货，如发现冲货，瞒报或者带电不备注行为没收货物并罚款1000-50000RMB.
B10: LAS1/GYR3/GYR2/SMF3/ SCK4/VGT2 | C10: 9.9 | D10: 8.9 | E10: =D10*200 -> 1780 | F10: 12KG+/1CBM+ | G10: 20天签收入仓
B11: 开船后第二天开始计算时效，超过承诺时效，按照每天赔偿（退0.5元/KG，80/方），最高理赔（1元/KG，160/cbm）签收当天不计赔偿日。1、如遇船司晚开、晚到、节假日时效顺延。2、如遇海关查验后放行还在承诺时效内，不做赔偿:超出承诺时效,统一退（退0.5元/KG，80/方）不参与时效赔偿承诺。3、码头停摆、罢工、恶劣天气等不可抗拒因素无赔偿，如遇亚马逊删约、跳约等无赔偿。
B13: 华南明星达16T卡派 (美森MAX航线）
B15: 仓库代码 | C15: 东莞仓(明星仓5号）福永仓（明星仓6号） | F15: 起收重量 | G15: 参考时效开船后 （无赔偿） | H15: 备注
C16: 12KG+ | D16: 50KG+ | E16: 按方包税1CBM+
B17: POC1/POC3/POC2 | C17: 9.4 | D17: 8.4 | E17: =D17*200 -> 1680 | F17: 12KG+/1CBM+ | G17: 19天左右签收入仓 | H17: 1.我司拒接一切敏感货物，此报价只收普货，如发现冲货，瞒报或者带电不备注行为在我司仓库查到的没收货物并罚款1万-5万元，若因冲货导致海关查验的罚款20万并追究其法律责任，和一切损失 . 3.按方渠道密度比最高（1CBM：363KGS）
B18: GEU3/GEU5/GEU2/MIT2/TCY2/TCY1/QXY8/SCK8/MCC1/HLI2 | C18: 9.6 | D18: 8.6 | E18: =D18*200 -> 1720 | F18: 12KG+/1CBM+ | G18: 18-22天左右签收
B19: IUSQ/IUSJ/IUSP/IUSW/IUTI/PSP3 | C19: 9.6 | D19: 8.6 | E19: =D19*200 -> 1720 | F19: 12KG+/1CBM+ | G19: 18-22天左右签收
B20: ABQ2 | C20: 10.6 | D20: 9.6 | E20: =D20*200 -> 1920 | F20: 12KG+/1CBM+ | G20: 18-22天左右签收
B21: PSC2 | C21: 11.4 | D21: 10.4 | E21: =D21*200 -> 2080 | F21: 12KG+/1CBM+ | G21: 19-25天左右签收
B22: FTW1/IAH3/AMA1/DFW6 | C22: 11.5 | D22: 10.5 | E22: =D22*200 -> 2100 | F22: 12KG+/1CBM+ | G22: 19-25天左右签收
B23: FWA4/IND9/MDW2 | C23: 11.7 | D23: 10.7 | E23: =D23*200 -> 2140 | F23: 12KG+/1CBM+ | G23: 19-25天左右签收
B24: MEM1/MQJ1/RFD2/SLC2/BNA6 | C24: 11.7 | D24: 10.7 | E24: =D24*200 -> 2140 | F24: 12KG+/1CBM+ | G24: 19-25天左右签收
B25: BNA2/DEN8/DEN2 | C25: 12 | D25: 11 | E25: =D25*200 -> 2200 | F25: 12KG+/1CBM+ | G25: 21-27天左右签收
B26: 仓库代码 | C26: 东莞仓(明星仓5号）福永仓（明星仓6号） | F26: 起收重量 | G26: 参考时效开船后 （无赔偿） | H26: 备注
C27: 12KG+ | D27: 100KG+ | E27: 按方包税1CBM+
B28: ABE8/TEB9/AVP1/CLT2 | C28: 13.4 | D28: 12.4 | E28: =D28*200 -> 2480 | F28: 12KG+/1CBM+ | G28: 21-25天左右签收 | H28: 1.我司拒接一切敏感货物，此报价只收普货，如发现冲货，瞒报或者带电不备注行为在我司仓库查到的没收货物并罚款1万-5万元，若因冲货导致海关查验的罚款20万并追究其法律责任，和一切损失 . 2.不同区不可以合并报关(如：一区不能和二区合并报关) 3.按方渠道密度比最高（1CBM：363KGS）
B29: TEB4/SWF1/SWF2 | C29: 14 | D29: 13 | E29: =D29*200 -> 2600 | F29: 12KG+/1CBM+ | G29: 23-27天左右签收
B30: ORF2/RMN3/RDU2 | C30: 14.4 | D30: 13.4 | E30: =D30*200 -> 2680 | F30: 12KG+/1CBM+ | G30: 23-27天左右签收
B31: 仓库代码 | C31: 东莞仓(明星仓5号）福永仓（明星仓6号） | F31: 按方包税1CBM+ | H31: 备注
C32: 50KG+ | D32: 100KG+ | E32: 1000KG+
B33: 美西海外仓自提 | C33: 9.1 | D33: 8.4 | E33: 8.4 | F33: =D33*200 -> 1680 | H33: 出库费$15/托，不包含其他费用（如海外仓仓储费，贴标费，派送费等），如有产生实报实销
B34: 90-91商业地址 | C34: 咨询我司客服单独报价 | H34: 不包含其他费用（如海外仓仓储费，贴标费，超时费，二次派送费等额外产生的杂费）如有产生实报实销
B35: 后续关税每上调1%，将对应增加0.03元/kg的费用，按方对应增加6元/方，反之降关税每下调1%，将对应退0.03元/kg的费用，按方对应退6元/方 发货即默认此条款
B36: 以下仓库10cbm以上可单独咨询我司客服报价
B37: LGB6/SBD2/SNA4/XLX7/SJC7/FAT2/SCK1/ MCE1/PHX5/PHX7/LAS6/OAK3/FOE1/HOU8/ICT2/LIT2/MEM6/MKC4/OKC2/STL3/STL4/CMH2/CMH3/IGQ2/IND5/JVL1/MDW6/ORD2/HIA1 /ILG1/ABE3/MDT1/PHL6/RDU2/RDU4/RYY2/TEB6/ALB1/BWI4/DCA6/MGE3 /PIT2/ RIC1 /RMN3/SAV3/JAX3/PBI3/TMB8/ TPA3/SWF1/SWF2/LAN2/LBE1/TEB9/SLC2
B38: 50KG+实重比优惠：1:190减0.5、1:250减0.8、1:300减1、1:350减1.3、1:400减1.5、1:450减1.8、1:500及以上减2 比重减后最低1.5/KG
B40: 赔偿说明
B42: 1.提供POD 和预约号后 亚马逊的货物请客户在签收后5个工作日内查询限FBA后台是否上架，签收后15个工作日内提供货物未上架后台截图(需带有电脑屏幕右下角当下真实时间)至我司方可进入开查程序，超过20个工作日反馈不予受理和赔偿。若卡派出现丢件在我司规定时间内调查核实后我司予以赔偿。丢件赔偿标准如下： 一.快递派标准 （1） 提取前任何形式的丢件 按货值赔偿（提供货值证明）最高不超过40/kg 不退运费 （2）提取上网后丢件 统一按照每件100美金赔偿 不退运费 二.卡派标准 （包含任何形式的丢件） （1）按公斤计费的丢件 按货值赔偿（提供货值证明）最高不超过40RMB/kg 不退运费 （2）按方计费的丢件 按货值赔偿（提供货值证明）最高不超过600RMB/件 不退运费 2.货物如因自身包装问题造成破损或数量短少的，不作赔偿； 3.货物未如实申报、侵权或不符合当地法规禁止进口的导致海关扣货不作赔偿, 并且保留追究发件人因此带来对我司的损失赔偿责任； 4.因船期延误或清关延误等不可抗因素，不作赔偿； 5.易碎品不接受任何损坏赔偿； 6.如客户一旦交货到我司，则默认上述赔款条例，出货前请详细阅读此赔偿标准。
B44: 注意事项
B45: 1.以上价格为华南仓库交货价,材积货算:长*宽*高CM/6000 。
B46: 3.以上价格为普货产品到最终Amazon仓库的全部价格
B47: 4.可接单独报关件，加收150RMB/票，退税件贸易国只接中国和美国，其他国家或者中国香港无服务。
B48: 5.单票货物超过5个品名，需额外加收30RMB/个。
B49: 6.订舱需提供出货模块资料，模块资料需提供详细品名，海关编码，材质，用途，图片，地址栏需认真仔细填写。
... B53: 特别提示：如客户一旦交货到我司，我司默认客户已详细阅读此价格表备注内容及说明，并接受其条款的约束！

Sheet 华南明星达18T卡派
J3: =目录!H4 -> 明日之星华南价格表入仓执行日期2025/1/27
B4: 浙江明日之星供应链管理有限公司(深圳分公司）
B7: 华南明星达18T卡派
B9: 组合区 | C9: 仓库代码 | D9: 东莞仓(明星仓5号）福永仓（明星仓6号） | G9: 起收重量 | H9: 开船后第二天 开始计算时效签收时效 | I9: 备注
D10: 12KG+ | E10: 50KG+ | F10: 按方包税1CBM+
B11: 一区美西特价 | C11: ONT8/LGB8/LAX9/SBD1 | D11: 5.4 | E11: 4.4 | F11: =E11*200 -> 880 | G11: 12KG+/1CBM+ | H11: 20天签收 | I11: 此报价只收普货，如发现冲货，瞒报或者带电不备注行为没收货物并罚款1000-50000RMB.
B12: 三区美西特价 | C12: GYR2/GYR3/LAS1/SMF3/SCK4/VGT2 | D12: 5.9 | E12: 4.9 | F12: =E12*200 -> 980 | G12: 12KG+/1CBM+ | H12: 21天签收
B13: 开船后第二天开始计算时效，超过承诺时效，按照每天赔偿（退0.5元/KG，80/方），最高理赔（1元/KG，160/cbm）签收当天不计赔偿日。1、如遇船司晚开、晚到、节假日时效顺延。2、如遇海关查验后放行还在承诺时效内，不做赔偿:超出承诺时效,统一退（退0.5元/KG，80/方）不参与时效赔偿承诺。3、码头停摆、罢工、恶劣天气等不可抗拒因素无赔偿，如遇亚马逊删约、跳约等无赔偿。
B15: 华南明星达18T卡派
B17: 组合区 | C17: 仓库代码 | D17: 东莞仓(明星仓5号）福永仓（明星仓6号） | G17: 起收重量 | H17: 参考时效开船后 （无赔偿） | I17: 备注
D18: 12KG+ | E18: 50KG+ | F18: 按方包税1CBM+
B19: 一区美西 | C19: POC1/POC3/ POC2 | D19: 5.6 | E19: 4.6 | F19: =E19*200 -> 920 | G19: 12KG+/1CBM+ | H19: 20天左右签收 | I19: 1.我司拒接一切敏感货物，此报价只收普货，如发现冲货，瞒报或者带电不备注行为在我司仓库查到的没收货物并罚款1万-5万元，若因冲货导致海关查验的罚款20万并追究其法律责任，和一切损失 . 2.不同区不可以合并报关(如：一区不能和二区合并报关) 3.按方渠道密度比最高（1CBM：363KGS）
B20: 二区美西 | C20: LGB4/LGB9/LGB6/SBD2 /SNA4/ XLX7/JOT1 | D20: 5.8 | E20: 4.8 | F20: =E20*200 -> 960 | G20: 12KG+/1CBM+ | H20: 21天左右签收
C21: IUSQ/IUSJ/IUSP/IUTI/IUSW/IUTE/PSP3 | D21: 5.8 | E21: 4.8 | F21: =E21*200 -> 960 | G21: 12KG+/1CBM+ | H21: 21天左右签收
B22: 三区美西 | C22: SCK8/MIT2/HLI2/TCY2/TCY1/MCC1 | D22: 6.3 | E22: 5.3 | F22: =E22*200 -> 1060 | G22: 12KG+/1CBM+ | H22: 19-24天左右签收
C23: GEU3/GEU5/GEU2/QXY5/QXY8 | D23: 6.3 | E23: 5.3 | F23: =E23*200 -> 1060 | G23: 12KG+/1CBM+ | H23: 19-24天左右签收
B24: 四区美西 | C24: SJC7/FAT2/SCK1/ MCE1 | D24: 6.3 | E24: 5.3 | F24: =E24*200 -> 1060 | G24: 12KG+/1CBM+ | H24: 19-24天左右签收
C25: PHX5/PHX7/LAS6/OAK3/SMF6 | D25: 6.3 | E25: 5.3 | F25: =E25*200 -> 1060 | G25: 12KG+/1CBM+ | H25: 19-24天左右签收
C26: ABQ2 | D26: 7.1 | E26: 6.1 | F26: =E26*200 -> 1220 | G26: 12KG+/1CBM+ | H26: 19-24天左右签收
B27: 五区美中 | C27: PSC2 | D27: 7.7 | E27: 6.7 | F27: =E27*200 -> 1340 | G27: 12KG+/1CBM+ | H27: 21-27天左右签收
C28: AMA1/SAT1/SAT4/DFW6/FTW1/IAH3/IUTH/AFW5/FTW5 | D28: 7.9 | E28: 6.9 | F28: =E28*200 -> 1380 | G28: 12KG+/1CBM+ | H28: 21-27天左右签收
C29: FWA4/IND9/MDW2/IUSF | D29: 8.2 | E29: 7.2 | F29: =E29*200 -> 1440 | G29: 12KG+/1CBM+ | H29: 21-27天左右签收
C30: MEM1/MQJ1/RFD2/SLC2/BNA6 | D30: 8.2 | E30: 7.2 | F30: =E30*200 -> 1440 | G30: 12KG+/1CBM+ | H30: 21-27天左右签收
B31: 组合区 | C31: 仓库代码 | D31: 东莞仓(明星仓5号）福永仓（明星仓6号） | G31: 起收重量 | H31: 参考时效开船后 （无赔偿） | I31: 备注
D32: 50KG+ | E32: 100KG+ | F32: 按方包税1CBM+
B33: 六区美中 | C33: BNA2/DEN8/DEN2/FOE1/PPO4 | D33: 8.5 | E33: 7.5 | F33: =E33*200 -> 1500 | G33: 50KG+/1CBM+ | H33: 23-29天左右签收 | I33: 1.我司拒接一切敏感货物，此报价只收普货，如发现冲货，瞒报或者带电不备注行为在我司仓库查到的没收货物并罚款1万-5万元，若因冲货导致海关查验的罚款20万并追究其法律责任，和一切损失 . 2.不同区不可以合并报关(如：一区不能和二区合并报关) 3.按方渠道密度比最高（1CBM：363KGS）
C34: HOU8/ICT2/LIT2/MEM6/MKC4 | D34: 8.5 | E34: 7.5 | F34: =E34*200 -> 1500 | G34: 50KG+/1CBM+ | H34: 23-29天左右签收
C35: OKC2/STL3/STL4/FTW3/BFI3/GEG2 | D35: 8.5 | E35: 7.5 | F35: =E35*200 -> 1500 | G35: 50KG+/1CBM+ | H35: 23-29天左右签收
B36: 七区美中 | C36: CMH2/CMH3/IGQ2/IND2/LAN2 | D36: 8.8 | E36: 7.8 | F36: =E36*200 -> 1560 | G36: 50KG+/1CBM+ | H36: 23-29天左右签收
C37: JVL1/MDW6/ORD2/RFD4/STL6/DET1/DET2 | D37: 8.8 | E37: 7.8 | F37: =E37*200 -> 1560 | G37: 50KG+/1CBM+ | H37: 23-29天左右签收
B38: 组合区 | C38: 仓库代码 | D38: 东莞仓(明星仓5号）福永仓（明星仓6号） | G38: 起收重量 | H38: 参考时效开船后 （无赔偿） | I38: 1.我司拒接一切敏感货物，此报价只收普货，如发现冲货，瞒报或者带电不备注行为在我司仓库查到的没收货物并罚款1万-5万元，若因冲货导致海关查验的罚款20万并追究其法律责任，和一切损失 . 2.不同区不可以合并报关(如：一区不能和二区合并报关) 3.按方渠道密度比最高（1CBM：363KGS）
D39: 12KG+ | E39: 100KG+ | F39: 按方包税1CBM+
B40: 美东纽约专区 | C40: ABE8/AVP1/TEB9/RMN3 | D40: 9.4 | E40: 8.4 | F40: =E40*200 -> 1680 | G40: 12KG+/1CBM+ | H40: 21-27天左右签收
C41: ACY2/TEB3/TEB6/TTN2/ABE4/RDU4/HEA2/RDU2 | D41: 9.9 | E41: 8.9 | F41: =E41*200 -> 1780 | G41: 12KG+/1CBM+ | H41: 25-29天左右签收
C42: TEB4/SWF1/SWF2/MDT1/WBW2 | D42: 9.9 | E42: 8.9 | F42: =E42*200 -> 1780 | G42: 12KG+/1CBM+ | H42: 25-29天左右签收
C43: MDT4/PHL4/PHL5/PHL6/DCA6/ILG1 /IUSL/HIA1 | D43: 10 | E43: 9 | F43: =E43*200 -> 1800 | G43: 12KG+/1CBM+ | H43: 25-29天左右签收
C44: ORF2/RIC1/BOS7/ALB1/XLX1/XRI3 | D44: 10 | E44: 9 | F44: =E44*200 -> 1800 | G44: 12KG+/1CBM+ | H44: 25-29天左右签收
C45: PIT2/LBE1/CHO1/ AKR1 /IUST | D45: 10 | E45: 9 | F45: =E45*200 -> 1800 | G45: 12KG+/1CBM+ | H45: 25-29天左右签收
B46: 组合区 | C46: 仓库代码 | D46: 东莞仓(明星仓5号）福永仓（明星仓6号） | G46: 起收重量 | H46: 参考时效开船后（无赔偿） | I46: 备注
D47: 12KG+ | E47: 100KG+ | F47: 按方包税1CBM+
B48: 美东萨凡纳专区 | C48: CLT2/XAV3 | D48: 9.1 | E48: 8.1 | F48: =E48*200 -> 1620 | G48: 12KG+/1CBM+ | H48: 21-27天左右签收 | I48: 1.我司拒接一切敏感货物，此报价只收普货，如发现冲货，瞒报或者带电不备注行为在我司仓库查到的没收货物并罚款1万-5万元，若因冲货导致海关查验的罚款20万并追究其法律责任，和一切损失 . 2.不同区不可以合并报关(如：一区不能和二区合并报关) 3.按方渠道密度比最高（1CBM：363KGS）
C49: MGE3/SAV3/JAX3 | D49: 9.9 | E49: 8.9 | F49: =E49*200 -> 1780 | G49: 12KG+/1CBM+ | H49: 25-29天签收
C50: CLT3/RYY2/XLX6/CLT6/GSO1/GSP1 | D50: 9.9 | E50: 8.9 | F50: =E50*200 -> 1780 | G50: 12KG+/1CBM+ | H50: 25-29天签收
C51: TPA2/TPA3/TPA6/MCO2 | D51: 10 | E51: 9 | F51: =E51*200 -> 1800 | G51: 12KG+/1CBM+ | H51: 25-29天签收
C52: HSV1/HSV2/IUSR/PBI2/PBI3/TMB8/XPB2 | D52: 10 | E52: 9 | F52: =E52*200 -> 1800 | G52: 12KG+/1CBM+ | H52: 25-29天签收
B53: 仓库代码 | D53: 东莞仓(明星仓5号）福永仓（明星仓6号） | G53: 按方包税1CBM+ | I53: 备注
D54: 50KG+ | E54: 100KG+ | F54: 500KG+
B55: 美西海外仓自提 | D55: 5.4 | E55: 4.4 | F55: 4.4 | G55: =F55*200 -> 880 | I55: 出库费$15/托，不包含其他费用（如海外仓仓储费，贴标费，派送费等），如有产生实报实销
B56: 90-91商业地址 | D56: 咨询我司客服单独报价 | I56: 不包含其他费用（如海外仓仓储费，贴标费，超时费，二次派送费等额外产生的杂费）如有产生实报实销
B57: 后续关税每上调1%，将对应增加0.03元/kg的费用，按方对应增加6元/方，反之降关税每下调1%，将对应退0.03元/kg的费用，按方对应退6元/方 发货即默认此条款
B58: 50KG+实重比优惠：1:190减0.5、1:250减0.8、1:300减1、1:350减1.3、1:400减1.5、1:450减1.8、1:500及以上减2 比重减后最低1.5/KG
B60: 赔偿说明
B62: 1.提供POD 和预约号后 亚马逊的货物请客户在签收后5个工作日内查询限FBA后台是否上架，签收后15个工作日内提供货物未上架后台截图(需带有电脑屏幕右下角当下真实时间)至我司方可进入开查程序，超过20个工作日反馈不予受理和赔偿。若卡派出现丢件在我司规定时间内调查核实后我司予以赔偿。丢件赔偿标准如下： 一.快递派标准 （1） 提取前任何形式的丢件 按货值赔偿（提供货值证明）最高不超过40/kg 不退运费 （2）提取上网后丢件 统一按照每件100美金赔偿 不退运费 二.卡派标准 （包含任何形式的丢件） （1）按公斤计费的丢件 按货值赔偿（提供货值证明）最高不超过40RMB/kg 不退运费 （2）按方计费的丢件 按货值赔偿（提供货值证明）最高不超过600RMB/件 不退运费 2.货物如因自身包装问题造成破损或数量短少的，不作赔偿； 3.货物未如实申报、侵权或不符合当地法规禁止进口的导致海关扣货不作赔偿, 并且保留追究发件人因此带来对我司的损失赔偿责任； 4.因船期延误或清关延误等不可抗因素，不作赔偿； 5.易碎品不接受任何损坏赔偿； 6.如客户一旦交货到我司，则默认上述赔款条例，出货前请详细阅读此赔偿标准。
B64: 注意事项
B66: 1.以上价格为华南仓库交货价,材积货算:长*宽*高CM/6000 。
B67: 3.以上价格为普货产品到最终Amazon仓库的全部价格
B68: 4.可接单独报关件，加收280RMB/票，退税件贸易国只接中国和美国，其他国家或者中国香港无服务。
B69: 5.单票货物超过5个品名，需额外加收30RMB/个。
B70: 6.订舱需提供出货模块资料，模块资料需提供详细品名，海关编码，材质，用途，图片，地址栏需认真仔细填写。
B71: 7.尺寸及重量：实重30-45KG加收1RMB/KG，(150/方）320CM<一长+两宽+两高<410CM加收5RMB/KG（800/方）尺寸及重量规则均叠加收费
B72: 8.FBA货物每件货物需贴2个或以上合格的FBA标签，我司提供贴标增值服务0.5RMB/标签。
... B74: 特别提示：如客户一旦交货到我司，我司默认客户已详细阅读此价格表备注内容及说明，并接受其条款的约束！

Sheet 华南明星达20T卡派
J4: =目录!H4 -> 明日之星华南价格表入仓执行日期2025/1/27
B5: 浙江明日之星供应链管理有限公司(深圳分公司）
B8: 华南明星达20T卡派(合德HDS3)华南王牌渠道
B10: 组合区 | C10: 仓库代码 | D10: 东莞仓(明星仓5号）福永仓（明星仓6号） | G10: 起收重量 | H10: 开船后第二天 开始计算时效签收时效 | I10: 备注
D11: 12KG+ | E11: 50KG+ | F11: 按方包税1CBM+
B12: 一区美西特价 | C12: ONT8/LGB8/LAX9/SBD1 | D12: 4.6 | E12: 3.6 | F12: =E12*200 -> 720 | G12: 12KG+/1CBM+ | H12: 22天签收 | I12: 此报价只收普货，如发现冲货，瞒报或者带电不备注行为没收货物并罚款1000-50000RMB.
B13: 三区美西特价 | C13: GYR2/GYR3/LAS1/SMF3/SCK4/VGT2 | D13: 5.1 | E13: 4.1 | F13: =E13*200 -> 820 | G13: 12KG+/1CBM+ | H13: 23天签收
B14: 开船后第二天开始计算时效，超过承诺时效，按照每天赔偿（退0.5元/KG，80/方），最高理赔（1元/KG，160/cbm）签收当天不计赔偿日。1、如遇船司晚开、晚到、节假日时效顺延。2、如遇海关查验后放行还在承诺时效内，不做赔偿:超出承诺时效,统一退（退0.5元/KG，80/方）不参与时效赔偿承诺。3、码头停摆、罢工、恶劣天气等不可抗拒因素无赔偿，如遇亚马逊删约、跳约等无赔偿。
B16: 华南明星达20T卡派(合德HDS3)华南王牌渠道
B18: 组合区 | C18: 仓库代码 | D18: 东莞仓(明星仓5号）福永仓（明星仓6号） | G18: 起收重量 | H18: 参考时效开船后 （无赔偿） | I18: 备注
D19: 12KG+ | E19: 50KG+ | F19: 按方包税1CBM+
B20: 一区美西 | C20: POC1/POC3/ POC2 | D20: 4.9 | E20: 3.9 | F20: =E20*200 -> 780 | G20: 12KG+/1CBM+ | H20: 22天左右签收 | I20: 1.我司拒接一切敏感货物，此报价只收普货，如发现冲货，瞒报或者带电不备注行为在我司仓库查到的没收货物并罚款1万-5万元，若因冲货导致海关查验的罚款20万并追究其法律责任，和一切损失 . 2.不同区不可以合并报关(如：一区不能和二区合并报关) 3.按方渠道密度比最高（1CBM：363KGS）
B21: 二区美西 | C21: LGB4/LGB9/LGB6/SBD2 /SNA4/ XLX7/JOT1 | D21: 5.1 | E21: 4.1 | F21: =E21*200 -> 820 | G21: 12KG+/1CBM+ | H21: 23天左右签收
C22: IUSQ/IUSJ/IUSP/IUTI/IUSW/IUTE/PSP3 | D22: 5.1 | E22: 4.1 | F22: =E22*200 -> 820 | G22: 12KG+/1CBM+ | H22: 23天左右签收
B23: 三区美西 | C23: SCK8/MIT2/HLI2/TCY2/TCY1/MCC1 | D23: 5.6 | E23: 4.6 | F23: =E23*200 -> 920 | G23: 12KG+/1CBM+ | H23: 19-24天左右签收
C24: GEU3/GEU5/GEU2/QXY5/QXY8 | D24: 5.6 | E24: 4.6 | F24: =E24*200 -> 920 | G24: 12KG+/1CBM+ | H24: 19-24天左右签收
B25: 四区美西 | C25: SJC7/FAT2/SCK1/ MCE1 | D25: 5.6 | E25: 4.6 | F25: =E25*200 -> 920 | G25: 12KG+/1CBM+ | H25: 19-24天左右签收
C26: PHX5/PHX7/LAS6/OAK3/SMF6 | D26: 5.6 | E26: 4.6 | F26: =E26*200 -> 920 | G26: 12KG+/1CBM+ | H26: 19-24天左右签收
C27: ABQ2 | D27: 6.4 | E27: 5.4 | F27: =E27*200 -> 1080 | G27: 12KG+/1CBM+ | H27: 19-24天左右签收
B28: 五区美中 | C28: PSC2 | D28: 7 | E28: 6 | F28: =E28*200 -> 1200 | G28: 12KG+/1CBM+ | H28: 21-27天左右签收
C29: AMA1/SAT1/SAT4/DFW6/FTW1/IAH3/IUTH/AFW5/FTW5 | D29: 7.2 | E29: 6.2 | F29: =E29*200 -> 1240 | G29: 12KG+/1CBM+ | H29: 21-27天左右签收
C30: FWA4/IND9/MDW2/IUSF | D30: 7.5 | E30: 6.5 | F30: =E30*200 -> 1300 | G30: 12KG+/1CBM+ | H30: 21-27天左右签收
C31: MEM1/MQJ1/RFD2/SLC2/BNA6 | D31: 7.5 | E31: 6.5 | F31: =E31*200 -> 1300 | G31: 12KG+/1CBM+ | H31: 21-27天左右签收
B32: 组合区 | C32: 仓库代码 | D32: 东莞仓(明星仓5号）福永仓（明星仓6号） | G32: 起收重量 | H32: 参考时效开船后 （无赔偿） | I32: 备注
D33: 50KG+ | E33: 100KG+ | F33: 按方包税1CBM+
B34: 六区美中 | C34: BNA2/DEN8/DEN2/FOE1/PPO4 | D34: 7.8 | E34: 6.8 | F34: =E34*200 -> 1360 | G34: 50KG+/1CBM+ | H34: 23-29天左右签收 | I34: 1.我司拒接一切敏感货物，此报价只收普货，如发现冲货，瞒报或者带电不备注行为在我司仓库查到的没收货物并罚款1万-5万元，若因冲货导致海关查验的罚款20万并追究其法律责任，和一切损失 . 2.不同区不可以合并报关(如：一区不能和二区合并报关) 3.按方渠道密度比最高（1CBM：363KGS）
C35: HOU8/ICT2/LIT2/MEM6/MKC4 | D35: 7.8 | E35: 6.8 | F35: =E35*200 -> 1360 | G35: 50KG+/1CBM+ | H35: 23-29天左右签收
C36: OKC2/STL3/STL4/FTW3/BFI3/GEG2 | D36: 7.8 | E36: 6.8 | F36: =E36*200 -> 1360 | G36: 50KG+/1CBM+ | H36: 23-29天左右签收
B37: 七区美中 | C37: CMH2/CMH3/IGQ2/IND2/LAN2 | D37: 8.1 | E37: 7.1 | F37: =E37*200 -> 1420 | G37: 50KG+/1CBM+ | H37: 23-29天左右签收
C38: JVL1/MDW6/ORD2/RFD4/STL6/DET1/DET2 | D38: 8.1 | E38: 7.1 | F38: =E38*200 -> 1420 | G38: 50KG+/1CBM+ | H38: 23-29天左右签收
B39: 组合区 | C39: 仓库代码 | D39: 东莞仓(明星仓5号）福永仓（明星仓6号） | G39: 起收重量 | H39: 参考时效开船后 （无赔偿） | I39: 1.我司拒接一切敏感货物，此报价只收普货，如发现冲货，瞒报或者带电不备注行为在我司仓库查到的没收货物并罚款1万-5万元，若因冲货导致海关查验的罚款20万并追究其法律责任，和一切损失 . 2.不同区不可以合并报关(如：一区不能和二区合并报关) 3.按方渠道密度比最高（1CBM：363KGS）
D40: 12KG+ | E40: 100KG+ | F40: 按方包税1CBM+
B41: 美东纽约专区 | C41: ABE8/AVP1/TEB9/RMN3 | D41: 8.7 | E41: 7.7 | F41: =E41*200 -> 1540 | G41: 12KG+/1CBM+ | H41: 21-27天左右签收
C42: ACY2/TEB3/TEB6/TTN2/ABE4/RDU4/HEA2/RDU2 | D42: 9.2 | E42: 8.2 | F42: =E42*200 -> 1640 | G42: 12KG+/1CBM+ | H42: 25-29天左右签收
C43: TEB4/SWF1/SWF2/MDT1/WBW2 | D43: 9.2 | E43: 8.2 | F43: =E43*200 -> 1640 | G43: 12KG+/1CBM+ | H43: 25-29天左右签收
C44: MDT4/PHL4/PHL5/PHL6/DCA6/ILG1 /IUSL/HIA1 | D44: 9.3 | E44: 8.3 | F44: =E44*200 -> 1660 | G44: 12KG+/1CBM+ | H44: 25-29天左右签收
C45: ORF2/RIC1/BOS7/ALB1/XLX1/XRI3 | D45: 9.3 | E45: 8.3 | F45: =E45*200 -> 1660 | G45: 12KG+/1CBM+ | H45: 25-29天左右签收
C46: PIT2/LBE1/CHO1/ AKR1 /IUST | D46: 9.3 | E46: 8.3 | F46: =E46*200 -> 1660 | G46: 12KG+/1CBM+ | H46: 25-29天左右签收
B47: 组合区 | C47: 仓库代码 | D47: 东莞仓(明星仓5号）福永仓（明星仓6号） | G47: 起收重量 | H47: 参考时效开船后（无赔偿） | I47: 备注
D48: 12KG+ | E48: 100KG+ | F48: 按方包税1CBM+
B49: 美东萨凡纳专区 | C49: CLT2/XAV3 | D49: 8.4 | E49: 7.4 | F49: =E49*200 -> 1480 | G49: 12KG+/1CBM+ | H49: 21-27天左右签收 | I49: 1.我司拒接一切敏感货物，此报价只收普货，如发现冲货，瞒报或者带电不备注行为在我司仓库查到的没收货物并罚款1万-5万元，若因冲货导致海关查验的罚款20万并追究其法律责任，和一切损失 . 2.不同区不可以合并报关(如：一区不能和二区合并报关) 3.按方渠道密度比最高（1CBM：363KGS）
C50: MGE3/SAV3/JAX3 | D50: 9.2 | E50: 8.2 | F50: =E50*200 -> 1640 | G50: 12KG+/1CBM+ | H50: 25-29天签收
C51: CLT3/RYY2/XLX6/CLT6/GSO1/GSP1 | D51: 9.2 | E51: 8.2 | F51: =E51*200 -> 1640 | G51: 12KG+/1CBM+ | H51: 25-29天签收
C52: TPA2/TPA3/TPA6/MCO2 | D52: 9.3 | E52: 8.3 | F52: =E52*200 -> 1660 | G52: 12KG+/1CBM+ | H52: 25-29天签收
C53: HSV1/HSV2/IUSR/PBI2/PBI3/TMB8/XPB2 | D53: 9.3 | E53: 8.3 | F53: =E53*200 -> 1660 | G53: 12KG+/1CBM+ | H53: 25-29天签收
B54: 仓库代码 | D54: 东莞仓(明星仓5号）福永仓（明星仓6号） | G54: 按方包税1CBM+ | I54: 备注
D55: 50KG+ | E55: 100KG+ | F55: 500KG+
B56: 美西海外仓自提 | D56: 4.6 | E56: 3.6 | F56: 3.6 | G56: =F56*200 -> 720 | I56: 出库费$15/托，不包含其他费用（如海外仓仓储费，贴标费，派送费等），如有产生实报实销
B57: 90-91商业地址 | D57: 咨询我司客服单独报价 | I57: 不包含其他费用（如海外仓仓储费，贴标费，超时费，二次派送费等额外产生的杂费）如有产生实报实销
B58: 后续关税每上调1%，将对应增加0.03元/kg的费用，按方对应增加6元/方，反之降关税每下调1%，将对应退0.03元/kg的费用，按方对应退6元/方 发货即默认此条款
B59: 50KG+实重比优惠：1:190减0.5、1:250减0.8、1:300减1、1:350减1.3、1:400减1.5、1:450减1.8、1:500及以上减2 比重减后最低1.5/KG
B61: 赔偿说明
B63: 1.提供POD 和预约号后 亚马逊的货物请客户在签收后5个工作日内查询限FBA后台是否上架，签收后15个工作日内提供货物未上架后台截图(需带有电脑屏幕右下角当下真实时间)至我司方可进入开查程序，超过20个工作日反馈不予受理和赔偿。若卡派出现丢件在我司规定时间内调查核实后我司予以赔偿。丢件赔偿标准如下： 一.快递派标准 （1） 提取前任何形式的丢件 按货值赔偿（提供货值证明）最高不超过40/kg 不退运费 （2）提取上网后丢件 统一按照每件100美金赔偿 不退运费 二.卡派标准 （包含任何形式的丢件） （1）按公斤计费的丢件 按货值赔偿（提供货值证明）最高不超过40RMB/kg 不退运费 （2）按方计费的丢件 按货值赔偿（提供货值证明）最高不超过600RMB/件 不退运费 2.货物如因自身包装问题造成破损或数量短少的，不作赔偿； 3.货物未如实申报、侵权或不符合当地法规禁止进口的导致海关扣货不作赔偿, 并且保留追究发件人因此带来对我司的损失赔偿责任； 4.因船期延误或清关延误等不可抗因素，不作赔偿； 5.易碎品不接受任何损坏赔偿； 6.如客户一旦交货到我司，则默认上述赔款条例，出货前请详细阅读此赔偿标准。
B65: 注意事项
B67: 1.以上价格为华南仓库交货价,材积货算:长*宽*高CM/6000
B68: 3.以上价格为普货产品到最终Amazon仓库的全部价格
B69: 4.可接单独报关件，加收150RMB/票，退税件贸易国只接中国和美国，其他国家或者中国香港无服务。
B70: 5.单票货物超过5个品名，需额外加收30RMB/个
B71: 6.订舱需提供出货模块资料，模块资料需提供详细品名，海关编码，材质，用途，图片，地址栏需认真仔细填写。
B72: 7.尺寸及重量：实重30-45KG加收1RMB/KG，(150/方）320CM<一长+两宽+两高<410CM加收5RMB/KG（800/方）尺寸及重量规则均叠加收费
B73: 8.FBA货物每件货物需贴2个或以上合格的FBA标签，我司提供贴标增值服务0.5RMB/标签。
... B75: 特别提示：如客户一旦交货到我司，我司默认客户已详细阅读此价格表备注内容及说明，并接受其条款的约束！

Sheet 华南OA普船卡派
J3: =目录!H4 -> 明日之星华南价格表入仓执行日期2025/1/27
B4: 浙江明日之星供应链管理有限公司(深圳分公司）
B7: 华南OA卡派直送（盐田 COSCO SEA航线)(本周船期OA必保舱位，如因船司爆仓甩柜赔付0.5/KG)
B9: 组合区 | C9: 仓库代码 | D9: 东莞仓(明星仓5号）福永仓（明星仓6号） | G9: 起收重量 | H9: 开船后第二天 开始计算时效签收时效 | I9: 备注
D10: 12KG+ | E10: 50KG+ | F10: 按方包税1CBM+
B11: 洛杉矶特价 | C11: ONT8/LGB8/LAX9/SBD1 | D11: 4.1 | E11: 3.1 | F11: =E11*200 -> 620 | G11: 12KG+/1CBM+ | H11: 19-26天签收 | I11: 此渠道报价为直送柜不接受拦截，若需要拦截每票2200美金/票，不接受合并报关。单件尺寸不超63cm，在截单前到货的保证装走，不集货，不延船期!
C12: GYR2/GYR3/LAS1/SMF3/SCK4/VGT2 | D12: 4.6 | E12: 3.6 | F12: =E12*200 -> 720 | G12: 12KG+/1CBM+ | H12: 19-26天签收
B14: 华南OA拆柜卡派（盐田 COSCO SEA航线)(本周船期OA必保舱位，如因船司爆仓甩柜赔付0.5/KG)
B16: 组合区 | C16: 仓库代码 | D16: 东莞仓(明星仓5号）福永仓（明星仓6号） | G16: 起收重量 | H16: 参考时效开船后 （无赔偿） | I16: 备注
D17: 12KG+ | E17: 50KG+ | F17: 按方包税1CBM+
B18: 一区美西 | C18: POC1/POC3/ POC2 | D18: 4.5 | E18: 3.5 | F18: =E18*200 -> 700 | G18: 12KG+/1CBM+ | H18: 22-28天签收 | I18: 1.我司拒接一切敏感货物，此报价只收普货，如发现冲货，瞒报或者带电不备注行为在我司仓库查到的没收货物并罚款1万-5万元，若因冲货导致海关查验的罚款20万并追究其法律责任，和一切损失 . 2.不同区不可以合并报关(如：一区不能和二区合并报关) 3.按方渠道密度比最高（1CBM：363KGS）
B19: 二区美西 | C19: LGB4/LGB9/LGB6/SBD2 /SNA4/ XLX7/JOT1 | D19: 4.7 | E19: 3.7 | F19: =E19*200 -> 740 | G19: 12KG+/1CBM+ | H19: 22-28天签收
C20: IUSQ/IUSJ/IUSP/IUTI/IUSW/IUTE/PSP3 | D20: 4.7 | E20: 3.7 | F20: =E20*200 -> 740 | G20: 12KG+/1CBM+ | H20: 22-28天签收
B21: 三区美西 | C21: SCK8/MIT2/HLI2/TCY2/TCY1/MCC1 | D21: 5.2 | E21: 4.2 | F21: =E21*200 -> 840 | G21: 12KG+/1CBM+ | H21: 22-28天签收
C22: GEU3/GEU5/GEU2/QXY5/QXY8 | D22: 5.2 | E22: 4.2 | F22: =E22*200 -> 840 | G22: 12KG+/1CBM+ | H22: 22-28天签收
B23: 四区美西 | C23: SJC7/FAT2/SCK1/ MCE1 | D23: 5.2 | E23: 4.2 | F23: =E23*200 -> 840 | G23: 12KG+/1CBM+ | H23: 22-28天签收
C24: PHX5/PHX7/LAS6/OAK3/SMF6 | D24: 5.2 | E24: 4.2 | F24: =E24*200 -> 840 | G24: 12KG+/1CBM+ | H24: 22-28天签收
C25: ABQ2 | D25: 6 | E25: 5 | F25: =E25*200 -> 1000 | G25: 12KG+/1CBM+ | H25: 22-28天签收
B26: 五区美中 | C26: PSC2 | D26: 6.6 | E26: 5.6 | F26: =E26*200 -> 1120 | G26: 12KG+/1CBM+ | H26: 24-30天签收
C27: AMA1/SAT1/SAT4/DFW6/FTW1/IAH3/IUTH/AFW5/FTW5 | D27: 6.8 | E27: 5.8 | F27: =E27*200 -> 1160 | G27: 12KG+/1CBM+ | H27: 24-30天签收
C28: FWA4/IND9/MDW2/IUSF | D28: 7.1 | E28: 6.1 | F28: =E28*200 -> 1220 | G28: 12KG+/1CBM+ | H28: 24-30天签收
C29: MEM1/MQJ1/RFD2/SLC2/BNA6 | D29: 7.1 | E29: 6.1 | F29: =E29*200 -> 1220 | G29: 12KG+/1CBM+ | H29: 24-30天签收
B30: 组合区 | C30: 仓库代码 | D30: 东莞仓(明星仓5号）福永仓（明星仓6号） | G30: 起收重量 | H30: 参考时效开船后 （无赔偿） | I30: 备注
D31: 50KG+ | E31: 100KG+ | F31: 按方包税1CBM+
B32: 六区美中 | C32: BNA2/DEN8/DEN2/FOE1/PPO4 | D32: 7.6 | E32: 6.6 | F32: =E32*200 -> 1320 | G32: 50KG+/1CBM+ | H32: 25-32天左右签收 | I32: 1.我司拒接一切敏感货物，此报价只收普货，如发现冲货，瞒报或者带电不备注行为在我司仓库查到的没收货物并罚款1万-5万元，若因冲货导致海关查验的罚款20万并追究其法律责任，和一切损失 . 2.不同区不可以合并报关(如：一区不能和二区合并报关) 3.按方渠道密度比最高（1CBM：363KGS）
C33: HOU8/ICT2/LIT2/MEM6/MKC4 | D33: 7.6 | E33: 6.6 | F33: =E33*200 -> 1320 | G33: 50KG+/1CBM+ | H33: 25-32天左右签收
C34: OKC2/STL3/STL4/FTW3/BFI3/GEG2 | D34: 7.6 | E34: 6.6 | F34: =E34*200 -> 1320 | G34: 50KG+/1CBM+ | H34: 25-32天左右签收
B35: 七区美中 | C35: CMH2/CMH3/IGQ2/IND2/LAN2 | D35: 7.9 | E35: 6.9 | F35: =E35*200 -> 1380 | G35: 50KG+/1CBM+ | H35: 25-32天左右签收
C36: JVL1/MDW6/ORD2/RFD4/STL6/DET1/DET2 | D36: 7.9 | E36: 6.9 | F36: =E36*200 -> 1380 | G36: 50KG+/1CBM+ | H36: 25-32天左右签收
B37: 组合区 | C37: 仓库代码 | D37: 东莞仓(明星仓5号）福永仓（明星仓6号） | G37: 起收重量 | H37: 参考时效开船后 （无赔偿） | I37: 1.我司拒接一切敏感货物，此报价只收普货，如发现冲货，瞒报或者带电不备注行为在我司仓库查到的没收货物并罚款1万-5万元，若因冲货导致海关查验的罚款20万并追究其法律责任，和一切损失 . 2.不同区不可以合并报关(如：一区不能和二区合并报关) 3.按方渠道密度比最高（1CBM：363KGS）
D38: 12KG+ | E38: 100KG+ | F38: 按方包税1CBM+
B39: 美东纽约专区 | C39: ABE8/AVP1/TEB9/RMN3 | D39: 8.5 | E39: 7.5 | F39: =E39*200 -> 1500 | G39: 12KG+/1CBM+ | H39: 25-32天签收
C40: ACY2/TEB3/TEB6/TTN2/ABE4/RDU4/HEA2/RDU2 | D40: 8.6 | E40: 7.6 | F40: =E40*200 -> 1520 | G40: 12KG+/1CBM+ | H40: 27-35天签收
C41: TEB4/SWF1/SWF2/MDT1/WBW2 | D41: 8.6 | E41: 7.6 | F41: =E41*200 -> 1520 | G41: 12KG+/1CBM+ | H41: 27-35天签收
C42: MDT4/PHL4/PHL5/PHL6/DCA6/ILG1 /IUSL/HIA1 | D42: 8.6 | E42: 7.6 | F42: =E42*200 -> 1520 | G42: 12KG+/1CBM+ | H42: 27-35天签收
C43: ORF2/RIC1/BOS7/ALB1/XLX1/XRI3 | D43: 8.6 | E43: 7.6 | F43: =E43*200 -> 1520 | G43: 12KG+/1CBM+ | H43: 27-35天签收
C44: PIT2/LBE1/CHO1/ AKR1 /IUST | D44: 8.6 | E44: 7.6 | F44: =E44*200 -> 1520 | G44: 12KG+/1CBM+ | H44: 27-35天签收
B45: 组合区 | C45: 仓库代码 | D45: 东莞仓(明星仓5号）福永仓（明星仓6号） | G45: 起收重量 | H45: 参考时效开船后（无赔偿） | I45: 备注
D46: 12KG+ | E46: 100KG+ | F46: 按方包税1CBM+
B47: 美东萨凡纳专区 | C47: CLT2/XAV3 | D47: 8.2 | E47: 7.2 | F47: =E47*200 -> 1440 | G47: 12KG+/1CBM+ | H47: 25-32天签收 | I47: 1.我司拒接一切敏感货物，此报价只收普货，如发现冲货，瞒报或者带电不备注行为在我司仓库查到的没收货物并罚款1万-5万元，若因冲货导致海关查验的罚款20万并追究其法律责任，和一切损失 . 2.不同区不可以合并报关(如：一区不能和二区合并报关) 3.按方渠道密度比最高（1CBM：363KGS）
C48: MGE3/SAV3/JAX3 | D48: 8.6 | E48: 7.6 | F48: =E48*200 -> 1520 | G48: 12KG+/1CBM+ | H48: 27-35天签收
C49: CLT3/RYY2/XLX6/CLT6/GSO1/GSP1 | D49: 8.6 | E49: 7.6 | F49: =E49*200 -> 1520 | G49: 12KG+/1CBM+ | H49: 27-35天签收
C50: TPA2/TPA3/TPA6/MCO2 | D50: 8.6 | E50: 7.6 | F50: =E50*200 -> 1520 | G50: 12KG+/1CBM+ | H50: 27-35天签收
C51: HSV1/HSV2/IUSR/PBI2/PBI3/TMB8/XPB2 | D51: 8.6 | E51: 7.6 | F51: =E51*200 -> 1520 | G51: 12KG+/1CBM+ | H51: 27-35天签收
B52: 仓库代码 | D52: 东莞仓(明星仓5号）福永仓（明星仓6号） | G52: 按方包税1CBM+ | I52: 备注
D53: 50KG+ | E53: 100KG+ | F53: 500KG+
B54: 美西海外仓自提 | D54: 4.1 | E54: 3.1 | F54: 3.1 | G54: =F54*200 -> 620 | I54: 出库费$15/托，不包含其他费用（如海外仓仓储费，贴标费，派送费等），如有产生实报实销
B55: 90-91商业地址 | D55: 咨询我司客服单独报价 | I55: 不包含其他费用（如海外仓仓储费，贴标费，超时费，二次派送费等额外产生的杂费）如有产生实报实销
B56: 后续关税每上调1%，将对应增加0.03元/kg的费用，按方对应增加6元/方，反之降关税每下调1%，将对应退0.03元/kg的费用，按方对应退6元/方 发货即默认此条款
B57: 50KG+实重比优惠：1:190减0.5、1:250减0.8、1:300减1、1:350减1.3、1:400减1.5、1:450减1.8、1:500及以上减2 比重减后最低1.5/KG
B59: 赔偿说明
B61: 1.提供POD 和预约号后 亚马逊的货物请客户在签收后5个工作日内查询限FBA后台是否上架，签收后15个工作日内提供货物未上架后台截图(需带有电脑屏幕右下角当下真实时间)至我司方可进入开查程序，超过20个工作日反馈不予受理和赔偿。若卡派出现丢件在我司规定时间内调查核实后我司予以赔偿。丢件赔偿标准如下： 一.快递派标准 （1） 提取前任何形式的丢件 按货值赔偿（提供货值证明）最高不超过40/kg 不退运费 （2）提取上网后丢件 统一按照每件100美金赔偿 不退运费 二.卡派标准 （包含任何形式的丢件） （1）按公斤计费的丢件 按货值赔偿（提供货值证明）最高不超过40RMB/kg 不退运费 （2）按方计费的丢件 按货值赔偿（提供货值证明）最高不超过600RMB/件 不退运费 2.货物如因自身包装问题造成破损或数量短少的，不作赔偿； 3.货物未如实申报、侵权或不符合当地法规禁止进口的导致海关扣货不作赔偿, 并且保留追究发件人因此带来对我司的损失赔偿责任； 4.因船期延误或清关延误等不可抗因素，不作赔偿； 5.易碎品不接受任何损坏赔偿； 6.如客户一旦交货到我司，则默认上述赔款条例，出货前请详细阅读此赔偿标准。
B63: 注意事项
B65: 1.以上价格为华南仓库交货价,材积货算:长*宽*高CM/6000
B66: 3.以上价格为普货产品到最终Amazon仓库的全部价格
B67: 4.可接单独报关件，加收150RMB/票，退税件贸易国只接中国和美国，其他国家或者中国香港无服务。
B68: 5.单票货物超过5个品名，需额外加收30RMB/个
B69: 6.订舱需提供出货模块资料，模块资料需提供详细品名，海关编码，材质，用途，图片，地址栏需认真仔细填写。
B70: 7.尺寸及重量：实重30-45KG加收1RMB/KG，(150/方）320CM<一长+两宽+两高<410CM加收5RMB/KG（800/方）尺寸及重量规则均叠加收费
B71: 8.FBA货物每件货物需贴2个或以上合格的FBA标签，我司提供贴标增值服务0.5RMB/标签。
... B73: 特别提示：如客户一旦交货到我司，我司默认客户已详细阅读此价格表备注内容及说明，并接受其条款的约束！

Sheet 华南特惠普船卡派
J3: =目录!H4 -> 明日之星华南价格表入仓执行日期2025/1/27
B4: 浙江明日之星供应链管理有限公司(深圳分公司）
B7: 华南特惠普船直送卡派（SML,HMM,WHL,YMM,TSL,SLS,ONE，CUL)(特惠线渠道有甩柜风险，赶时效货物建议选择OA)
B9: 组合区 | C9: 仓库代码 | D9: 东莞仓(明星仓5号）福永仓（明星仓6号） | G9: 起收重量 | H9: 开船后第二天 开始计算时效签收时效 | I9: 备注
D10: 12KG+ | E10: 50KG+ | F10: 按方包税1CBM+
B11: 洛杉矶特价 | C11: ONT8/LGB8/LAX9/SBD1 | D11: 3.9 | E11: 2.9 | F11: =E11*200 -> 580 | G11: 12KG+/1CBM+ | H11: 21-28天签收 | I11: 此渠道报价为直送柜不接受拦截，若需要拦截每票2200美金/票，不接受合并报关。单件尺寸不超63cm，在截单前到货的保证装走，不集货，不延船期!
C12: GYR2/GYR3/LAS1/SMF3/SCK4/VGT2 | D12: 4.4 | E12: 3.4 | F12: =E12*200 -> 680 | G12: 12KG+/1CBM+ | H12: 21-28天签收
B14: 华南特惠普船卡派（SML,HMM,WHL,YMM,TSL,SLS,ONE，CUL)(特惠线渠道有甩柜风险，赶时效货物建议选择OA)
B16: 组合区 | C16: 仓库代码 | D16: 东莞仓(明星仓5号）福永仓（明星仓6号） | G16: 起收重量 | H16: 参考时效开船后 （无赔偿） | I16: 备注
D17: 12KG+ | E17: 50KG+ | F17: 按方包税1CBM+
B18: 一区美西 | C18: POC1/POC3/ POC2 | D18: 4.2 | E18: 3.2 | F18: =E18*200 -> 640 | G18: 12KG+/1CBM+ | H18: 24-30天签收 | I18: 1.我司拒接一切敏感货物，此报价只收普货，如发现冲货，瞒报或者带电不备注行为在我司仓库查到的没收货物并罚款1万-5万元，若因冲货导致海关查验的罚款20万并追究其法律责任，和一切损失 . 2.不同区不可以合并报关(如：一区不能和二区合并报关) 3.按方渠道密度比最高（1CBM：363KGS）
B19: 二区美西 | C19: LGB4/LGB9/LGB6/SBD2 /SNA4/ XLX7/JOT1 | D19: 4.4 | E19: 3.4 | F19: =E19*200 -> 680 | G19: 12KG+/1CBM+ | H19: 24-30天签收
C20: IUSQ/IUSJ/IUSP/IUTI/IUSW/IUTE/PSP3 | D20: 4.4 | E20: 3.4 | F20: =E20*200 -> 680 | G20: 12KG+/1CBM+ | H20: 24-30天签收
B21: 三区美西 | C21: SCK8/MIT2/HLI2/TCY2/TCY1/MCC1 | D21: 4.9 | E21: 3.9 | F21: =E21*200 -> 780 | G21: 12KG+/1CBM+ | H21: 24-30天签收
C22: GEU3/GEU5/GEU2/QXY5/QXY8 | D22: 4.9 | E22: 3.9 | F22: =E22*200 -> 780 | G22: 12KG+/1CBM+ | H22: 24-30天签收
B23: 四区美西 | C23: SJC7/FAT2/SCK1/ MCE1 | D23: 4.9 | E23: 3.9 | F23: =E23*200 -> 780 | G23: 12KG+/1CBM+ | H23: 24-30天签收
C24: PHX5/PHX7/LAS6/OAK3/SMF6 | D24: 4.9 | E24: 3.9 | F24: =E24*200 -> 780 | G24: 12KG+/1CBM+ | H24: 24-30天签收
C25: ABQ2 | D25: 5.7 | E25: 4.7 | F25: =E25*200 -> 940 | G25: 12KG+/1CBM+ | H25: 24-30天签收
B26: 五区美中 | C26: PSC2 | D26: 6.3 | E26: 5.3 | F26: =E26*200 -> 1060 | G26: 12KG+/1CBM+ | H26: 26-32天签收
C27: AMA1/SAT1/SAT4/DFW6/FTW1/IAH3/IUTH/AFW5/FTW5 | D27: 6.5 | E27: 5.5 | F27: =E27*200 -> 1100 | G27: 12KG+/1CBM+ | H27: 26-32天签收
C28: FWA4/IND9/MDW2/IUSF | D28: 6.8 | E28: 5.8 | F28: =E28*200 -> 1160 | G28: 12KG+/1CBM+ | H28: 26-32天签收
C29: MEM1/MQJ1/RFD2/SLC2/BNA6 | D29: 6.8 | E29: 5.8 | F29: =E29*200 -> 1160 | G29: 12KG+/1CBM+ | H29: 26-32天签收
B30: 组合区 | C30: 仓库代码 | D30: 东莞仓(明星仓5号）福永仓（明星仓6号） | G30: 起收重量 | H30: 参考时效开船后 （无赔偿） | I30: 备注
D31: 50KG+ | E31: 100KG+ | F31: 按方包税1CBM+
B32: 六区美中 | C32: BNA2/DEN8/DEN2/FOE1/PPO4 | D32: 7.3 | E32: 6.3 | F32: =E32*200 -> 1260 | G32: 50KG+/1CBM+ | H32: 27-34天左右签收 | I32: 1.我司拒接一切敏感货物，此报价只收普货，如发现冲货，瞒报或者带电不备注行为在我司仓库查到的没收货物并罚款1000-50000RMB，若因冲货导致海关查验的罚款20万并追究其法律责任，和一切损失 . 2.不同区不可以合并报关(如：一区不能和二区合并报关) 3.按方渠道密度比最高（1CBM：363KGS）
C33: HOU8/ICT2/LIT2/MEM6/MKC4 | D33: 7.3 | E33: 6.3 | F33: =E33*200 -> 1260 | G33: 50KG+/1CBM+ | H33: 27-34天左右签收
C34: OKC2/STL3/STL4/FTW3/BFI3/GEG2 | D34: 7.3 | E34: 6.3 | F34: =E34*200 -> 1260 | G34: 50KG+/1CBM+ | H34: 27-34天左右签收
B35: 七区美中 | C35: CMH2/CMH3/IGQ2/IND2/LAN2 | D35: 7.6 | E35: 6.6 | F35: =E35*200 -> 1320 | G35: 50KG+/1CBM+ | H35: 27-34天左右签收
C36: JVL1/MDW6/ORD2/RFD4/STL6/DET1/DET2 | D36: 7.6 | E36: 6.6 | F36: =E36*200 -> 1320 | G36: 50KG+/1CBM+ | H36: 27-34天左右签收
B37: 组合区 | C37: 仓库代码 | D37: 东莞仓(明星仓5号）福永仓（明星仓6号） | G37: 起收重量 | H37: 参考时效开船后 （无赔偿） | I37: 1.我司拒接一切敏感货物，此报价只收普货，如发现冲货，瞒报或者带电不备注行为在我司仓库查到的没收货物并罚款1万-5万元，若因冲货导致海关查验的罚款20万并追究其法律责任，和一切损失 . 2.不同区不可以合并报关(如：一区不能和二区合并报关) 3.按方渠道密度比最高（1CBM：363KGS）
D38: 12KG+ | E38: 100KG+ | F38: 按方包税1CBM+
B39: 美东纽约专区 | C39: ABE8/AVP1/TEB9/RMN3 | D39: 8.2 | E39: 7.2 | F39: =E39*200 -> 1440 | G39: 12KG+/1CBM+ | H39: 27-36天左右签收
C40: ACY2/TEB3/TEB6/TTN2/ABE4/RDU4/HEA2/RDU2 | D40: 8.3 | E40: 7.3 | F40: =E40*200 -> 1460 | G40: 12KG+/1CBM+ | H40: 27-36天左右签收
C41: TEB4/SWF1/SWF2/MDT1/WBW2 | D41: 8.3 | E41: 7.3 | F41: =E41*200 -> 1460 | G41: 12KG+/1CBM+ | H41: 27-36天左右签收
C42: MDT4/PHL4/PHL5/PHL6/DCA6/ILG1 /IUSL/HIA1 | D42: 8.3 | E42: 7.3 | F42: =E42*200 -> 1460 | G42: 12KG+/1CBM+ | H42: 27-36天左右签收
C43: ORF2/RIC1/BOS7/ALB1/XLX1/XRI3 | D43: 8.3 | E43: 7.3 | F43: =E43*200 -> 1460 | G43: 12KG+/1CBM+ | H43: 27-36天左右签收
C44: PIT2/LBE1/CHO1/ AKR1 /IUST | D44: 8.3 | E44: 7.3 | F44: =E44*200 -> 1460 | G44: 12KG+/1CBM+ | H44: 27-36天左右签收
B45: 组合区 | C45: 仓库代码 | D45: 东莞仓(明星仓5号）福永仓（明星仓6号） | G45: 起收重量 | H45: 参考时效开船后（无赔偿） | I45: 备注
D46: 12KG+ | E46: 100KG+ | F46: 按方包税1CBM+
B47: 美东萨凡纳专区 | C47: CLT2/XAV3 | D47: 7.9 | E47: 6.9 | F47: =E47*200 -> 1380 | G47: 12KG+/1CBM+ | H47: 27-36天左右签收 | I47: 1.我司拒接一切敏感货物，此报价只收普货，如发现冲货，瞒报或者带电不备注行为在我司仓库查到的没收货物并罚款1万-5万元，若因冲货导致海关查验的罚款20万并追究其法律责任，和一切损失 . 2.不同区不可以合并报关(如：一区不能和二区合并报关) 3.按方渠道密度比最高（1CBM：363KGS）
C48: MGE3/SAV3/JAX3 | D48: 8.3 | E48: 7.3 | F48: =E48*200 -> 1460 | G48: 12KG+/1CBM+ | H48: 27-36天左右签收
C49: CLT3/RYY2/XLX6/CLT6/GSO1/GSP1 | D49: 8.3 | E49: 7.3 | F49: =E49*200 -> 1460 | G49: 12KG+/1CBM+ | H49: 27-36天左右签收
C50: TPA2/TPA3/TPA6/MCO2 | D50: 8.3 | E50: 7.3 | F50: =E50*200 -> 1460 | G50: 12KG+/1CBM+ | H50: 27-36天左右签收
C51: HSV1/HSV2/IUSR/PBI2/PBI3/TMB8/XPB2 | D51: 8.3 | E51: 7.3 | F51: =E51*200 -> 1460 | G51: 12KG+/1CBM+ | H51: 27-36天左右签收
B52: 仓库代码 | D52: 东莞仓(明星仓5号）福永仓（明星仓6号） | G52: 按方包税1CBM+ | I52: 备注
D53: 50KG+ | E53: 100KG+ | F53: 500KG+
B54: 美西海外仓自提 | D54: 3.9 | E54: 2.9 | F54: 2.9 | G54: =F54*200 -> 580 | I54: 出库费$15/托，不包含其他费用（如海外仓仓储费，贴标费，派送费等），如有产生实报实销
B55: 90-91商业地址 | D55: 咨询我司客服单独报价 | I55: 不包含其他费用（如海外仓仓储费，贴标费，超时费，二次派送费等额外产生的杂费）如有产生实报实销
B56: 后续关税每上调1%，将对应增加0.03元/kg的费用，按方对应增加6元/方，反之降关税每下调1%，将对应退0.03元/kg的费用，按方对应退6元/方 发货即默认此条款
B57: 50KG+实重比优惠：1:190减0.5、1:250减0.8、1:300减1、1:350减1.3、1:400减1.5、1:450减1.8、1:500及以上减2 比重减后最低1.5/KG
B59: 赔偿说明
B61: 1.提供POD 和预约号后 亚马逊的货物请客户在签收后5个工作日内查询限FBA后台是否上架，签收后15个工作日内提供货物未上架后台截图(需带有电脑屏幕右下角当下真实时间)至我司方可进入开查程序，超过20个工作日反馈不予受理和赔偿。若卡派出现丢件在我司规定时间内调查核实后我司予以赔偿。丢件赔偿标准如下： 一.快递派标准 （1） 提取前任何形式的丢件 按货值赔偿（提供货值证明）最高不超过40/kg 不退运费 （2）提取上网后丢件 统一按照每件100美金赔偿 不退运费 二.卡派标准 （包含任何形式的丢件） （1）按公斤计费的丢件 按货值赔偿（提供货值证明）最高不超过40RMB/kg 不退运费 （2）按方计费的丢件 按货值赔偿（提供货值证明）最高不超过600RMB/件 不退运费 2.货物如因自身包装问题造成破损或数量短少的，不作赔偿； 3.货物未如实申报、侵权或不符合当地法规禁止进口的导致海关扣货不作赔偿, 并且保留追究发件人因此带来对我司的损失赔偿责任； 4.因船期延误或清关延误等不可抗因素，不作赔偿； 5.易碎品不接受任何损坏赔偿； 6.如客户一旦交货到我司，则默认上述赔款条例，出货前请详细阅读此赔偿标准。
B63: 注意事项
B65: 1.以上价格为华南仓库交货价,材积货算:长*宽*高CM/6000 。
B66: 3.以上价格为普货产品到最终Amazon仓库的全部价格
B67: 4.可接单独报关件，加收150RMB/票，退税件贸易国只接中国和美国，其他国家或者中国香港无服务。
B68: 5.单票货物超过5个品名，需额外加收30RMB/个。
B69: 6.订舱需提供出货模块资料，模块资料需提供详细品名，海关编码，材质，用途，图片，地址栏需认真仔细填写。
B70: 7.尺寸及重量：实重30-45KG加收1RMB/KG，(150/方）320CM<一长+两宽+两高<410CM加收5RMB/KG（800/方）尺寸及重量规则均叠加收费
B71: 8.FBA货物每件货物需贴2个或以上合格的FBA标签，我司提供贴标增值服务0.5RMB/标签。
... B73: 特别提示：如客户一旦交货到我司，我司默认客户已详细阅读此价格表备注内容及说明，并接受其条款的约束！

Sheet 华南西雅图普船卡派-暂停
B2: 浙江明日之星供应链管理有限公司
B5: 华南西雅图普船卡派（OA,SML统配）-该渠道暂停 对应亚马逊仓库地址建议走洛杉矶港口！！！
G6: =目录!H4 -> 明日之星华南价格表入仓执行日期2025/1/27
B7: 仓库代码 | C7: 东莞仓(明星仓5号）福永仓（明星仓6号） | F7: 起收重量 | G7: 开船后第二天 开始计算时效签收时效 | H7: 备注
C8: 12KG+ | D8: 50KG+ | E8: 按方包税1CBM+
B9: PSC2 | C9: / | D9: / | E9: =D9*200 -> #VALUE! | F9: 12KG+/1CBM+ | G9: 35-40天左右签收 | H9: 此报价只收普货，如发现冲货，瞒报或者带电不备注行为没收货物并罚款10000-50000RMB.
B10: BFI3 | C10: / | D10: / | E10: =D10*200 -> #VALUE! | F10: 12KG+/1CBM+ | G10: 35-40天左右签收
B11: PDX7/PDX6 | C11: / | D11: / | E11: =D11*200 -> #VALUE! | F11: 12KG+/1CBM+ | G11: 35-40天左右签收
B12: GEG2 | C12: / | D12: / | E12: =D12*200 -> #VALUE! | F12: 12KG+/1CBM+ | G12: 35-40天左右签收
B13: 后续关税每上调1%，将对应增加0.03元/kg的费用，按方对应增加6元/方，反之降关税每下调1%，将对应退0.03元/kg的费用，按方对应退6元/方 发货即默认此条款
B14: 50KG+实重比优惠：1:190减0.5、1:250减0.8、1:300减1、1:350减1.3、1:400减1.5、1:450减1.8、1:500及以上减2 比重减后最低1.5/KG
B16: 计费规则
B18: 计费规则：单边超过200CM拒收； 亚马逊地址单件实重超过30KG小于45KG货物加收RMB1/KG； 320CM<一长+两宽+两高<410CM加收5RMB/KG 非亚马逊地址无超重费，超长费正常收取。
B19: 请注意：按照美国海关要求，所有中国出口美国货物的外包装及货物内包装（或者货物本身）必须有“MADE IN CHINA”的标记，否则一旦被查到将会被要求在美国海关的监管下逐件贴标，限期未完成者将会被处以至少为发票金额的6倍的罚款，由此导致的时效延误及一切费用概由客人承担。
B21: 赔偿说明
B23: 1.提供POD 和预约号后 亚马逊的货物请客户在签收后5个工作日内查询限FBA后台是否上架，签收后15个工作日内提供货物未上架后台截图(需带有电脑屏幕右下角当下真实时间)至我司方可进入开查程序，超过20个工作日反馈不予受理和赔偿。若卡派出现丢件在我司规定时间内调查核实后我司予以赔偿。丢件赔偿标准如下： 一.快递派标准 （1） 提取前任何形式的丢件 按货值赔偿（提供货值证明）最高不超过40/kg 不退运费 （2）提取上网后丢件 统一按照每件100美金赔偿 不退运费 二.卡派标准 （包含任何形式的丢件） （1）按公斤计费的丢件 按货值赔偿（提供货值证明）最高不超过40RMB/kg 不退运费 （2）按方计费的丢件 按货值赔偿（提供货值证明）最高不超过600RMB/件 不退运费 2.货物如因自身包装问题造成破损或数量短少的，不作赔偿； 3.货物未如实申报、侵权或不符合当地法规禁止进口的导致海关扣货不作赔偿, 并且保留追究发件人因此带来对我司的损失赔偿责任； 4.因船期延误或清关延误等不可抗因素，不作赔偿； 5.易碎品不接受任何损坏赔偿； 6.如客户一旦交货到我司，则默认上述赔款条例，出货前请详细阅读此赔偿标准。
B25: 注意事项
B27: 1.以上价格为华南仓库交货价,材积货算:长*宽*高CM/6000 。
B28: 3.以上价格为普货产品到最终Amazon仓库的全部价格
B29: 4.可接单独报关件，加收150RMB/票，退税件贸易国只接中国和美国，其他国家或者中国香港无服务。
B30: 5.单票货物超过5个品名，需额外加收30RMB/个。
... B35: 特别提示：如客户一旦交货到我司，我司默认客户已详细阅读此价格表备注内容及说明，并接受其条款的约束！

Sheet 华南奥克兰普船卡派
I2: =目录!H4 -> 明日之星华南价格表入仓执行日期2025/1/27
B3: 浙江明日之星供应链管理有限公司
B6: 华南奥克兰直送卡派（EXX航线和WHL,OA统配）
B8: 渠道产品 | C8: 仓库代码 | E8: 东莞仓(明星仓5号）福永仓（明星仓6号） | H8: 起收重量 | I8: 开船后第二天 开始计算时效签收时效 | J8: 备注
E9: 12KG+ | F9: 50KG+ | G9: 按方包税1CBM+
B10: 奥克兰特惠 | C10: SMF3/SCK4/SJC7/TCY1/TCY2 | E10: 3.8 | F10: 3.3 | G10: =F10*200 -> 660 | H10: 12KG+/1cbm+ | I10: 23-28天左右签收 | J10: 此渠道报价为直送柜不接受拦截，若需要拦截每票2200美金/票，不接受合并报关。单件尺寸不超63cm，在截单前到货的保证装走，不集货，不延船期。
B12: 华南奥克兰拆柜卡派 （EXX航线和WHL,OA统配）
B14: 仓库代码 | D14: 东莞仓(明星仓5号）福永仓（明星仓6号） | G14: 开船后第二天开始计算 | J14: 备注
D15: 12KG+ | E15: 50KG+ | F15: 按方包税1CBM+
B16: MCC1（95742） | D16: 4.1 | E16: 3.6 | F16: =E16*200 -> 720 | G16: 25-30天左右
B17: SCK8（94561） | D17: 4.1 | E17: 3.6 | F17: =E17*200 -> 720 | G17: 25-30天左右
B18: SCK3（95336） | D18: 4.3 | E18: 3.8 | F18: =E18*200 -> 760 | G18: 25-30天左右
B19: OAK3（95363） | D19: 4.3 | E19: 3.8 | F19: =E19*200 -> 760 | G19: 25-30天左右
B20: SCK1（95215） | D20: 4.3 | E20: 3.8 | F20: =E20*200 -> 760 | G20: 25-30天左右
B21: MCE1（95380） | D21: 4.3 | E21: 3.8 | F21: =E21*200 -> 760 | G21: 25-30天左右
B22: SMF6（95835） | D22: 4.5 | E22: 4 | F22: =E22*200 -> 800 | G22: 25-30天左右
B23: HLI2 (95023 ) | D23: 4.5 | E23: 4 | F23: =E23*200 -> 800 | G23: 25-30天左右
B24: SMF7 (95688) | D24: 4.5 | E24: 4 | F24: =E24*200 -> 800 | G24: 25-30天左右
B25: FAT2（93725) | D25: 4.7 | E25: 4.2 | F25: =E25*200 -> 840 | G25: 25-30天左右
B26: SMF1（95688）(沃尔玛） | D26: 4.7 | E26: 4.2 | F26: =E26*200 -> 840 | G26: 25-30天左右
C28: 东莞仓(明星仓5号）福永仓（明星仓6号） | G28: 备注
C29: 50KG+ | D29: 100KG+ | E29: 500KG+ | F29: 按方包税1cbm+
B30: 美西奥克兰海外仓自提 | C30: 4.3 | D30: 3.3 | E30: 3.3 | F30: =D30*200 -> 660 | G30: 出库费$15/托，不包含其他费用（如海外仓仓储费，贴标费，派送费等），如有产生实报实销
B31: 后续关税每上调1%，将对应增加0.03元/kg的费用，按方对应增加6元/方，反之降关税每下调1%，将对应退0.03元/kg的费用，按方对应退6元/方 发货即默认此条款
B32: 50KG+实重比优惠：1:190减0.5、1:250减0.8、1:300减1、1:350减1.3、1:400减1.5、1:450减1.8、1:500及以上减2 比重减后最低1.5/KG
B34: 赔偿说明
B36: 1.提供POD 和预约号后 亚马逊的货物请客户在签收后5个工作日内查询限FBA后台是否上架，签收后15个工作日内提供货物未上架后台截图(需带有电脑屏幕右下角当下真实时间)至我司方可进入开查程序，超过20个工作日反馈不予受理和赔偿。若卡派出现丢件在我司规定时间内调查核实后我司予以赔偿。丢件赔偿标准如下： 一.快递派标准 （1） 提取前任何形式的丢件 按货值赔偿（提供货值证明）最高不超过40/kg 不退运费 （2）提取上网后丢件 统一按照每件100美金赔偿 不退运费 二.卡派标准 （包含任何形式的丢件） （1）按公斤计费的丢件 按货值赔偿（提供货值证明）最高不超过40RMB/kg 不退运费 （2）按方计费的丢件 按货值赔偿（提供货值证明）最高不超过600RMB/件 不退运费 2.货物如因自身包装问题造成破损或数量短少的，不作赔偿； 3.货物未如实申报、侵权或不符合当地法规禁止进口的导致海关扣货不作赔偿, 并且保留追究发件人因此带来对我司的损失赔偿责任； 4.因船期延误或清关延误等不可抗因素，不作赔偿； 5.易碎品不接受任何损坏赔偿； 6.如客户一旦交货到我司，则默认上述赔款条例，出货前请详细阅读此赔偿标准。
B38: 注意事项
B40: 1.以上价格为华南仓库交货价,材积货算:长*宽*高CM/6000 。
B41: 3.以上价格为普货产品到最终Amazon仓库的全部价格
B42: 4.可接单独报关件，加收150RMB/票，退税件贸易国只接中国和美国，其他国家或者中国香港无服务。
B43: 5.单票货物超过5个品名，需额外加收30RMB/个。
B44: 6.订舱需提供出货模块资料，模块资料需提供详细品名，海关编码，材质，用途，图片，地址栏需认真仔细填写。
B45: 7.尺寸及重量：实重30-45KG加收1RMB/KG，(150/方）320CM<一长+两宽+两高<410CM加收5RMB/KG（800/方）尺寸及重量规则均叠加收费
B46: 8.FBA货物每件货物需贴2个或以上合格的FBA标签，我司提供贴标增值服务0.5RMB/标签。
... B48: 特别提示：如客户一旦交货到我司，我司默认客户已详细阅读此价格表备注内容及说明，并接受其条款的约束！

Sheet 华南芝加哥普船卡派
B3: 浙江明日之星供应链管理有限公司
B5: 华南芝加哥直送卡派 （CMA/ZIM/SML/OA统配航线到LA转火车）
H6: =目录!H4 -> 明日之星华南价格表入仓执行日期2025/1/27
B7: 渠道产品 | C7: 仓库代码 | D7: 东莞仓(明星仓5号）福永仓（明星仓6号） | G7: 起收重量 | H7: 开船后第二天 开始计算时效签收时效 | I7: 备注
D8: 12KG+ | E8: 50KG+ | F8: 按方包税1CBM+
B9: 芝加哥特惠卡派 | C9: MDW2 | D9: 6 | E9: 5 | F9: =E9*200 -> 1000 | G9: 12kg+/1CBM+ | H9: 26-31天左右签收 | I9: 此渠道报价为直送柜不接受拦截，若需要拦截每票2200美金/票，不接受合并报关。单件尺寸不超63cm，单件实重不超23kg
C10: IND9/FWA4 | D10: 6.3 | E10: 5.3 | F10: =E10*200 -> 1060 | G10: 12kg+/1CBM+ | H10: 26-31天左右签收
B12: 华南芝加哥普船卡派 （CMA/ZIM/SML/OA统配航线到LA转火车）
B14: 芝加哥一区 | C14: MDW2/ORD2/IGQ2/MDW6 | D14: 6.3 | E14: 5.3 | F14: =E14*200 -> 1060 | G14: 12kg+/1CBM+ | H14: 32-40天左右签收 | I14: 此报价为拆柜派送可以合并，报关此报价只收普货，如发现冲货，瞒报或者带电不备注行为没收货物并罚款1000-50000RMB. 不同区不能合并报关
C15: MDW9/RFD2/RFD4/JVL1/ 沃尔玛---ORD1S | D15: 6.3 | E15: 5.3 | F15: =E15*200 -> 1060 | G15: 12kg+/1CBM+ | H15: 32-40天左右签收
B16: 芝加哥二区 | C16: IND9/MQJ2/STL4/IND2/IND4/IND5/ MQJ1/PPO4/LAN2 | D16: 6.7 | E16: 5.7 | F16: =E16*200 -> 1140 | G16: 12kg+/1CBM+ | H16: 32-40天左右签收
C17: 沃尔玛---IND2/沃尔玛---IND3/沃尔玛---IND2N | D17: 6.8 | E17: 5.8 | F17: =E17*200 -> 1160 | G17: 12kg+/1CBM+ | H17: 32-40天左右签收
B18: 芝加哥三区 | C18: DET1/DET2/CMH2/CMH3/CMH7 | D18: 7 | E18: 6 | F18: =E18*200 -> 1200 | G18: 12kg+/1CBM+ | H18: 32-40天左右签收
B19: 芝加哥四区 | C19: FOE1/MKC4/MCI3/STL3/MEM1/MEM6 | D19: 7.5 | E19: 6.5 | F19: =E19*200 -> 1300 | G19: 12kg+/1CBM+ | H19: 32-40天左右签收
C20: 沃尔玛---KS1/沃尔玛---MCI1N | D20: 7.7 | E20: 6.7 | F20: =E20*200 -> 1340 | G20: 12kg+/1CBM+ | H20: 32-40天左右签收
B21: 芝加哥留仓自提 | C21: 留仓自提 | D21: 6 | E21: 5 | F21: =E21*200 -> 1000 | G21: 12kg+/1CBM+ | H21: 32-40天左右签收
B22: 后续关税每上调1%，将对应增加0.03元/kg的费用，按方对应增加6元/方，反之降关税每下调1%，将对应退0.03元/kg的费用，按方对应退6元/方 发货即默认此条款
B23: 50KG+实重比优惠：1:190减0.5、1:250减0.8、1:300减1、1:350减1.3、1:400减1.5、1:450减1.8、1:500及以上减2 比重减后最低1.5/KG
B25: 计费规则
B27: 计费规则：单边超过200CM拒收； 亚马逊地址单件实重超过30KG小于45KG货物加收RMB1/KG； 320CM<一长+两宽+两高<410CM加收5RMB/KG 非亚马逊地址无超重费，超长费正常收取。
B28: 请注意：按照美国海关要求，所有中国出口美国货物的外包装及货物内包装（或者货物本身）必须有“MADE IN CHINA”的标记，否则一旦被查到将会被要求在美国海关的监管下逐件贴标，限期未完成者将会被处以至少为发票金额的6倍的罚款，由此导致的时效延误及一切费用概由客人承担。
B30: 赔偿说明
B32: 1.提供POD 和预约号后 亚马逊的货物请客户在签收后5个工作日内查询限FBA后台是否上架，签收后15个工作日内提供货物未上架后台截图(需带有电脑屏幕右下角当下真实时间)至我司方可进入开查程序，超过20个工作日反馈不予受理和赔偿。若卡派出现丢件在我司规定时间内调查核实后我司予以赔偿。丢件赔偿标准如下： 一.快递派标准 （1） 提取前任何形式的丢件 按货值赔偿（提供货值证明）最高不超过40/kg 不退运费 （2）提取上网后丢件 统一按照每件100美金赔偿 不退运费 二.卡派标准 （包含任何形式的丢件） （1）按公斤计费的丢件 按货值赔偿（提供货值证明）最高不超过40RMB/kg 不退运费 （2）按方计费的丢件 按货值赔偿（提供货值证明）最高不超过600RMB/件 不退运费 2.货物如因自身包装问题造成破损或数量短少的，不作赔偿； 3.货物未如实申报、侵权或不符合当地法规禁止进口的导致海关扣货不作赔偿, 并且保留追究发件人因此带来对我司的损失赔偿责任； 4.因船期延误或清关延误等不可抗因素，不作赔偿； 5.易碎品不接受任何损坏赔偿； 6.如客户一旦交货到我司，则默认上述赔款条例，出货前请详细阅读此赔偿标准。
B34: 注意事项
B36: 1.以上价格为华南仓库交货价,材积货算:长*宽*高CM/6000 。
B37: 3.以上价格为普货产品到最终Amazon仓库的全部价格
B38: 4.可接单独报关件，加收150RMB/票，退税件贸易国只接中国和美国，其他国家或者中国香港无服务。
B39: 5.单票货物超过5个品名，需额外加收30RMB/个。
... B44: 特别提示：如客户一旦交货到我司，我司默认客户已详细阅读此价格表备注内容及说明，并接受其条款的约束！

Sheet 华南休斯顿普船卡派
H3: =目录!H4 -> 明日之星华南价格表入仓执行日期2025/1/27
B4: 浙江明日之星供应链管理有限公司
B6: 华南休斯顿普船卡派
B8: 渠道产品 | C8: 仓库代码 | D8: 东莞仓(明星仓5号）福永仓（明星仓6号） | G8: 开船后第二天 开始计算时效签收时效 | H8: 备注
D9: 12KG+ | E9: 50KG+ | F9: 按方包税1CBM+
B10: 休斯顿专线拆柜派送 | C10: HOU8/HOU7/HOU3/HOU2/HOU1/IAH3 | D10: 5.1 | E10: 4.1 | F10: =E10*200 -> 820 | G10: 32-40天左右签收 | H10: 此报价为拆柜派送可以合并，报关此报价只收普货，如发现冲货，瞒报或者带电不备注行为没收货物并罚款1000-50000RMB.
C11: FTW9/FTW1/FTW5/FTW3/SAT1/FTW2/IUSF/DFW7/DFW6/DAL3/SAT6/SAT4/IUTH/AFW5 | D11: 5.9 | E11: 4.9 | F11: =E11*200 -> 980 | G11: 32-40天左右签收
C12: MEM6/MEM1/LFT1/AMA1/OKC2/LIT2/ ICT2/FOE1 | D12: 6.5 | E12: 5.5 | F12: =E12*200 -> 1100 | G12: 32-40天左右签收
B13: 休斯顿留仓自提 | D13: 5.1 | E13: 4.1 | F13: =E13*200 -> 820 | G13: 32-40天左右签收
B14: 后续关税每上调1%，将对应增加0.03元/kg的费用，按方对应增加6元/方，反之降关税每下调1%，将对应退0.03元/kg的费用，按方对应退6元/方 发货即默认此条款
B15: 50KG+实重比优惠：1:190减0.5、1:250减0.8、1:300减1、1:350减1.3、1:400减1.5、1:450减1.8、1:500及以上减2 比重减后最低1.5/KG
B17: 计费规则
B19: 计费规则：单边超过200CM拒收； 亚马逊地址单件实重超过30KG小于45KG货物加收RMB1/KG； 320CM<一长+两宽+两高<410CM加收5RMB/KG 非亚马逊地址无超重费，超长费正常收取。
B20: 请注意：按照美国海关要求，所有中国出口美国货物的外包装及货物内包装（或者货物本身）必须有“MADE IN CHINA”的标记，否则一旦被查到将会被要求在美国海关的监管下逐件贴标，限期未完成者将会被处以至少为发票金额的6倍的罚款，由此导致的时效延误及一切费用概由客人承担。
B22: 赔偿说明
B24: 1.提供POD 和预约号后 亚马逊的货物请客户在签收后5个工作日内查询限FBA后台是否上架，签收后15个工作日内提供货物未上架后台截图(需带有电脑屏幕右下角当下真实时间)至我司方可进入开查程序，超过20个工作日反馈不予受理和赔偿。若卡派出现丢件在我司规定时间内调查核实后我司予以赔偿。丢件赔偿标准如下： 一.快递派标准 （1） 提取前任何形式的丢件 按货值赔偿（提供货值证明）最高不超过40/kg 不退运费 （2）提取上网后丢件 统一按照每件100美金赔偿 不退运费 二.卡派标准 （包含任何形式的丢件） （1）按公斤计费的丢件 按货值赔偿（提供货值证明）最高不超过40RMB/kg 不退运费 （2）按方计费的丢件 按货值赔偿（提供货值证明）最高不超过600RMB/件 不退运费 2.货物如因自身包装问题造成破损或数量短少的，不作赔偿； 3.货物未如实申报、侵权或不符合当地法规禁止进口的导致海关扣货不作赔偿, 并且保留追究发件人因此带来对我司的损失赔偿责任； 4.因船期延误或清关延误等不可抗因素，不作赔偿； 5.易碎品不接受任何损坏赔偿； 6.如客户一旦交货到我司，则默认上述赔款条例，出货前请详细阅读此赔偿标准。
B26: 注意事项
B28: 1.以上价格为华南仓库交货价,材积货算:长*宽*高CM/6000 。
B29: 3.以上价格为普货产品到最终Amazon仓库的全部价格
B30: 4.可接单独报关件，加收150RMB/票，退税件贸易国只接中国和美国，其他国家或者中国香港无服务。
B31: 5.单票货物超过5个品名，需额外加收30RMB/个。
... B36: 特别提示：如客户一旦交货到我司，我司默认客户已详细阅读此价格表备注内容及说明，并接受其条款的约束！

Sheet 华南萨凡纳普船卡派
B3: 浙江明日之星供应链管理有限公司
B4: =目录!H4 -> 明日之星华南价格表入仓执行日期2025/1/27
B5: 华南萨凡纳普船卡派
B7: 仓库代码 | C7: 东莞仓(明星仓5号）福永仓（明星仓5号） | F7: 起收重量 | G7: 开船后第二天 开始计算时效签收时效 | H7: 备注
C8: 12KG+ | D8: 50KG+ | E8: 按方包税1CBM+
B9: XLX6/SAV3/MGE3/CLT2/ JAX3 | C9: 5.3 | D9: 4.3 | E9: =D9*200 -> 860 | F9: 12KG+/1CBM+ | G9: 35-45天左右签收 | H9: 此报价只收普货，如发现冲货，瞒报或者带电不备注行为没收货物并罚款1000-50000RMB.
B10: GSP1/RYY2/IUSR/RDU4/ATL8/MGE1/CLT3/XAV3 | C10: 5.7 | D10: 4.7 | E10: =D10*200 -> 940 | F10: 12KG+/1CBM+ | G10: 35-45天左右签收
B11: GSO1/CLT6/CLT4/RDU2/MCO2 | C11: 6 | D11: 5 | E11: =D11*200 -> 1000 | F11: 12KG+/1CBM+ | G11: 35-45天左右签收
B12: TPA2/TPA3/TPA6/ATL2 | C12: 6 | D12: 5 | E12: =D12*200 -> 1000 | F12: 12KG+/1CBM+ | G12: 35-45天左右签收
B13: CHA2/BNA2/HSV1/HSV2/PBI3 /PBI2/XPB2/BNA6 | C13: 6.3 | D13: 5.3 | E13: =D13*200 -> 1060 | F13: 12KG+/1CBM+ | G13: 35-45天左右签收
B14: MEM8/MQY1/TMB8 | C14: 6.3 | D14: 5.3 | E14: =D14*200 -> 1060 | F14: 12KG+/1CBM+ | G14: 35-45天左右签收
B15: Walmart仓点（仓库代码需填写对应的仓点）
B16: Wal-MCO2/Wal-MEM1s | C16: 6.2 | D16: 5.2 | E16: =D16*200 -> 1040 | F16: 12KG+/1CBM+ | G16: 35-45天左右签收
B17: Wal-ATL3/Wal-Atl2n/Wal-ATL1 | C17: 6.2 | D17: 5.2 | E17: =D17*200 -> 1040 | F17: 12KG+/1CBM+ | G17: 35-45天左右签收
B18: 三方私人仓区（仓库代码需填写对应的仓点）不足350kg按照350kg计费
B19: 仓库代码 | C19: 东莞仓(明星仓5号）福永仓（明星仓6号） | F19: 起收重量 | G19: 开船后第二天 开始计算时效签收时效
C20: 350kg+ | D20: 500KG+ | E20: 按方包税1CBM+
B21: 西邮 WPGA1/西邮 WPGA4 | C21: 5 | D21: 4.8 | E21: =D21*200 -> 960 | F21: 350kg+/2CBM+ | G21: 35-45天左右签收
B22: 谷仓美南1号/谷仓美南2号 | C22: 5 | D22: 4.8 | E22: =D22*200 -> 960 | F22: 350kg+/2CBM+ | G22: 35-45天左右签收
B23: 乐歌SAV仓/TIKTOK GA仓 | C23: 5 | D23: 4.8 | E23: =D23*200 -> 960 | F23: 350kg+/2CBM+ | G23: 35-45天左右签收
B24: 运去哪 GA1号仓/大健云仓 GA/万邑通GA仓 | C24: 5 | D24: 4.8 | E24: =D24*200 -> 960 | F24: 350kg+/2CBM+ | G24: 35-45天左右签收
B25: 留仓自提 | C25: 4.9 | D25: 4.7 | E25: =D25*200 -> 940 | F25: 350kg+/2CBM+ | G25: 35-45天左右签收
B26: 后续关税每上调1%，将对应增加0.03元/kg的费用，按方对应增加6元/方，反之降关税每下调1%，将对应退0.03元/kg的费用，按方对应退6元/方 发货即默认此条款
B27: 50KG+实重比优惠：1:190减0.5、1:250减0.8、1:300减1、1:350减1.3、1:400减1.5、1:450减1.8、1:500及以上减2 比重减后最低1.5/KG
B28: 计费规则
B30: 计费规则：单边超过200CM拒收； 亚马逊地址单件实重超过30KG小于45KG货物加收RMB1/KG； 320CM<一长+两宽+两高<410CM加收5RMB/KG 非亚马逊地址无超重费，超长费正常收取。
B31: 请注意：按照美国海关要求，所有中国出口美国货物的外包装及货物内包装（或者货物本身）必须有“MADE IN CHINA”的标记，否则一旦被查到将会被要求在美国海关的监管下逐件贴标，限期未完成者将会被处以至少为发票金额的6倍的罚款，由此导致的时效延误及一切费用概由客人承担。
B33: 赔偿说明
B35: 1.提供POD 和预约号后 亚马逊的货物请客户在签收后5个工作日内查询限FBA后台是否上架，签收后15个工作日内提供货物未上架后台截图(需带有电脑屏幕右下角当下真实时间)至我司方可进入开查程序，超过20个工作日反馈不予受理和赔偿。若卡派出现丢件在我司规定时间内调查核实后我司予以赔偿。丢件赔偿标准如下： 一.快递派标准 （1） 提取前任何形式的丢件 按货值赔偿（提供货值证明）最高不超过40/kg 不退运费 （2）提取上网后丢件 统一按照每件100美金赔偿 不退运费 二.卡派标准 （包含任何形式的丢件） （1）按公斤计费的丢件 按货值赔偿（提供货值证明）最高不超过40RMB/kg 不退运费 （2）按方计费的丢件 按货值赔偿（提供货值证明）最高不超过600RMB/件 不退运费 2.货物如因自身包装问题造成破损或数量短少的，不作赔偿； 3.货物未如实申报、侵权或不符合当地法规禁止进口的导致海关扣货不作赔偿, 并且保留追究发件人因此带来对我司的损失赔偿责任； 4.因船期延误或清关延误等不可抗因素，不作赔偿； 5.易碎品不接受任何损坏赔偿； 6.如客户一旦交货到我司，则默认上述赔款条例，出货前请详细阅读此赔偿标准。
B37: 注意事项
B39: 1.以上价格为华南仓库交货价,材积货算:长*宽*高CM/6000 。
B40: 3.以上价格为普货产品到最终Amazon仓库的全部价格
B41: 4.可接单独报关件，加收150RMB/票，退税件贸易国只接中国和美国，其他国家或者中国香港无服务。
B42: 5.单票货物超过5个品名，需额外加收30RMB/个。
... B47: 特别提示：如客户一旦交货到我司，我司默认客户已详细阅读此价格表备注内容及说明，并接受其条款的约束！

Sheet 华南纽约经济普船卡派
F2: =目录!H4 -> 明日之星华南价格表入仓执行日期2025/1/27
B3: 浙江明日之星供应链管理有限公司(深圳分公司）
B6: 华南纽约经济普船卡派（ZIM-ZXB）
B8: 仓库代码 | C8: 东莞仓(明星仓5号）福永仓（明星仓6号） | F8: 起收重量 | G8: 开船后第二天 开始计算时效签收时效 | H8: 备注
C9: 12KG+ | D9: 50KG+ | E9: 按方包税1CBM+
B10: 特价仓库 ABE8/TEB9/ACY2 | C10: 4.9 | D10: 3.9 | E10: =D10*200 -> 780 | F10: 12kg+/1CBM | G10: 42-48天左右签收 | H10: 此报价只收普货，如发现冲货，瞒报或者带电不备注行为没收货物并罚款1000-50000RMB.
B11: 特价仓库 AVP1/TEB4 | C11: 5.1 | D11: 4.1 | E11: =D11*200 -> 820 | F11: 12kg+/1CBM | G11: 42-48天左右签收
B12: 特价仓库 ORF2/BOS7/RMN3 | C12: 5.8 | D12: 4.8 | E12: =D12*200 -> 960 | F12: 12kg+/1CBM | G12: 42-48天左右签收
B13: TEB3/TEB6/TTN2/ABE4/XEW5 | C13: 5.1 | D13: 4.1 | E13: =D13*200 -> 820 | F13: 12kg+/1CBM | G13: 42-48天左右签收
B14: SWF1//MDT1/WBW2/HEA2 | C14: 5.4 | D14: 4.4 | E14: =D14*200 -> 880 | F14: 12kg+/1CBM | G14: 42-48天左右签收
B15: MDT4/PHL4/PHL5/PHL6/DCA6/ILG1/SWF2 /IUSL/HIA1 | C15: 5.7 | D15: 4.7 | E15: =D15*200 -> 940 | F15: 12kg+/1CBM | G15: 42-48天左右签收
B16: RIC1/ALB1/XLX1/XRI3/ BWI4 | C16: 6.1 | D16: 5.1 | E16: =D16*200 -> 1020 | F16: 12kg+/1CBM | G16: 42-48天左右签收
B17: PIT2/CMH2/CMH3/LBE1/CHO1/AKR1 /IUST | C17: 6.3 | D17: 5.3 | E17: =D17*200 -> 1060 | F17: 12kg+/1CBM | G17: 42-48天左右签收
B18: 留仓自提 | C18: / | D18: 4.1 | E18: =D18*200 -> 820 | F18: 12kg+/1CBM | G18: 42-48天左右签收
B19: 后续关税每上调1%，将对应增加0.03元/kg的费用，按方对应增加6元/方，反之降关税每下调1%，将对应退0.03元/kg的费用，按方对应退6元/方 发货即默认此条款
B20: 50KG+实重比优惠：1:190减0.5、1:250减0.8、1:300减1、1:350减1.3、1:400减1.5、1:450减1.8、1:500及以上减2 比重减后最低1.5/KG
B22: 计费规则
B24: 计费规则：单边超过200CM拒收； 亚马逊地址单件实重超过30KG小于45KG货物加收RMB1/KG； 320CM<一长+两宽+两高<410CM加收5RMB/KG 非亚马逊地址无超重费，超长费正常收取。
B25: 请注意：按照美国海关要求，所有中国出口美国货物的外包装及货物内包装（或者货物本身）必须有“MADE IN CHINA”的标记，否则一旦被查到将会被要求在美国海关的监管下逐件贴标，限期未完成者将会被处以至少为发票金额的6倍的罚款，由此导致的时效延误及一切费用概由客人承担。
B27: 赔偿说明
B29: 1.提供POD 和预约号后 亚马逊的货物请客户在签收后5个工作日内查询限FBA后台是否上架，签收后15个工作日内提供货物未上架后台截图(需带有电脑屏幕右下角当下真实时间)至我司方可进入开查程序，超过20个工作日反馈不予受理和赔偿。若卡派出现丢件在我司规定时间内调查核实后我司予以赔偿。丢件赔偿标准如下： 一.快递派标准 （1） 提取前任何形式的丢件 按货值赔偿（提供货值证明）最高不超过40/kg 不退运费 （2）提取上网后丢件 统一按照每件100美金赔偿 不退运费 二.卡派标准 （包含任何形式的丢件） （1）按公斤计费的丢件 按货值赔偿（提供货值证明）最高不超过40RMB/kg 不退运费 （2）按方计费的丢件 按货值赔偿（提供货值证明）最高不超过600RMB/件 不退运费 2.货物如因自身包装问题造成破损或数量短少的，不作赔偿； 3.货物未如实申报、侵权或不符合当地法规禁止进口的导致海关扣货不作赔偿, 并且保留追究发件人因此带来对我司的损失赔偿责任； 4.因船期延误或清关延误等不可抗因素，不作赔偿； 5.易碎品不接受任何损坏赔偿； 6.如客户一旦交货到我司，则默认上述赔款条例，出货前请详细阅读此赔偿标准。
B31: 注意事项
B33: 1.以上价格为华南仓库交货价,材积货算:长*宽*高CM/6000 。
B34: 3.以上价格为普货产品到最终Amazon仓库的全部价格
B35: 4.可接单独报关件，加收150RMB/票，退税件贸易国只接中国和美国，其他国家或者中国香港无服务。
B36: 5.单票货物超过5个品名，需额外加收30RMB/个。
... B41: 特别提示：如客户一旦交货到我司，我司默认客户已详细阅读此价格表备注内容及说明，并接受其条款的约束！

Sheet 华南纽约普船卡派
F2: =目录!H4 -> 明日之星华南价格表入仓执行日期2025/1/27
B3: 浙江明日之星供应链管理有限公司(深圳分公司）
B6: 华南纽约普船卡派（精品COSCO-AWE4航线）
B8: 仓库代码 | C8: 东莞仓(明星仓5号）福永仓（明星仓6号） | F8: 起收重量 | G8: 开船后第二天 开始计算时效签收时效 | H8: 备注
C9: 12KG+ | D9: 50KG+ | E9: 按方包税1CBM+
B10: 特价仓库 ABE8/TEB9/ACY2 | C10: 5 | D10: 4 | E10: =D10*200 -> 800 | F10: 12kg+/1CBM | G10: 40-45天左右签收 | H10: 此报价只收普货，如发现冲货，瞒报或者带电不备注行为没收货物并罚款1000-50000RMB.
B11: 特价仓库 AVP1/TEB4 | C11: 5.2 | D11: 4.2 | E11: =D11*200 -> 840 | F11: 12kg+/1CBM | G11: 40-45天左右签收
B12: 特价仓库 ORF2/BOS7/RMN3 | C12: 5.9 | D12: 4.9 | E12: =D12*200 -> 980 | F12: 12kg+/1CBM | G12: 40-45天左右签收
B13: TEB3/TEB6/TTN2/ABE4/XEW5 | C13: 5.2 | D13: 4.2 | E13: =D13*200 -> 840 | F13: 12kg+/1CBM | G13: 40-45天左右签收
B14: SWF1//MDT1/WBW2/HEA2 | C14: 5.5 | D14: 4.5 | E14: =D14*200 -> 900 | F14: 12kg+/1CBM | G14: 40-45天左右签收
B15: MDT4/PHL4/PHL5/PHL6/DCA6/ILG1/SWF2 /IUSL/HIA1 | C15: 5.8 | D15: 4.8 | E15: =D15*200 -> 960 | F15: 12kg+/1CBM | G15: 40-45天左右签收
B16: RIC1/ALB1/XLX1/XRI3/ BWI4 | C16: 6.2 | D16: 5.2 | E16: =D16*200 -> 1040 | F16: 12kg+/1CBM | G16: 40-45天左右签收
B17: PIT2/CMH2/CMH3/LBE1/CHO1/AKR1 /IUST | C17: 6.4 | D17: 5.4 | E17: =D17*200 -> 1080 | F17: 12kg+/1CBM | G17: 40-45天左右签收
B18: 留仓自提 | C18: / | D18: 4.2 | E18: =D18*200 -> 840 | F18: 12kg+/1CBM | G18: 40-45天左右签收
B19: 华南纽约普船海派（精品COSCO-AWE4航线）
B20: 国家 | C20: 东莞仓(明星仓5号）福永仓（明星仓6号） | F20: 备注
C21: 12KG+ | D21: 51KG+ | E21: 100KG+
B22: 美东邮编0,1,2, | C22: 10.6 | D22: 8.8 | E22: 8.4 | F22: 参考时效：开船后30-35天提取 联邦和UPS随机打单 | G22: 一般贸易报关： 280一票 | H22: 非亚马逊地址+1 偏远3/KG 超偏远4/KG 超极偏远5/KG，如需指定打单+5
B23: 美东邮编3 | C23: 11.6 | D23: 9.3 | E23: 8.9
B24: 后续关税每上调1%，将对应增加0.03元/kg的费用，按方对应增加6元/方，反之降关税每下调1%，将对应退0.03元/kg的费用，按方对应退6元/方 发货即默认此条款
B25: 50KG+实重比优惠：1:190减0.5、1:250减0.8、1:300减1、1:350减1.3、1:400减1.5、1:450减1.8、1:500及以上减2 比重减后最低1.5/KG
B27: 计费规则
B29: 计费规则：单边超过200CM拒收； 亚马逊地址单件实重超过30KG小于45KG货物加收RMB1/KG； 320CM<一长+两宽+两高<410CM加收5RMB/KG 非亚马逊地址无超重费，超长费正常收取。
B30: 请注意：按照美国海关要求，所有中国出口美国货物的外包装及货物内包装（或者货物本身）必须有“MADE IN CHINA”的标记，否则一旦被查到将会被要求在美国海关的监管下逐件贴标，限期未完成者将会被处以至少为发票金额的6倍的罚款，由此导致的时效延误及一切费用概由客人承担。
B32: 赔偿说明
B34: 1.提供POD 和预约号后 亚马逊的货物请客户在签收后5个工作日内查询限FBA后台是否上架，签收后15个工作日内提供货物未上架后台截图(需带有电脑屏幕右下角当下真实时间)至我司方可进入开查程序，超过20个工作日反馈不予受理和赔偿。若卡派出现丢件在我司规定时间内调查核实后我司予以赔偿。丢件赔偿标准如下： 一.快递派标准 （1） 提取前任何形式的丢件 按货值赔偿（提供货值证明）最高不超过40/kg 不退运费 （2）提取上网后丢件 统一按照每件100美金赔偿 不退运费 二.卡派标准 （包含任何形式的丢件） （1）按公斤计费的丢件 按货值赔偿（提供货值证明）最高不超过40RMB/kg 不退运费 （2）按方计费的丢件 按货值赔偿（提供货值证明）最高不超过600RMB/件 不退运费 2.货物如因自身包装问题造成破损或数量短少的，不作赔偿； 3.货物未如实申报、侵权或不符合当地法规禁止进口的导致海关扣货不作赔偿, 并且保留追究发件人因此带来对我司的损失赔偿责任； 4.因船期延误或清关延误等不可抗因素，不作赔偿； 5.易碎品不接受任何损坏赔偿； 6.如客户一旦交货到我司，则默认上述赔款条例，出货前请详细阅读此赔偿标准。
B36: 注意事项
B38: 1.以上价格为华南仓库交货价,材积货算:长*宽*高CM/6000 。
B39: 3.以上价格为普货产品到最终Amazon仓库的全部价格
B40: 4.可接单独报关件，加收150RMB/票，退税件贸易国只接中国和美国，其他国家或者中国香港无服务。
B41: 5.单票货物超过5个品名，需额外加收30RMB/个。
... B46: 特别提示：如客户一旦交货到我司，我司默认客户已详细阅读此价格表备注内容及说明，并接受其条款的约束！

Sheet 华南纽约海铁卡派
F2: =目录!H4 -> 明日之星华南价格表入仓执行日期2025/1/27
B3: 浙江明日之星供应链管理有限公司(深圳分公司）
B6: 华南纽约海铁卡派（ZIM/EXX/OA航线到LA转火车到NY）
B8: 仓库代码 | C8: 东莞仓(明星仓5号）福永仓（明星仓6号） | F8: 起收重量 | G8: 开船后第二天 开始计算时效签收时效 | H8: 备注
C9: 12KG+ | D9: 50KG+ | E9: 按方包税1CBM+
B10: ABE8/TEB9/XEW5 | C10: 8.3 | D10: 7.3 | E10: =D10*200 -> 1460 | F10: 12kg+/1CBM | G10: 25-30天左右签收 | H10: 此报价只收普货，如发现冲货，瞒报或者带电不备注行为没收货物并罚款1000-50000RMB.
B11: ACY2/TEB3/TEB6/TTN2/ABE4/ABE3 | C11: 8.4 | D11: 7.4 | E11: =D11*200 -> 1480 | F11: 12kg+/1CBM | G11: 25-30天左右签收
B12: TEB4/SWF1/AVP1/MDT1/WBW2/ HEA2 | C12: 8.8 | D12: 7.8 | E12: =D12*200 -> 1560 | F12: 12kg+/1CBM | G12: 25-30天左右签收
B13: MDT4/PHL4/PHL5/PHL6/DCA6/ILG1/SWF2 /IUSL/HIA1 | C13: 9.2 | D13: 8.2 | E13: =D13*200 -> 1640 | F13: 12kg+/1CBM | G13: 25-30天左右签收
B14: ORF2/RIC1/BOS7/ALB1/RMN3/XLX1/XRI3/BWI4 | C14: 9.8 | D14: 8.8 | E14: =D14*200 -> 1760 | F14: 12kg+/1CBM | G14: 25-30天左右签收
B15: PIT2/CMH2/CMH3/LBE1/CHO1/AKR1 /IUST | C15: 10 | D15: 9 | E15: =D15*200 -> 1800 | F15: 12kg+/1CBM | G15: 25-30天左右签收
B16: 后续关税每上调1%，将对应增加0.03元/kg的费用，按方对应增加6元/方，反之降关税每下调1%，将对应退0.03元/kg的费用，按方对应退6元/方 发货即默认此条款
B17: 50KG+实重比优惠：1:190减0.5、1:250减0.8、1:300减1、1:350减1.3、1:400减1.5、1:450减1.8、1:500及以上减2 比重减后最低1.5/KG
B19: 计费规则
B21: 计费规则：单边超过200CM拒收； 亚马逊地址单件实重超过30KG小于45KG货物加收RMB1/KG； 320CM<一长+两宽+两高<410CM加收5RMB/KG 非亚马逊地址无超重费，超长费正常收取。
B22: 请注意：按照美国海关要求，所有中国出口美国货物的外包装及货物内包装（或者货物本身）必须有“MADE IN CHINA”的标记，否则一旦被查到将会被要求在美国海关的监管下逐件贴标，限期未完成者将会被处以至少为发票金额的6倍的罚款，由此导致的时效延误及一切费用概由客人承担。
B24: 赔偿说明
B26: 1.提供POD 和预约号后 亚马逊的货物请客户在签收后5个工作日内查询限FBA后台是否上架，签收后15个工作日内提供货物未上架后台截图(需带有电脑屏幕右下角当下真实时间)至我司方可进入开查程序，超过20个工作日反馈不予受理和赔偿。若卡派出现丢件在我司规定时间内调查核实后我司予以赔偿。丢件赔偿标准如下： 一.快递派标准 （1） 提取前任何形式的丢件 按货值赔偿（提供货值证明）最高不超过40/kg 不退运费 （2）提取上网后丢件 统一按照每件100美金赔偿 不退运费 二.卡派标准 （包含任何形式的丢件） （1）按公斤计费的丢件 按货值赔偿（提供货值证明）最高不超过40RMB/kg 不退运费 （2）按方计费的丢件 按货值赔偿（提供货值证明）最高不超过600RMB/件 不退运费 2.货物如因自身包装问题造成破损或数量短少的，不作赔偿； 3.货物未如实申报、侵权或不符合当地法规禁止进口的导致海关扣货不作赔偿, 并且保留追究发件人因此带来对我司的损失赔偿责任； 4.因船期延误或清关延误等不可抗因素，不作赔偿； 5.易碎品不接受任何损坏赔偿； 6.如客户一旦交货到我司，则默认上述赔款条例，出货前请详细阅读此赔偿标准。
B28: 注意事项
B30: 1.以上价格为华南仓库交货价,材积货算:长*宽*高CM/6000 。
B31: 3.以上价格为普货产品到最终Amazon仓库的全部价格
B32: 4.可接单独报关件，加收150RMB/票，退税件贸易国只接中国和美国，其他国家或者中国香港无服务。
B33: 5.单票货物超过5个品名，需额外加收30RMB/个。
... B38: 特别提示：如客户一旦交货到我司，我司默认客户已详细阅读此价格表备注内容及说明，并接受其条款的约束！

Sheet 华南纽约私卡
A2: =目录!H4 -> 明日之星华南价格表入仓执行日期2025/1/27
A4: 浙江明日之星供应链管理有限公司(深圳分公司）
A6: 华南纽约私人卡派
A7: 美东纽约区私卡邮编自查表 | K7: 下单渠道 | L7: 东莞仓(明星仓5号）福永仓（明星仓6号） | N7: 参考时效
L8: 100kg+ | M8: 2CBM+
A9: 07001 | B9: 07002 | C9: 07008 | D9: 07010 | E9: 07011 | F9: 07012 | G9: 07013 | H9: 07015 | I9: 07016 | J9: 07017 | K9: 华南明星达18T私卡/按方 | L9: 9.8 | M9: =L9*220 -> 2156 | N9: 20-25天左右签收
A10: 07018 | B10: 07019 | C10: 07020 | D10: 07021 | E10: 07022 | F10: 07023 | G10: 07024 | H10: 07026 | I10: 07027 | J10: 07029
A11: 07030 | B11: 07031 | C11: 07032 | D11: 07033 | E11: 07036 | F11: 07040 | G11: 07041 | H11: 07043 | I11: 07047 | J11: 07050 | K11: 华南明星达20T私卡/按方 | L11: 9.4 | M11: =L11*220 -> 2068 | N11: 23-28天左右签收
A12: 07051 | B12: 07052 | C12: 07054 | D12: 07055 | E12: 07057 | F12: 07059 | G12: 07060 | H12: 07061 | I12: 07062 | J12: 07063
A13: 07064 | B13: 07065 | C13: 07066 | D13: 07067 | E13: 07069 | F13: 07070 | G13: 07071 | H13: 07072 | I13: 07073 | J13: 07074 | K13: 华南OA普船私卡/按方 | L13: 8.2 | M13: =L13*220 -> 1804 | N13: 25-30天左右签收
A14: 07075 | B14: 07076 | C14: 07077 | D14: 07078 | E14: 07079 | F14: 07080 | G14: 07081 | H14: 07083 | I14: 07086 | J14: 07087
A15: 07088 | B15: 07090 | C15: 07091 | D15: 07092 | E15: 07093 | F15: 07094 | G15: 07095 | H15: 07096 | I15: 07097 | J15: 07099 | K15: 华南纽约快线普船私卡/按方 | L15: 4.5 | M15: =L15*220 -> 990 | N15: 35-40天左右签收
A16: 07101 | B16: 07102 | C16: 07103 | D16: 07104 | E16: 07105 | F16: 07106 | G16: 07107 | H16: 07108 | I16: 07109 | J16: 07110
A17: 07111 | B17: 07112 | C17: 07114 | D17: 07175 | E17: 07184 | F17: 07188 | G17: 07189 | H17: 07191 | I17: 07192 | J17: 07193 | K17: 华南纽约经济普船私卡/按方 | L17: 4.3 | M17: =L17*220 -> 946 | N17: 40-45天左右签收
A18: 07195 | B18: 07198 | C18: 07199 | D18: 07201 | E18: 07202 | F18: 07203 | G18: 07204 | H18: 07205 | I18: 07206 | J18: 07207
A19: 07208 | B19: 07302 | C19: 07303 | D19: 07304 | E19: 07305 | F19: 07306 | G19: 07307 | H19: 07308 | I19: 07310 | J19: 07311 | K19: 华南纽约海铁私卡/按方 | L19: 7.4 | M19: =L19*220 -> 1628 | N19: 40-45天左右签收
A20: 07395 | B20: 07399 | C20: 07424 | D20: 07503 | E20: 07533 | F20: 07601 | G20: 07602 | H20: 07603 | I20: 07604 | J20: 07605
A21: 07606 | B21: 07608 | C21: 07643 | D21: 07650 | E21: 07657 | F21: 07660 | G21: 07666 | H21: 07699 | I21: 07701 | J21: 07702 | K21: 备注
A22: 07703 | B22: 07704 | C22: 07710 | D22: 07711 | E22: 07712 | F22: 07716 | G22: 07717 | H22: 07718 | I22: 07719 | J22: 07720
A23: 07721 | B23: 07722 | C23: 07723 | D23: 07724 | E23: 07726 | F23: 07727 | G23: 07728 | H23: 07730 | I23: 07731 | J23: 07732
A24: 07733 | B24: 07734 | C24: 07735 | D24: 07737 | E24: 07738 | F24: 07739 | G24: 07740 | H24: 07746 | I24: 07747 | J24: 07748
A25: 07750 | B25: 07751 | C25: 07752 | D25: 07753 | E25: 07754 | F25: 07755 | G25: 07756 | H25: 07757 | I25: 07758 | J25: 07760
A26: 07763 | B26: 07764 | C26: 07765 | D26: 07799 | E26: 07830 | F26: 07836 | G26: 07845 | H26: 07853 | I26: 07869 | J26: 07870
A27: 07876 | B27: 07901 | C27: 07902 | D27: 07920 | E27: 07921 | F27: 07922 | G27: 07924 | H27: 07928 | I27: 07930 | J27: 07931 | K27: 此报价只收普货，如发现冲货，瞒报或者带电不备注行为没收货物并罚款1000-50000RMB.
A28: 07933 | B28: 07934 | C28: 07938 | D28: 07939 | E28: 07945 | F28: 07946 | G28: 07950 | H28: 07960 | I28: 07961 | J28: 07962
A29: 07963 | B29: 07970 | C29: 07974 | D29: 07976 | E29: 07977 | F29: 07978 | G29: 07979 | H29: 07980 | I29: 08501 | J29: 08502
A30: 08504 | B30: 08505 | C30: 08510 | D30: 08512 | E30: 08520 | F30: 08525 | G30: 08526 | H30: 08528 | I30: 08530 | J30: 08534
A31: 08535 | B31: 08536 | C31: 08540 | D31: 08541 | E31: 08542 | F31: 08543 | G31: 08544 | H31: 08550 | I31: 08551 | J31: 08553
A32: 08555 | B32: 08557 | C32: 08558 | D32: 08560 | E32: 08561 | F32: 08601 | G32: 08602 | H32: 08603 | I32: 08604 | J32: 08605
A33: 08606 | B33: 08607 | C33: 08608 | D33: 08609 | E33: 08610 | F33: 08611 | G33: 08618 | H33: 08619 | I33: 08620 | J33: 08625
A34: 08628 | B34: 08629 | C34: 08638 | D34: 08645 | E34: 08642 | F34: 08647 | G34: 08648 | H34: 08650 | I34: 08666 | J34: 08690
A35: 08691 | B35: 08695 | C35: 08701 | D35: 08720 | E35: 08736 | F35: 08801 | G35: 08803 | H35: 08805 | I35: 08807 | J35: 08809
A36: 08810 | B36: 08812 | C36: 08816 | D36: 08817 | E36: 08818 | F36: 08820 | G36: 08821 | H36: 08822 | I36: 08823 | J36: 08824
A37: 08827 | B37: 08828 | C37: 08829 | D37: 08830 | E37: 08831 | F37: 08832 | G37: 08833 | H37: 08835 | I37: 08836 | J37: 08837
A38: 08840 | B38: 08844 | C38: 08846 | D38: 08850 | E38: 08852 | F38: 08853 | G38: 08854 | H38: 08855 | I38: 08857 | J38: 08858
A39: 08859 | B39: 08861 | C39: 08862 | D39: 08863 | E39: 08867 | F39: 08869 | G39: 08870 | H39: 08871 | I39: 08872 | J39: 08873
A40: 08875 | B40: 08876 | C40: 08879 | D40: 08880 | E40: 08882 | F40: 08884 | G40: 08885 | H40: 08887 | I40: 08888 | J40: 08889
A41: 08890 | B41: 08899 | C41: 08901 | D41: 08902 | E41: 08903 | F41: 08904 | G41: 08906 | H41: 08933 | I41: 08989 | J41: 18938
A42: 18977 | B42: 19030 | C42: 19054 | D42: 19067
A44: 07003 | B44: 07004 | C44: 07005 | D44: 07006 | E44: 07007 | F44: 07009 | G44: 07028 | H44: 07034 | I44: 07035 | J44: 07039 | K44: 明星达18T私卡/按方 | L44: 10.3 | M44: =L44*220 -> 2266 | N44: 20-25天左右签收
A45: 07042 | B45: 07044 | C45: 07045 | D45: 07046 | E45: 07058 | F45: 07068 | G45: 07082 | H45: 07401 | I45: 07403 | J45: 07405
A46: 07407 | B46: 07410 | C46: 07417 | D46: 07420 | E46: 07423 | F46: 07432 | G46: 07435 | H46: 07436 | I46: 07440 | J46: 07442 | K46: 明星达20T私卡/按方 | L46: 9.8 | M46: =L46*220 -> 2156 | N46: 23-28天左右签收
A47: 07444 | B47: 07446 | C47: 07450 | D47: 07451 | E47: 07452 | F47: 07457 | G47: 07458 | H47: 07463 | I47: 07465 | J47: 07470
A48: 07474 | B48: 07481 | C48: 07501 | D48: 07502 | E48: 07504 | F48: 07505 | G48: 07506 | H48: 07507 | I48: 07508 | J48: 07509 | K48: 华南OA普船私卡/按方 | L48: 8.7 | M48: =L48*220 -> 1914 | N48: 25-30天左右签收
A49: 07510 | B49: 07511 | C49: 07512 | D49: 07513 | E49: 07514 | F49: 07522 | G49: 07524 | H49: 07538 | I49: 07543 | J49: 07544
A50: 07607 | B50: 07620 | C50: 07621 | D50: 07624 | E50: 07626 | F50: 07627 | G50: 07628 | H50: 07630 | I50: 07631 | J50: 07632 | K50: 纽约快线普船私卡/按方 | L50: 4.9 | M50: =L50*220 -> 1078 | N50: 35-40天左右签收
A51: 07640 | B51: 07641 | C51: 07642 | D51: 07644 | E51: 07646 | F51: 07647 | G51: 07648 | H51: 07649 | I51: 07652 | J51: 07653
A52: 07656 | B52: 07661 | C52: 07662 | D52: 07663 | E52: 07670 | F52: 07675 | G52: 07676 | H52: 07677 | I52: 07715 | J52: 07762 | K52: 纽约经济普船私卡/按方 | L52: 4.7 | M52: =L52*220 -> 1034 | N52: 40-45天左右签收
A53: 07801 | B53: 07802 | C53: 07803 | D53: 07806 | E53: 07820 | F53: 07821 | G53: 07823 | H53: 07825 | I53: 07828 | J53: 07831
A54: 07833 | B54: 07834 | C54: 07837 | D54: 07838 | E54: 07839 | F54: 07840 | G54: 07842 | H54: 07843 | I54: 07846 | J54: 07847 | K54: 纽约海铁私卡/按方 | L54: 7.8 | M54: =L54*220 -> 1716 | N54: 40-45天左右签收
A55: 07849 | B55: 07850 | C55: 07852 | D55: 07855 | E55: 07856 | F55: 07857 | G55: 07860 | H55: 07863 | I55: 07865 | J55: 07866
A56: 07874 | B56: 07875 | C56: 07877 | D56: 07878 | E56: 07879 | F56: 07880 | G56: 07882 | H56: 07885 | I56: 07926 | J56: 07927 | K56: 备注
A57: 07932 | B57: 07935 | C57: 07936 | D57: 07940 | E57: 07981 | F57: 07999 | G57: 08010 | H57: 08011 | I57: 08016 | J57: 08022
A58: 08036 | B58: 08041 | C58: 08042 | D58: 08046 | E58: 08048 | F58: 08052 | G58: 08054 | H58: 08055 | I58: 08057 | J58: 08060
A59: 08064 | B59: 08068 | C59: 08073 | D59: 08075 | E59: 08077 | F59: 08088 | G59: 08511 | H59: 08514 | I59: 08515 | J59: 08518
A60: 08527 | B60: 08533 | C60: 08554 | D60: 08556 | E60: 08559 | F60: 08562 | G60: 08640 | H60: 08641 | I60: 08721 | J60: 08722
A61: 08723 | B61: 08724 | C61: 08730 | D61: 08732 | E61: 08733 | F61: 08735 | G61: 08738 | H61: 08739 | I61: 08740 | J61: 08742
A62: 08750 | B62: 08751 | C62: 08752 | D62: 08753 | E62: 08755 | F62: 08757 | G62: 08759 | H62: 08802 | I62: 08804 | J62: 08808 | K62: 此报价只收普货，如发现冲货，瞒报或者带电不备注行为没收货物并罚款1000-50000RMB.
A63: 08825 | B63: 08826 | C63: 08834 | D63: 08848 | E63: 08865 | F63: 08868 | G63: 08886 | H63: 18013 | I63: 18039 | J63: 18040
A64: 18042 | B64: 18043 | C64: 18044 | D64: 18045 | E64: 18063 | F64: 18077 | G64: 18081 | H64: 18351 | I64: 18901 | J64: 18902
A65: 18910 | B65: 18911 | C65: 18912 | D65: 18913 | E65: 18914 | F65: 18917 | G65: 18920 | H65: 18922 | I65: 18923 | J65: 18925
A66: 18928 | B66: 18929 | C66: 18930 | D66: 18931 | E66: 18932 | F66: 18933 | G66: 18934 | H66: 18940 | I66: 18943 | J66: 18944
A67: 18946 | B67: 18947 | C67: 18950 | D67: 18953 | E67: 18954 | F67: 18956 | G67: 18962 | H67: 18963 | I67: 18966 | J67: 18972
A68: 18974 | B68: 18976 | C68: 18980 | D68: 19006 | E68: 19007 | F68: 19009 | G68: 19021 | H68: 19047 | I68: 19048 | J68: 19049
A69: 19053 | B69: 19055 | C69: 19056 | D69: 19057 | E69: 19058 | F69: 19111 | G69: 19114 | H69: 19115 | I69: 19116 | J69: 19136
A70: 19152 | B70: 19154
A71: 后续关税每上调1%，将对应增加0.03元/kg的费用，按方对应增加6元/方，反之降关税每下调1%，将对应退0.03元/kg的费用，按方对应退6元/方 发货即默认此条款
A72: 50KG+实重比优惠：1:190减0.5、1:250减0.8、1:300减1、1:350减1.3、1:400减1.5、1:450减1.8、1:500及以上减2 比重减后最低1.5/KG
A74: 计费规则
A76: 计费规则：单边超过200CM拒收； 亚马逊地址单件实重超过30KG小于45KG货物加收RMB1/KG； 320CM<一长+两宽+两高<410CM加收5RMB/KG 非亚马逊地址无超重费，超长费正常收取。
A77: 请注意：按照美国海关要求，所有中国出口美国货物的外包装及货物内包装（或者货物本身）必须有“MADE IN CHINA”的标记，否则一旦被查到将会被要求在美国海关的监管下逐件贴标，限期未完成者将会被处以至少为发票金额的6倍的罚款，由此导致的时效延误及一切费用概由客人承担。
A79: 赔偿说明
A81: 1.提供POD 和预约号后 亚马逊的货物请客户在签收后5个工作日内查询限FBA后台是否上架，签收后15个工作日内提供货物未上架后台截图(需带有电脑屏幕右下角当下真实时间)至我司方可进入开查程序，超过20个工作日反馈不予受理和赔偿。若卡派出现丢件在我司规定时间内调查核实后我司予以赔偿。丢件赔偿标准如下： 一.快递派标准 （1） 提取前任何形式的丢件 按货值赔偿（提供货值证明）最高不超过40/kg 不退运费 （2）提取上网后丢件 统一按照每件100美金赔偿 不退运费 二.卡派标准 （包含任何形式的丢件） （1）按公斤计费的丢件 按货值赔偿（提供货值证明）最高不超过40RMB/kg 不退运费 （2）按方计费的丢件 按货值赔偿（提供货值证明）最高不超过600RMB/件 不退运费 2.货物如因自身包装问题造成破损或数量短少的，不作赔偿； 3.货物未如实申报、侵权或不符合当地法规禁止进口的导致海关扣货不作赔偿, 并且保留追究发件人因此带来对我司的损失赔偿责任； 4.因船期延误或清关延误等不可抗因素，不作赔偿； 5.易碎品不接受任何损坏赔偿； 6.如客户一旦交货到我司，则默认上述赔款条例，出货前请详细阅读此赔偿标准。
A83: 注意事项
A85: 1.以上价格为华南仓库交货价,材积货算:长*宽*高CM/6000 。
A86: 3.以上价格为普货产品到最终Amazon仓库的全部价格
A87: 4.可接单独报关件，加收150RMB/票，退税件贸易国只接中国和美国，其他国家或者中国香港无服务。
A88: 5.单票货物超过5个品名，需额外加收30RMB/个。
... A93: 特别提示：如客户一旦交货到我司，我司默认客户已详细阅读此价格表备注内容及说明，并接受其条款的约束！

Sheet 华南全美商私卡
A1: 浙江明日之星供应链管理有限公司(深圳分公司）
A2: =目录!H4 -> 明日之星华南价格表入仓执行日期2025/1/27
A3: 全美商私卡报价（美西港口转卡车派送）
A4: 全美商私卡报价仅限有卸货平台及卸货能力、能进53尺大车和小车派送的商业仓库地址
A5: OR-俄勒冈州 WA-华盛顿州 ID-爱达荷州 AZ-亚利桑那州 NV-内华达州 IN-印第安纳州 IL-伊利诺伊州 WI-威斯康星州 MN-明尼苏达州 OH-俄亥俄州 IA-爱荷华州
A6: MI-密歇根州 KY-肯塔基州 AL-亚拉巴马州 MO-密苏里州 OK-俄克拉荷马州 CO-科罗拉多州 TN-田纳西州 TX-德克萨斯州 UT-犹他州 FL-佛罗里达州 GA-佐治亚州
A7: SC-南卡罗来纳州 DC-哥伦比亚特区 VA-弗吉尼亚州 NC-北卡罗莱纳州 MD-马里兰州 NJ-新泽西州 PA-宾夕法尼亚州 NY-纽约州 MA-马萨诸塞州 DE-特拉华州
A8: 下单渠道 | B8: 华南-明星达14T商私卡 东莞仓(明星仓5号）福永仓（明星仓6号） | K8: 签收时效 | L8: 备注
A9: 州/仓库 | B9: 350KG+ | C9: 1000KG+ | D9: 2000KG+ | E9: 5000KG+ | F9: 9000KG+ | G9: 按方包税2CBM | H9: 按方包税12CBM | I9: 按方包税30CBM | J9: 按方包税60CBM
A10: OR/WA/ID/ | B10: 14.5 | C10: 13.5 | D10: 13 | E10: 12.5 | F10: 12 | G10: =B10*210 -> 3045 | H10: =D10*220 -> 2860 | I10: =E10*220 -> 2750 | J10: =F10*220 -> 2640 | K10: 提柜后7-10个工作日签收，无时效赔付 | L10: 1.此报价只收普货，如发现冲货，瞒报或者带电不备注行为没收货物并罚款10000-50000RMB. 2.后续关税每上调1%，将对应增加0.03元/kg的费用，按方对应增加6元/方，反之降关税每下调1%，将对应退0.03元/kg的费用，按方对应退6元/方 发货即默认此条款。 3.发货前请联系我司客服查询是否有卸货平台！如没有卸货平台的私人住宅需承担升降机每票$150，私人住宅最多不超20个方，超出需分票出（包括按KG计费）
A11: AZ/NV | B11: 13 | C11: 12 | D11: 11.5 | E11: 11 | F11: 10.5 | G11: =B11*210 -> 2730 | H11: =D11*220 -> 2530 | I11: =E11*220 -> 2420 | J11: =F11*220 -> 2310 | K11: 开船后（以开船时间计算）的第二天开算起，19天签收，第20天开始理赔，超一天理赔0.5，最高理赔1元/kg。（注：美国节假日放假，船晚到港，码头罢工，因收件人联系不上导致的延误均不在承诺时效内
A12: IN | B12: 16 | C12: 14 | D12: 13.5 | E12: 13 | F12: 12.5 | G12: =B12*210 -> 3360 | H12: =D12*220 -> 2970 | I12: =E12*220 -> 2860 | J12: =F12*220 -> 2750 | K12: 开船后（以开船时间计算）的第二天开算起，21天签收，第22天开始理赔，超一天理赔0.5，最高理赔1元/kg。（美国节假日放假，船晚到港，码头罢工，因收件人联系不上导致的延误均不在承诺时效内
A13: IL/WI/MN | B13: 16 | C13: 14 | D13: 13.5 | E13: 13 | F13: 12.5 | G13: =B13*210 -> 3360 | H13: =D13*220 -> 2970 | I13: =E13*220 -> 2860 | J13: =F13*220 -> 2750 | K13: 提柜后7-10个工作日签收，无时效赔付
A14: OH/IA/MI/KY/AL | B14: 15.5 | C14: 13.3 | D14: 13 | E14: 12.5 | F14: 12 | G14: =B14*210 -> 3255 | H14: =D14*220 -> 2860 | I14: =E14*220 -> 2750 | J14: =F14*220 -> 2640 | K14: 提柜后7-10个工作日签收，无时效赔付
A15: MO/OK/CO/TN | B15: 15.5 | C15: 13.3 | D15: 13 | E15: 12.5 | F15: 12 | G15: =B15*210 -> 3255 | H15: =D15*220 -> 2860 | I15: =E15*220 -> 2750 | J15: =F15*220 -> 2640 | K15: 提柜后7-10个工作日签收，无时效赔付
A16: TX | B16: 15.1 | C16: 14 | D16: 13.2 | E16: 12.7 | F16: 12 | G16: =B16*210 -> 3171 | H16: =D16*220 -> 2904 | I16: =E16*220 -> 2794 | J16: =F16*220 -> 2640 | K16: 开船后（以开船时间计算）的第二天开算起，19天签收，第20天开始理赔，超一天理赔0.5，最高理赔1元/kg（美国节假日放假，船晚到港，码头罢码头罢工，因收件人联系不上导致的延误均不在承诺时效内
A17: UT | B17: 14.1 | C17: 12.1 | D17: 11.5 | E17: 11 | F17: 10.5 | G17: =B17*210 -> 2961 | H17: =D17*220 -> 2530 | I17: =E17*220 -> 2420 | J17: =F17*220 -> 2310 | K17: 提柜后7-10个工作日签收，无时效赔付
A18: FL/GA/SC/DC/VA/NC | B18: 17 | C18: 15 | D18: 14.5 | E18: 14.3 | F18: 13.5 | G18: =B18*210 -> 3570 | H18: =D18*220 -> 3190 | I18: =E18*220 -> 3146 | J18: =F18*220 -> 2970 | K18: 提柜后7-10个工作日签收，无时效赔付
A19: MD/NJ/PA | B19: 17.3 | C19: 15.3 | D19: 14.8 | E19: 14.6 | F19: 13.8 | G19: =B19*210 -> 3633 | H19: =D19*220 -> 3256 | I19: =E19*220 -> 3212 | J19: =F19*220 -> 3036 | K19: 提柜后7-10个工作日签收，无时效赔付
A20: NY/MA/DE | B20: 20.1 | C20: 17.1 | D20: 16.6 | E20: 16.3 | F20: 16 | G20: =B20*210 -> 4221 | H20: =D20*220 -> 3652 | I20: =E20*220 -> 3586 | J20: =F20*220 -> 3520 | K20: 提柜后7-10个工作日签收，无时效赔付
A21: 按方渠道密度比最高（1CBM：363KGS）
A22: 下单渠道 | B22: 华南-明星达16T商私卡 东莞仓(明星仓5号）福永仓（明星仓6号） | K22: 签收时效 | L22: 备注
A23: 州/仓库 | B23: 350KG+ | C23: 1000KG+ | D23: 2000KG+ | E23: 5000KG+ | F23: 9000KG+ | G23: 按方包税2CBM | H23: 按方包税12CBM | I23: 按方包税30CBM | J23: 按方包税60CBM
A24: OR/WA/ID/ | B24: 14.2 | C24: 13.2 | D24: 12.7 | E24: 12.2 | F24: 11.7 | G24: =B24*210 -> 2982 | H24: =D24*220 -> 2794 | I24: =E24*220 -> 2684 | J24: =F24*220 -> 2574 | K24: 提柜后7-10个工作日签收，无时效赔付 | L24: 1.此报价只收普货，如发现冲货，瞒报或者带电不备注行为没收货物并罚款10000-50000RMB. 2.后续关税每上调1%，将对应增加0.03元/kg的费用，按方对应增加6元/方，反之降关税每下调1%，将对应退0.03元/kg的费用，按方对应退6元/方 发货即默认此条款3.发货前请联系我司客服查询是否有卸货平台！如没有卸货平台的私人住宅需承担升降机每票$150，私人住宅最多不超20个方，超出需分票出！
A25: AZ/NV | B25: 12.7 | C25: 11.7 | D25: 11.2 | E25: 10.7 | F25: 10.2 | G25: =B25*210 -> 2667 | H25: =D25*220 -> 2464 | I25: =E25*220 -> 2354 | J25: =F25*220 -> 2244 | K25: 开船后（以开船时间计算）的第二天开算起，21天签收，第20天开始理赔，超一天理赔0.5，最高理赔1元/kg。（注：美国节假日放假，船晚到港，码头罢工码头罢工，因收件人联系不上导致的延误均不在承诺时效内
A26: IN | B26: 15.7 | C26: 13.7 | D26: 13.2 | E26: 12.7 | F26: 12.2 | G26: =B26*210 -> 3297 | H26: =D26*220 -> 2904 | I26: =E26*220 -> 2794 | J26: =F26*220 -> 2684 | K26: 开船后（以开船时间计算）的第二天开算起，23天签收，第22天开始理赔，超一天理赔0.5，最高理赔1元/kg。（美国节假日放假，船晚到港，码头罢工码头罢工，因收件人联系不上导致的延误均不在承诺时效内
A27: IL/WI/MN | B27: 15.7 | C27: 13.7 | D27: 13.2 | E27: 12.7 | F27: 12.2 | G27: =B27*210 -> 3297 | H27: =D27*220 -> 2904 | I27: =E27*220 -> 2794 | J27: =F27*220 -> 2684 | K27: 提柜后7-10个工作日签收，无时效赔付
A28: OH/IA/MI/KY/AL | B28: 15.2 | C28: 13 | D28: 12.7 | E28: 12.2 | F28: 11.7 | G28: =B28*210 -> 3192 | H28: =D28*220 -> 2794 | I28: =E28*220 -> 2684 | J28: =F28*220 -> 2574 | K28: 提柜后7-10个工作日签收，无时效赔付
A29: MO/OK/CO/TN | B29: 15.2 | C29: 13 | D29: 12.7 | E29: 12.2 | F29: 11.7 | G29: =B29*210 -> 3192 | H29: =D29*220 -> 2794 | I29: =E29*220 -> 2684 | J29: =F29*220 -> 2574 | K29: 提柜后7-10个工作日签收，无时效赔付
A30: TX | B30: 14.8 | C30: 13.7 | D30: 12.9 | E30: 12.4 | F30: 11.7 | G30: =B30*210 -> 3108 | H30: =D30*220 -> 2838 | I30: =E30*220 -> 2728 | J30: =F30*220 -> 2574 | K30: 开船后（以开船时间计算）的第二天开算起，21天签收，第20天开始理赔，超一天理赔0.5，最高理赔1元/kg（美国节假日放假，船晚到港，码头罢工，因收件人联系不上导致的延误均不在承诺时效内
A31: UT | B31: 13.8 | C31: 11.8 | D31: 11.2 | E31: 10.7 | F31: 10.2 | G31: =B31*210 -> 2898 | H31: =D31*220 -> 2464 | I31: =E31*220 -> 2354 | J31: =F31*220 -> 2244 | K31: 提柜后7-10个工作日签收，无时效赔付
A32: FL/GA/SC/DC/VA/NC | B32: 16.7 | C32: 14.7 | D32: 14.2 | E32: 14 | F32: 13.2 | G32: =B32*210 -> 3507 | H32: =D32*220 -> 3124 | I32: =E32*220 -> 3080 | J32: =F32*220 -> 2904 | K32: 提柜后7-10个工作日签收，无时效赔付
A33: MD/NJ/PA/DE | B33: 17 | C33: 15 | D33: 14.5 | E33: 14.3 | F33: 13.5 | G33: =B33*210 -> 3570 | H33: =D33*220 -> 3190 | I33: =E33*220 -> 3146 | J33: =F33*220 -> 2970 | K33: 提柜后7-10个工作日签收，无时效赔付
A34: NY/MA | B34: 19.8 | C34: 16.8 | D34: 16.3 | E34: 16 | F34: 15.7 | G34: =B34*210 -> 4158 | H34: =D34*220 -> 3586 | I34: =E34*220 -> 3520 | J34: =F34*220 -> 3454 | K34: 提柜后7-10个工作日签收，无时效赔付
A35: 按方渠道密度比最高（1CBM：363KGS）
A36: 下单渠道 | B36: 华南-明星达18T商私卡 东莞仓(明星仓5号）福永仓（明星仓6号） | K36: 签收时效 | L36: 备注
A37: 州/仓库 | B37: 350KG+ | C37: 1000KG+ | D37: 2000KG+ | E37: 5000KG+ | F37: 9000KG+ | G37: 按方包税2CBM | H37: 按方包税12CBM | I37: 按方包税30CBM | J37: 按方包税60CBM
A38: OR/WA/ID/ | B38: 11 | C38: 10 | D38: 9.5 | E38: 9 | F38: 8.5 | G38: =B38*210 -> 2310 | H38: =D38*220 -> 2090 | I38: =E38*220 -> 1980 | J38: =F38*220 -> 1870 | K38: 提柜后7-10个工作日签收，无时效赔付 | L38: 1.此报价只收普货，如发现冲货，瞒报或者带电不备注行为没收货物并罚款10000-50000RMB. 2.后续关税每上调1%，将对应增加0.03元/kg的费用，按方对应增加6元/方，反之降关税每下调1%，将对应退0.03元/kg的费用，按方对应退6元/方 发货即默认此条款3.发货前请联系我司客服查询是否有卸货平台！如没有卸货平台的私人住宅需承担升降机每票$150，私人住宅最多不超20个方，超出需分票出！
A39: AZ/NV | B39: 9.5 | C39: 8.5 | D39: 8 | E39: 7.5 | F39: 7 | G39: =B39*210 -> 1995 | H39: =D39*220 -> 1760 | I39: =E39*220 -> 1650 | J39: =F39*220 -> 1540 | K39: 开船后（以开船时间计算）的第二天开算起，22天签收，第20天开始理赔，超一天理赔0.5，最高理赔1元/kg。（注：美国节假日放假，船晚到港，码头罢工，因收件人联系不上导致的延误均不在承诺时效内
A40: IN | B40: 12.5 | C40: 10.5 | D40: 10 | E40: 9.5 | F40: 9 | G40: =B40*210 -> 2625 | H40: =D40*220 -> 2200 | I40: =E40*220 -> 2090 | J40: =F40*220 -> 1980 | K40: 开船后（以开船时间计算）的第二天开算起，24天签收，第22天开始理赔，超一天理赔0.5，最高理赔1元/kg。（美国节假日放假，船晚到港，码头罢工，因收件人联系不上导致的延误均不在承诺时效内
A41: IL/WI/MN | B41: 12.5 | C41: 10.5 | D41: 10 | E41: 9.5 | F41: 9 | G41: =B41*210 -> 2625 | H41: =D41*220 -> 2200 | I41: =E41*220 -> 2090 | J41: =F41*220 -> 1980 | K41: 提柜后7-10个工作日签收，无时效赔付
A42: OH/IA/MI/KY/AL | B42: 12 | C42: 9.8 | D42: 9.5 | E42: 9 | F42: 8.5 | G42: =B42*210 -> 2520 | H42: =D42*220 -> 2090 | I42: =E42*220 -> 1980 | J42: =F42*220 -> 1870 | K42: 提柜后7-10个工作日签收，无时效赔付
A43: MO/OK/CO/TN | B43: 12 | C43: 9.8 | D43: 9.5 | E43: 9 | F43: 8.5 | G43: =B43*210 -> 2520 | H43: =D43*220 -> 2090 | I43: =E43*220 -> 1980 | J43: =F43*220 -> 1870 | K43: 提柜后7-10个工作日签收，无时效赔付
A44: TX | B44: 11.6 | C44: 10.5 | D44: 9.7 | E44: 9.2 | F44: 8.5 | G44: =B44*210 -> 2436 | H44: =D44*220 -> 2134 | I44: =E44*220 -> 2024 | J44: =F44*220 -> 1870 | K44: 开船后（以开船时间计算）的第二天开算起，22天签收，第20天开始理赔，超一天理赔0.5，最高理赔1元/kg（美国节假日放假，船晚到港，码头罢工，因收件人联系不上导致的延误均不在承诺时效内
A45: UT | B45: 10.6 | C45: 8.6 | D45: 8 | E45: 7.5 | F45: 7 | G45: =B45*210 -> 2226 | H45: =D45*220 -> 1760 | I45: =E45*220 -> 1650 | J45: =F45*220 -> 1540 | K45: 提柜后7-10个工作日签收，无时效赔付
A46: FL/GA/SC/DC/VA/NC | B46: 13.5 | C46: 11.5 | D46: 11 | E46: 10.8 | F46: 10 | G46: =B46*210 -> 2835 | H46: =D46*220 -> 2420 | I46: =E46*220 -> 2376 | J46: =F46*220 -> 2200 | K46: 提柜后7-10个工作日签收，无时效赔付
A47: MD/NJ/PA/DE | B47: 13.8 | C47: 11.8 | D47: 11.3 | E47: 11.1 | F47: 10.3 | G47: =B47*210 -> 2898 | H47: =D47*220 -> 2486 | I47: =E47*220 -> 2442 | J47: =F47*220 -> 2266 | K47: 提柜后7-10个工作日签收，无时效赔付
A48: NY/MA | B48: 16.6 | C48: 13.6 | D48: 13.1 | E48: 12.8 | F48: 12.5 | G48: =B48*210 -> 3486 | H48: =D48*220 -> 2882 | I48: =E48*220 -> 2816 | J48: =F48*220 -> 2750 | K48: 提柜后7-10个工作日签收，无时效赔付
A49: 按方渠道密度比最高（1CBM：363KGS）
A50: 下单渠道 | B50: 华南-明星达20T商私卡 东莞仓(明星仓5号）福永仓（明星仓6号） | K50: 签收时效 | L50: 备注
A51: 州/仓库 | B51: 350KG+ | C51: 1000KG+ | D51: 2000KG+ | E51: 5000KG+ | F51: 9000KG+ | G51: 按方包税2CBM | H51: 按方包税12CBM | I51: 按方包税30CBM | J51: 按方包税60CBM
A52: OR/WA/ID/ | B52: 10.3 | C52: 9.3 | D52: 8.8 | E52: 8.3 | F52: 7.8 | G52: =B52*210 -> 2163 | H52: =D52*220 -> 1936 | I52: =E52*220 -> 1826 | J52: =F52*220 -> 1716 | K52: 提柜后7-10个工作日签收，无时效赔付 | L52: 1.此报价只收普货，如发现冲货，瞒报或者带电不备注行为没收货物并罚款10000-50000RMB. 2.后续关税每上调1%，将对应增加0.03元/kg的费用，按方对应增加6元/方，反之降关税每下调1%，将对应退0.03元/kg的费用，按方对应退6元/方 发货即默认此条款3.发货前请联系我司客服查询是否有卸货平台！如没有卸货平台的私人住宅需承担升降机每票$150，私人住宅最多不超20个方，超出需分票出！
A53: AZ/NV | B53: 8.8 | C53: 7.8 | D53: 7.3 | E53: 6.8 | F53: 6.3 | G53: =B53*210 -> 1848 | H53: =D53*220 -> 1606 | I53: =E53*220 -> 1496 | J53: =F53*220 -> 1386 | K53: 开船后（以开船时间计算）的第二天开算起，24天签收，第20天开始理赔，超一天理赔0.5，最高理赔1元/kg。（注：美国节假日放假，船晚到港，码头罢工，因收件人联系不上导致的延误均不在承诺时效内
A54: IN | B54: 11.8 | C54: 9.8 | D54: 9.3 | E54: 8.8 | F54: 8.3 | G54: =B54*210 -> 2478 | H54: =D54*220 -> 2046 | I54: =E54*220 -> 1936 | J54: =F54*220 -> 1826 | K54: 开船后（以开船时间计算）的第二天开算起，26天签收，第22天开始理赔，超一天理赔0.5，最高理赔1元/kg。（美国节假日放假，船晚到港，码头罢工，因收件人联系不上导致的延误均不在承诺时效内
A55: IL/WI/MN | B55: 11.8 | C55: 9.8 | D55: 9.3 | E55: 8.8 | F55: 8.3 | G55: =B55*210 -> 2478 | H55: =D55*220 -> 2046 | I55: =E55*220 -> 1936 | J55: =F55*220 -> 1826 | K55: 提柜后7-10个工作日签收，无时效赔付
A56: OH/IA/MI/KY/AL | B56: 11.3 | C56: 9.1 | D56: 8.8 | E56: 8.3 | F56: 7.8 | G56: =B56*210 -> 2373 | H56: =D56*220 -> 1936 | I56: =E56*220 -> 1826 | J56: =F56*220 -> 1716 | K56: 提柜后7-10个工作日签收，无时效赔付
A57: MO/OK/CO/TN | B57: 11.3 | C57: 9.1 | D57: 8.8 | E57: 8.3 | F57: 7.8 | G57: =B57*210 -> 2373 | H57: =D57*220 -> 1936 | I57: =E57*220 -> 1826 | J57: =F57*220 -> 1716 | K57: 提柜后7-10个工作日签收，无时效赔付
A58: TX | B58: 10.9 | C58: 9.8 | D58: 9 | E58: 8.5 | F58: 7.8 | G58: =B58*210 -> 2289 | H58: =D58*220 -> 1980 | I58: =E58*220 -> 1870 | J58: =F58*220 -> 1716 | K58: 开船后（以开船时间计算）的第二天开算起，24天签收，第20天开始理赔，超一天理赔0.5，最高理赔1元/kg（美国节假日放假，船晚到港，码头罢工，因收件人联系不上导致的延误均不在承诺时效内
A59: UT | B59: 9.9 | C59: 7.9 | D59: 7.3 | E59: 6.8 | F59: 6.3 | G59: =B59*210 -> 2079 | H59: =D59*220 -> 1606 | I59: =E59*220 -> 1496 | J59: =F59*220 -> 1386 | K59: 提柜后7-10个工作日签收，无时效赔付
A60: FL/GA/SC/DC/VA/NC | B60: 12.8 | C60: 10.8 | D60: 10.3 | E60: 10.1 | F60: 9.3 | G60: =B60*210 -> 2688 | H60: =D60*220 -> 2266 | I60: =E60*220 -> 2222 | J60: =F60*220 -> 2046 | K60: 提柜后7-10个工作日签收，无时效赔付
A61: MD/NJ/PA/DE | B61: 13.1 | C61: 11.1 | D61: 10.6 | E61: 10.4 | F61: 9.6 | G61: =B61*210 -> 2751 | H61: =D61*220 -> 2332 | I61: =E61*220 -> 2288 | J61: =F61*220 -> 2112 | K61: 提柜后7-10个工作日签收，无时效赔付
A62: NY/MA | B62: 15.9 | C62: 12.9 | D62: 12.4 | E62: 12.1 | F62: 11.8 | G62: =B62*210 -> 3339 | H62: =D62*220 -> 2728 | I62: =E62*220 -> 2662 | J62: =F62*220 -> 2596 | K62: 提柜后7-10个工作日签收，无时效赔付
A63: 按方渠道密度比最高（1CBM：363KGS）
A64: 下单渠道 | B64: 华南-OA普船商私卡 东莞仓(明星仓5号）福永仓（明星仓6号） | K64: 签收时效 | L64: 备注
A65: 州/仓库 | B65: 350KG+ | C65: 1000KG+ | D65: 2000KG+ | E65: 5000KG+ | F65: 9000KG+ | G65: 按方包税2CBM | H65: 按方包税12CBM | I65: 按方包税30CBM | J65: 按方包税60CBM
A66: OR/WA/ID/ | B66: 10.1 | C66: 9.1 | D66: 8.6 | E66: 8.1 | F66: 7.6 | G66: =B66*210 -> 2121 | H66: =D66*220 -> 1892 | I66: =E66*220 -> 1782 | J66: =F66*220 -> 1672 | K66: 提柜后7-10个工作日签收，无时效赔付 | L66: 1.此报价只收普货，如发现冲货，瞒报或者带电不备注行为没收货物并罚款10000-50000RMB. 2.后续关税每上调1%，将对应增加0.03元/kg的费用，按方对应增加6元/方，反之降关税每下调1%，将对应退0.03元/kg的费用，按方对应退6元/方 发货即默认此条款3.发货前请联系我司客服查询是否有卸货平台！如没有卸货平台的私人住宅需承担升降机每票$150，私人住宅最多不超20个方，超出需分票出！
A67: AZ/NV | B67: 8.6 | C67: 7.6 | D67: 7.1 | E67: 6.6 | F67: 6.1 | G67: =B67*210 -> 1806 | H67: =D67*220 -> 1562 | I67: =E67*220 -> 1452 | J67: =F67*220 -> 1342 | K67: 提柜后7-10个工作日签收，无时效赔付
A68: IN | B68: 11.6 | C68: 9.6 | D68: 9.1 | E68: 8.6 | F68: 8.1 | G68: =B68*210 -> 2436 | H68: =D68*220 -> 2002 | I68: =E68*220 -> 1892 | J68: =F68*220 -> 1782 | K68: 提柜后7-10个工作日签收，无时效赔付
A69: IL/WI/MN | B69: 11.6 | C69: 9.6 | D69: 9.1 | E69: 8.6 | F69: 8.1 | G69: =B69*210 -> 2436 | H69: =D69*220 -> 2002 | I69: =E69*220 -> 1892 | J69: =F69*220 -> 1782 | K69: 提柜后7-10个工作日签收，无时效赔付
A70: OH/IA/MI/KY/AL | B70: 11.1 | C70: 8.9 | D70: 8.6 | E70: 8.1 | F70: 7.6 | G70: =B70*210 -> 2331 | H70: =D70*220 -> 1892 | I70: =E70*220 -> 1782 | J70: =F70*220 -> 1672 | K70: 提柜后7-10个工作日签收，无时效赔付
A71: MO/OK/CO/TN | B71: 11.1 | C71: 8.9 | D71: 8.6 | E71: 8.1 | F71: 7.6 | G71: =B71*210 -> 2331 | H71: =D71*220 -> 1892 | I71: =E71*220 -> 1782 | J71: =F71*220 -> 1672 | K71: 提柜后7-10个工作日签收，无时效赔付
A72: TX | B72: 10.7 | C72: 9.6 | D72: 8.8 | E72: 8.3 | F72: 7.6 | G72: =B72*210 -> 2247 | H72: =D72*220 -> 1936 | I72: =E72*220 -> 1826 | J72: =F72*220 -> 1672 | K72: 提柜后7-10个工作日签收，无时效赔付
A73: UT | B73: 9.7 | C73: 7.7 | D73: 7.1 | E73: 6.6 | F73: 6.1 | G73: =B73*210 -> 2037 | H73: =D73*220 -> 1562 | I73: =E73*220 -> 1452 | J73: =F73*220 -> 1342 | K73: 提柜后7-10个工作日签收，无时效赔付
A74: FL/GA/SC/DC/VA/NC | B74: 12.6 | C74: 10.6 | D74: 10.1 | E74: 9.9 | F74: 9.1 | G74: =B74*210 -> 2646 | H74: =D74*220 -> 2222 | I74: =E74*220 -> 2178 | J74: =F74*220 -> 2002 | K74: 提柜后7-10个工作日签收，无时效赔付
A75: MD/NJ/PA/DE | B75: 12.9 | C75: 10.9 | D75: 10.4 | E75: 10.2 | F75: 9.4 | G75: =B75*210 -> 2709 | H75: =D75*220 -> 2288 | I75: =E75*220 -> 2244 | J75: =F75*220 -> 2068 | K75: 提柜后7-10个工作日签收，无时效赔付
A76: NY/MA | B76: 15.7 | C76: 12.7 | D76: 12.2 | E76: 11.9 | F76: 11.6 | G76: =B76*210 -> 3297 | H76: =D76*220 -> 2684 | I76: =E76*220 -> 2618 | J76: =F76*220 -> 2552 | K76: 提柜后7-10个工作日签收，无时效赔付
A77: 按方渠道密度比最高（1CBM：363KGS）
A79: 50KG+实重比优惠：1:190减0.5、1:250减0.8、1:300减1、1:350减1.3、1:400减1.5、1:450减1.8、1:500及以上减2 比重减后最低1.5/KG
A81: 计费规则：单边超过200CM拒收； 亚马逊地址单件实重超过30KG小于45KG货物加收RMB1/KG； 320CM<一长+两宽+两高<410CM加收5RMB/KG 非亚马逊地址无超重费，超长费正常收取。
A82: 请注意：按照美国海关要求，所有中国出口美国货物的外包装及货物内包装（或者货物本身）必须有“MADE IN CHINA”的标记，否则一旦被查到将会被要求在美国海关的监管下逐件贴标，限期未完成者将会被处以至少为发票金额的6倍的罚款，由此导致的时效延误及一切费用概由客人承担。
A84: 赔偿说明
A86: 1.提供POD 和预约号后 亚马逊的货物请客户在签收后5个工作日内查询限FBA后台是否上架，签收后15个工作日内提供货物未上架后台截图(需带有电脑屏幕右下角当下真实时间)至我司方可进入开查程序，超过20个工作日反馈不予受理和赔偿。若卡派出现丢件在我司规定时间内调查核实后我司予以赔偿。丢件赔偿标准如下： 一.快递派标准 （1） 提取前任何形式的丢件 按货值赔偿（提供货值证明）最高不超过40/kg 不退运费 （2）提取上网后丢件 统一按照每件100美金赔偿 不退运费 二.卡派标准 （包含任何形式的丢件） （1）按公斤计费的丢件 按货值赔偿（提供货值证明）最高不超过40RMB/kg 不退运费 （2）按方计费的丢件 按货值赔偿（提供货值证明）最高不超过600RMB/件 不退运费 2.货物如因自身包装问题造成破损或数量短少的，不作赔偿； 3.货物未如实申报、侵权或不符合当地法规禁止进口的导致海关扣货不作赔偿, 并且保留追究发件人因此带来对我司的损失赔偿责任； 4.因船期延误或清关延误等不可抗因素，不作赔偿； 5.易碎品不接受任何损坏赔偿； 6.如客户一旦交货到我司，则默认上述赔款条例，出货前请详细阅读此赔偿标准。
A88: 注意事项
A90: 1.以上价格为华南仓库交货价,材积货算:长*宽*高CM/6000 。
A91: 3.以上价格为普货产品到最终Amazon仓库的全部价格
A92: 4.可接单独报关件，加收150RMB/票，退税件贸易国只接中国和美国，其他国家或者中国香港无服务。
A93: 5.单票货物超过5个品名，需额外加收30RMB/个。
A94: 6.订舱需提供出货模块资料，模块资料需提供详细品名，海关编码，材质，用途，图片，地址栏需认真仔细填写。
... A98: 特别提示：如客户一旦交货到我司，我司默认客户已详细阅读此价格表备注内容及说明，并接受其条款的约束！

Sheet 美国亚马逊常见偏远地址
B4: 浙江明日之星供应链管理有限公司(深圳分公司）
B7: 亚马逊常见偏远地址
B9: Code/仓库代码 | C9: State/洲 | D9: Zip/邮编 | E9: City城市 | F9: Address | G9: 备注
B10: TEB4 | C10: NJ | D10: 8069 | E10: Penns Grove | F10: 747 Courses Landing Rd | G10: 需加收偏远附加费
B11: ALB1 | C11: NY | D11: 12033-9634 | E11: Castleton | F11: 1835 US Route 9 | G11: 需加收偏远附加费
B12: SWF1 | C12: NY | D12: 12575-5150 | E12: ROCK TAVERN | F12: 635 INTERNATIONAL BLVD | G12: 需加收偏远附加费
B13: PIT2 | C13: PA | D13: 15126-1002 | E13: IMPERIAL | F13: 1200 Westport Rd | G13: 需加收偏远附加费
B14: AVP3 | C14: PA | D14: 18424-9492 | E14: GOULDSBORO | F14: 298 1ST AVE | G14: 需加收偏远附加费
B15: RDG1 | C15: PA | D15: 19526 | E15: HAMBURG | F15: 3563 Mountain Road | G15: 需加收偏远附加费
B16: IUSL | C16: MD | D16: 21901-2914 | E16: NORTH EAST | F16: 600 PRINCIPIO PKWY W | G16: 需加收偏远附加费
B17: MDT2 | C17: MD | D17: 21901-2914 | E17: North East | F17: 600 Principio Parkway West | G17: 需加收偏远附加费
B18: RIC1 | C18: VA | D18: 23803 | E18: Petersburg | F18: 5000 Commerce Way | G18: 需加收偏远附加费
B19: CSG1 | C19: GA | D19: 30259-2867 | E19: Moreland | F19: 280 BRIDGEPORT BLVD | G19: 需加收偏远附加费
B20: MGE3 | C20: GA | D20: 30549 | E20: Jefferson | F20: 808 Hog Mountain Road | G20: 需加收偏远附加费
B21: ATL3 | C21: GA | D21: 30567 | E21: Pendergrass | F21: 445 Valentine Industrial Parkway | G21: 需加收偏远附加费
B22: HSV1 | C22: AL | D22: 35756-4403 | E22: MADISON | F22: 7817 Greenbrier Road | G22: 需加收偏远附加费
B23: BNA2 | C23: TN | D23: 37090-8123 | E23: Lebanon | F23: 500 Duke Dr | G23: 需加收偏远附加费
B24: BNA1 | C24: TN | D24: 37090 | E24: Lebanon | F24: 14840 Central Pike Suite 190 | G24: 需加收偏远附加费
B25: CHA2 | C25: TN | D25: 37310-1400 | E25: Charleston | F25: 225 Infinity Dr NW | G25: 需加收偏远附加费
B26: MEM2 | C26: MS | D26: 38611-2306 | E26: BYHALIA | F26: 191 NORFOLK SOUTHERN WAY | G26: 需加收偏远附加费
B27: KY1 | C27: KY | D27: 40165 | E27: Shepherdsville | F27: 120 Velocity Way | G27: 需加收偏远附加费
B28: SDF9 | C28: KY | D28: 40165 | E28: Shepherdsville | F28: 100 W. Thomas P. Echols Lane | G28: 需加收偏远附加费
B29: SDF7 | C29: KY | D29: 40165 | E29: Shepherdsville | F29: 300 Omicron Court | G29: 需加收偏远附加费
B30: SDF6 | C30: KY | D30: 40165 | E30: Shepherdsville | F30: 271 Omega Pkwy | G30: 需加收偏远附加费
B31: SDF4 | C31: KY | D31: 40165 | E31: Shepherdsville | F31: 376 Zappos.com Blvd | G31: 需加收偏远附加费
B32: SDF1 | C32: KY | D32: 42718-2454 | E32: Campbellsville | F32: 1050 South Columbia | G32: 需加收偏远附加费
B33: IND4 | C33: IN | D33: 46231-1132 | E33: Indianapolis | F33: 710 S. Girls School Rd | G33: 需加收偏远附加费
B34: ORD2 | C34: IL | D34: 60410-8758 | E34: CHANNAHON | F34: 23714 W Amoco Rd | G34: 需加收偏远附加费
B35: MDW7 | C35: IL | D35: 60449 | E35: Monee | F35: 6605 Monee Manhattan Road | G35: 需加收偏远附加费
B36: KS1 | C36: Edgerton | D36: 66021 | E36: KS | F36: 30801 W 191ST ST | G36: 需加收偏远附加费
B37: MKC4 | C37: KS | D37: 66021-9588 | E37: Edgerton | F37: 19645 Waverly Rd | G37: 需加收偏远附加费
B38: TUL1 | C38: KS | D38: 67337 | E38: Coffeyville | F38: 2654 North Highway 169 | G38: 需加收偏远附加费
B39: FTW5 | C39: TX | D39: 75126-3566 | E39: FORNEY | F39: 1475 AKRON WAY | G39: 需加收偏远附加费
B40: HOU3 | C40: TX | D40: 77423 | E40: Brookshire | F40: 31555 Highway 90 E | G40: 需加收偏远附加费
B41: DEN8 | C41: CO | D41: 80018 | E41: AURORA | F41: 21000 E 13th Ave | G41: 需加收偏远附加费
B42: RNO1 | C42: NV | D42: 89408 | E42: Fernley | F42: 1600 East Newlands RD | G42: 需加收偏远附加费
B43: SCK4 | C43: CA | D43: 95215-8354 | E43: STOCKTON | F43: 6001 S AUSTIN RD | G43: 需加收偏远附加费
B44: SCK1 | C44: CA | D44: 95215 | E44: STOCKTON | F44: 4532 NEWCASTLE RD | G44: 需加收偏远附加费
B45: MCE1 | C45: CA | D45: 95380-9684 | E45: TURLOCK | F45: 3200 Fulkerth Road | G45: 需加收偏远附加费

Sheet 美国海运偏远邮编
B4: 浙江明日之星供应链管理有限公司(深圳分公司）
B7: 美 国 海 运 偏 远 邮 编
B9: 邮编 | C9: 邮编 | D9: 邮编 | E9: 邮编 | F9: 邮编 | G9: 邮编 | H9: 邮编 | I9: 邮编 | J9: 邮编 | K9: 邮编 | L9: 邮编 | M9: 邮编 | N9: 邮编 | O9: 邮编 | P9: 邮编 | R9: 邮编 | S9: 邮编 | T9: 邮编 | U9: 邮编 | V9: 邮编 | W9: 邮编 | X9: 邮编 | Y9: 邮编 | Z9: 邮编 | AA9: 邮编 | AB9: 邮编 | AC9: 邮编 | AD9: 邮编 | AE9: 邮编 | AF9: 邮编
B10: 1002 | C10: 1420 | D10: 1754 | E10: 2330 | F10: 2660 | G10: 2880 | H10: 3461 | I10: 3902 | J10: 4257 | K10: 4665 | L10: 5053 | M10: 5633 | N10: 6039 | O10: 6279 | P10: 6447 | R10: 1005 | S10: 1263 | T10: 2832 | U10: 3268 | V10: 3593 | W10: 3851 | X10: 4055 | Y10: 4290 | Z10: 4448 | AA10: 4556 | AB10: 4646 | AC10: 4746 | AD10: 4864 | AE10: 4979 | AF10: 5081
B11: 1004 | C11: 1430 | D11: 1756 | E11: 2331 | F11: 2662 | G11: 2883 | H11: 3466 | I11: 3903 | J11: 4259 | K11: 4669 | L11: 5055 | M11: 5641 | N11: 6043 | O11: 6280 | P11: 6469 | R11: 1008 | S11: 1264 | T11: 2833 | U11: 3269 | V11: 3595 | W11: 3852 | X11: 4056 | Y11: 4292 | Z11: 4449 | AA11: 4558 | AB11: 4648 | AC11: 4747 | AD11: 4910 | AE11: 4982 | AF11: 5083
B12: 1007 | C12: 1431 | D12: 1770 | E12: 2332 | F12: 2668 | G12: 2891 | H12: 3467 | I12: 3905 | J12: 4260 | K12: 4672 | L12: 5060 | M12: 5649 | N12: 6057 | O12: 6331 | P12: 6470 | R12: 1011 | S12: 1266 | T12: 2872 | U12: 3272 | V12: 3597 | W12: 3853 | X12: 4057 | Y12: 4294 | Z12: 4450 | AA12: 4562 | AB12: 4649 | AC12: 4750 | AD12: 4911 | AE12: 4983 | AF12: 5084
B13: 1010 | C13: 1432 | D13: 1773 | E13: 2338 | F13: 2669 | G13: 3032 | H13: 3468 | I13: 3907 | J13: 4263 | K13: 4675 | L13: 5061 | M13: 5654 | N13: 6059 | O13: 6333 | P13: 6474 | R13: 1012 | S13: 1270 | T13: 2873 | U13: 3273 | V13: 3601 | W13: 3855 | X13: 4063 | Y13: 4341 | Z13: 4451 | AA13: 4563 | AB13: 4650 | AC13: 4751 | AD13: 4912 | AE13: 4984 | AF13: 5085
B14: 1032 | C14: 1436 | D14: 1775 | E14: 2341 | F14: 2670 | G14: 3033 | H14: 3469 | I14: 3908 | J14: 4265 | K14: 4690 | L14: 5073 | M14: 5656 | N14: 6060 | O14: 6335 | P14: 6475 | R14: 1026 | S14: 1330 | T14: 2894 | U14: 3278 | V14: 3602 | W14: 3860 | X14: 4066 | Y14: 4342 | Z14: 4453 | AA14: 4564 | AB14: 4652 | AC14: 4756 | AD14: 4920 | AE14: 4985 | AF14: 5086
B15: 1033 | C15: 1438 | D15: 1826 | E15: 2347 | F15: 2671 | G15: 3034 | H15: 3470 | I15: 4002 | J15: 4266 | K15: 4730 | L15: 5089 | M15: 5657 | N15: 6062 | O15: 6339 | P15: 6478 | R15: 1029 | S15: 1339 | T15: 2898 | U15: 3279 | V15: 3603 | W15: 3864 | X15: 4068 | Y15: 4343 | Z15: 4454 | AA15: 4565 | AB15: 4653 | AC15: 4757 | AD15: 4921 | AE15: 4986 | AF15: 5142
B16: 1036 | C16: 1450 | D16: 1827 | E16: 2348 | F16: 2675 | G16: 3036 | H16: 3570 | I16: 4008 | J16: 4268 | K16: 4736 | L16: 5091 | M16: 5661 | N16: 6071 | O16: 6351 | P16: 6479 | R16: 1031 | S16: 1340 | T16: 3043 | U16: 3280 | V16: 3605 | W16: 3872 | X16: 4069 | Y16: 4348 | Z16: 4455 | AA16: 4567 | AB16: 4654 | AC16: 4758 | AD16: 4922 | AE16: 4987 | AF16: 5143
B17: 1038 | C17: 1451 | D17: 1830 | E17: 2355 | F17: 2702 | G17: 3037 | H17: 3581 | I17: 4015 | J17: 4270 | K17: 4738 | L17: 5101 | M17: 5662 | N17: 6072 | O17: 6353 | P17: 6480 | R17: 1034 | S17: 1341 | T17: 3047 | U17: 3282 | V17: 3607 | W17: 3875 | X17: 4071 | Y17: 4349 | Z17: 4457 | AA17: 4568 | AB17: 4655 | AC17: 4759 | AD17: 4923 | AE17: 4988 | AF17: 5146
B18: 1039 | C18: 1463 | D18: 1831 | E18: 2364 | F18: 2715 | G18: 3040 | H18: 3584 | I18: 4019 | J18: 4271 | K18: 4740 | L18: 5141 | M18: 5663 | N18: 6073 | O18: 6354 | P18: 6481 | R18: 1037 | S18: 1343 | T18: 3071 | U18: 3284 | V18: 3609 | W18: 3882 | X18: 4075 | Y18: 4352 | Z18: 4459 | AA18: 4570 | AB18: 4656 | AC18: 4760 | AD18: 4924 | AE18: 4989 | AF18: 5148
B19: 1056 | C19: 1464 | D19: 1832 | E19: 2366 | F19: 2717 | G19: 3044 | H19: 3585 | I19: 4021 | J19: 4274 | K19: 4742 | L19: 5150 | M19: 5664 | N19: 6075 | O19: 6355 | P19: 6482 | R19: 1050 | S19: 1344 | T19: 3082 | U19: 3285 | V19: 3740 | W19: 3883 | X19: 4076 | Y19: 4353 | Z19: 4460 | AA19: 4571 | AB19: 4657 | AC19: 4761 | AD19: 4925 | AE19: 5030 | AF19: 5149
B20: 1057 | C20: 1467 | D20: 1833 | E20: 2367 | F20: 2739 | G20: 3045 | H20: 3598 | I20: 4030 | J20: 4280 | K20: 4841 | L20: 5154 | M20: 5670 | N20: 6076 | O20: 6357 | P20: 6483 | R20: 1054 | S20: 1346 | T20: 3215 | U20: 3287 | V20: 3745 | W20: 3884 | X20: 4078 | Y20: 4354 | Z20: 4461 | AA20: 4572 | AB20: 4658 | AC20: 4762 | AD20: 4926 | AE20: 5031 | AF20: 5151
B21: 1059 | C21: 1468 | D21: 1860 | E21: 2534 | F21: 2743 | G21: 3046 | H21: 3604 | I21: 4038 | J21: 4281 | K21: 4843 | L21: 5156 | M21: 5671 | N21: 6077 | O21: 6360 | P21: 6487 | R21: 1066 | S21: 1350 | T21: 3216 | U21: 3290 | V21: 3746 | W21: 3886 | X21: 4088 | Y21: 4358 | Z21: 4462 | AA21: 4574 | AB21: 4660 | AC21: 4763 | AD21: 4928 | AE21: 5032 | AF21: 5152
... B460: 75189 | C460: 75693 | D460: 76241 | E460: 76633 | F460: 77473 | G460: 77979 | H460: 78560 | I460: 79029 | J460: 80520 | K460: 81303 | L460: 82942 | M460: 84049 | N460: 85228 | O460: 86303 | P460: 87508 | R460: 42404 | S460: 42649 | T460: 43007 | U460: 43310 | V460: 43457 | W460: 43733 | X460: 43836 | Y460: 44076 | Z460: 44818 | AA460: 45153 | AB460: 45642 | AC460: 45724 | AD460: 45820 | AE460: 46050 | AF460: 46348
B461: 87514 | C461: 88268 | D461: 91935 | E461: 92359 | F461: 93420 | G461: 93654 | H461: 94947 | I461: 95357 | J461: 95620 | K461: 95972 | L461: 97335 | M461: 97540 | N461: 98321 | O461: 98674 | R461: 46349 | S461: 46794 | T461: 47030 | U461: 47235 | V461: 47367 | W461: 47516 | X461: 47617 | Y461: 47879 | Z461: 47990 | AA461: 48467 | AB461: 48730 | AC461: 48835 | AD461: 49035 | AE461: 49268 | AF461: 49436
B462: 87516 | C462: 88310 | D462: 91978 | E462: 92372 | F462: 93421 | G462: 93657 | H462: 94948 | I462: 95358 | J462: 95626 | K462: 95973 | L462: 97338 | M462: 97601 | N462: 98322 | O462: 98802 | R462: 46365 | S462: 46910 | T462: 47031 | U462: 47236 | V462: 47368 | W462: 47519 | X462: 47619 | Y462: 47917 | Z462: 47991 | AA462: 48468 | AB462: 48731 | AC462: 48841 | AD462: 49040 | AE462: 49271 | AF462: 49446
B463: 87523 | C463: 88311 | D463: 92003 | E463: 92386 | F463: 93422 | G463: 93670 | H463: 94951 | I463: 95361 | J463: 95632 | K463: 95976 | L463: 97339 | M463: 97603 | N463: 98324 | O463: 98823 | R463: 46366 | S463: 46911 | T463: 47032 | U463: 47243 | V463: 47369 | W463: 47520 | X463: 47631 | Y463: 47918 | Z463: 47992 | AA463: 48469 | AB463: 48733 | AC463: 48845 | AD463: 49042 | AE463: 49274 | AF463: 49449
B464: 87532 | C464: 88330 | D464: 92026 | E464: 92391 | F464: 93423 | G464: 93673 | H464: 94952 | I464: 95370 | J464: 95639 | K464: 95980 | L464: 97341 | M464: 97707 | N464: 98325 | O464: 98824 | R464: 46374 | S464: 46912 | T464: 47035 | U464: 47245 | V464: 47370 | W464: 47521 | X464: 47633 | Y464: 47921 | Z464: 47993 | AA464: 48470 | AB464: 48735 | AC464: 48847 | AD464: 49045 | AE464: 49275 | AF464: 49450
B465: 87533 | C465: 88346 | D465: 92027 | E465: 92393 | F465: 93427 | G465: 93723 | H465: 94953 | I465: 95372 | J465: 95642 | K465: 96007 | L465: 97351 | M465: 97756 | N465: 98329 | O465: 98828 | R465: 46376 | S465: 46913 | T465: 47036 | U465: 47246 | V465: 47373 | W465: 47522 | X465: 47634 | Y465: 47922 | Z465: 47994 | AA465: 48472 | AB465: 48736 | AC465: 48849 | AD465: 49050 | AE465: 49276 | AF465: 49451
B466: 87547 | C466: 89019 | D466: 92028 | E466: 92394 | F466: 93434 | G466: 93901 | H466: 94978 | I466: 95373 | J466: 95650 | K466: 96073 | L466: 97352 | M466: 97759 | N466: 98333 | O466: 98829 | R466: 46379 | S466: 46916 | T466: 47037 | U466: 47247 | V466: 47380 | W466: 47524 | X466: 47635 | Y466: 47923 | Z466: 47995 | AA466: 48475 | AB466: 48737 | AC466: 48850 | AD466: 49052 | AE466: 49279 | AF466: 49452
B467: 87569 | C467: 89028 | D467: 92030 | E467: 92395 | F467: 93436 | G467: 93902 | H467: 95004 | I467: 95380 | J467: 95654 | K467: 96078 | L467: 97355 | M467: 97801 | N467: 98338 | O467: 98837 | R467: 46380 | S467: 46917 | T467: 47038 | U467: 47260 | V467: 47381 | W467: 47525 | X467: 47637 | Y467: 47926 | Z467: 48002 | AA467: 48610 | AB467: 48739 | AC467: 48851 | AD467: 49056 | AE467: 49284 | AF467: 49454
B468: 87574 | C468: 89029 | D468: 92040 | E468: 92398 | F468: 93437 | G468: 93905 | H468: 95005 | I468: 95381 | J468: 95658 | K468: 96087 | L468: 97361 | M468: 97838 | N468: 98339 | O468: 98841 | R468: 46381 | S468: 46920 | T468: 47040 | U468: 47263 | V468: 47382 | W468: 47527 | X468: 47640 | Y468: 47928 | Z468: 48004 | AA468: 48613 | AB468: 48740 | AC468: 48856 | AD468: 49057 | AE468: 49288 | AF468: 49455
B469: 87578 | C469: 89034 | D469: 92059 | E469: 92414 | F469: 93438 | G469: 93907 | H469: 95007 | I469: 95402 | J469: 95663 | K469: 96092 | L469: 97364 | M469: 97850 | N469: 98342 | O469: 98844 | R469: 46382 | S469: 46923 | T469: 47041 | U469: 47264 | V469: 47384 | W469: 47528 | X469: 47647 | Y469: 47929 | Z469: 48006 | AA469: 48614 | AB469: 48741 | AC469: 48860 | AD469: 49061 | AE469: 49303 | AF469: 49459
B470: 87582 | C470: 89048 | D470: 92065 | E470: 92543 | F470: 93440 | G470: 93912 | H470: 95012 | I470: 95404 | J470: 95665 | K470: 96146 | L470: 97366 | M470: 97882 | N470: 98343 | O470: 98848 | R470: 46390 | S470: 46926 | T470: 47042 | U470: 47265 | V470: 47386 | W470: 47529 | X470: 47649 | Y470: 47930 | Z470: 48022 | AA470: 48615 | AB470: 48742 | AC470: 48861 | AD470: 49063 | AE470: 49304 | AF470: 49611
B471: 87583 | C471: 89067 | D471: 92067 | E471: 92546 | F471: 93442 | G471: 93921 | H471: 95013 | I471: 95416 | J471: 95667 | K471: 96148 | L471: 97368 | M471: 97914 | N471: 98344 | O471: 98850 | R471: 46392 | S471: 46928 | T471: 47043 | U471: 47270 | V471: 47387 | W471: 47531 | X471: 47654 | Y471: 47932 | Z471: 48028 | AA471: 48618 | AB471: 48743 | AC471: 48862 | AD471: 49066 | AE471: 49305 | AF471: 49612
B472: 87722 | C472: 89166 | D472: 92075 | E472: 92548 | F472: 93443 | G472: 93922 | H472: 95018 | I472: 95422 | J472: 95668 | K472: 96150 | L472: 97369 | M472: 98010 | N472: 98346 | O472: 98923 | R472: 46501 | S472: 46929 | T472: 47108 | U472: 47272 | V472: 47390 | W472: 47536 | X472: 47660 | Y472: 47940 | Z472: 48032 | AA472: 48619 | AB472: 48744 | AC472: 48865 | AD472: 49067 | AE472: 49309 | AF472: 49613
... B487: 88081 | C487: 90264 | D487: 92278 | E487: 93218 | F487: 93546 | G487: 94556 | H487: 95301 | I487: 95486 | J487: 95924 | K487: 97051 | L487: 97439 | M487: 98255 | N487: 98532 | O487: 99362 | R487: 46742 | S487: 46985 | T487: 47160 | U487: 47342 | V487: 47452 | W487: 47575 | X487: 47850 | Y487: 47967 | Z487: 48419 | AA487: 48653 | AB487: 48770 | AC487: 48890 | AD487: 49238 | AE487: 49343 | AF487: 49634
B488: 88101 | C488: 90265 | D488: 92284 | E488: 93221 | F488: 93552 | G488: 94558 | H488: 95305 | I488: 95487 | J488: 95940 | K488: 97053 | L488: 97448 | M488: 98257 | N488: 98544 | R488: 46746 | S488: 46986 | T488: 47162 | U488: 47344 | V488: 47453 | W488: 47576 | X488: 47852 | Y488: 47968 | Z488: 48422 | AA488: 48654 | AB488: 48806 | AC488: 48891 | AD488: 49241 | AE488: 49346 | AF488: 49638
B489: 88102 | C489: 90290 | D489: 92286 | E489: 93223 | F489: 93560 | G489: 94559 | H489: 95309 | I489: 95490 | J489: 95945 | K489: 97055 | L489: 97449 | M489: 98260 | N489: 98556 | R489: 46759 | S489: 46988 | T489: 47163 | U489: 47345 | V489: 47454 | W489: 47577 | X489: 47854 | Y489: 47969 | Z489: 48426 | AA489: 48656 | AB489: 48807 | AC489: 48892 | AD489: 49246 | AE489: 49347 | AF489: 49639
B490: 88201 | C490: 90704 | D490: 92307 | E490: 93230 | F490: 93606 | G490: 94561 | H490: 95312 | I490: 95503 | J490: 95946 | K490: 97056 | L490: 97455 | M490: 98263 | N490: 98569 | R490: 46760 | S490: 46990 | T490: 47174 | U490: 47346 | V490: 47456 | W490: 47578 | X490: 47855 | Y490: 47970 | Z490: 48427 | AA490: 48659 | AB490: 48809 | AC490: 48893 | AD490: 49247 | AE490: 49349 | AF490: 49640
B491: 88202 | C491: 90742 | D491: 92308 | E491: 93232 | F491: 93615 | G491: 94562 | H491: 95315 | I491: 95519 | J491: 95948 | K491: 97058 | L491: 97459 | M491: 98264 | N491: 98584 | R491: 46761 | S491: 46991 | T491: 47175 | U491: 47348 | V491: 47457 | W491: 47580 | X491: 47858 | Y491: 47971 | Z491: 48432 | AA491: 48662 | AB491: 48811 | AC491: 48894 | AD491: 49248 | AE491: 49402 | AF491: 49642
B492: 88203 | C492: 91024 | D492: 92311 | E492: 93235 | F492: 93619 | G492: 94563 | H492: 95319 | I492: 95524 | J492: 95949 | K492: 97089 | L492: 97470 | M492: 98272 | N492: 98597 | R492: 46764 | S492: 46996 | T492: 47220 | U492: 47351 | V492: 47459 | W492: 47581 | X492: 47859 | Y492: 47974 | Z492: 48434 | AA492: 48701 | AB492: 48815 | AC492: 48897 | AD492: 49249 | AE492: 49403 | AF492: 49644
B493: 88210 | C493: 91310 | D493: 92312 | E493: 93245 | F493: 93625 | G493: 94570 | H493: 95320 | I493: 95534 | J493: 95951 | K493: 97113 | L493: 97471 | M493: 98274 | N493: 98604 | R493: 46766 | S493: 46998 | T493: 47223 | U493: 47352 | V493: 47460 | W493: 47584 | X493: 47860 | Y493: 47975 | Z493: 48435 | AA493: 48703 | AB493: 48816 | AC493: 49011 | AD493: 49251 | AE493: 49405 | AF493: 49645
B494: 88211 | C494: 91321 | D494: 92315 | E494: 93247 | F494: 93630 | G494: 94573 | H494: 95324 | I494: 95537 | J494: 95954 | K494: 97115 | L494: 97472 | M494: 98276 | N494: 98605 | R494: 46771 | S494: 47010 | T494: 47224 | U494: 47353 | V494: 47465 | W494: 47585 | X494: 47861 | Y494: 47977 | Z494: 48441 | AA494: 48705 | AB494: 48818 | AC494: 49013 | AD494: 49252 | AE494: 49408 | AF494: 49648
B495: 88220 | C495: 91322 | D495: 92317 | E495: 93257 | F495: 93631 | G495: 94574 | H495: 95326 | I495: 95540 | J495: 95958 | K495: 97116 | L495: 97478 | M495: 98277 | N495: 98606 | R495: 46772 | S495: 47011 | T495: 47227 | U495: 47354 | V495: 47468 | W495: 47590 | X495: 47862 | Y495: 47978 | Z495: 48445 | AA495: 48720 | AB495: 48819 | AC495: 49021 | AD495: 49253 | AE495: 49410 | AF495: 49649
B496: 88221 | C496: 91383 | D496: 92325 | E496: 93258 | F496: 93633 | G496: 94575 | H496: 95334 | I496: 95551 | J496: 95961 | K496: 97134 | L496: 97520 | M496: 98282 | N496: 98609 | R496: 46773 | S496: 47012 | T496: 47228 | U496: 47355 | V496: 47470 | W496: 47597 | X496: 47866 | Y496: 47980 | Z496: 48450 | AA496: 48721 | AB496: 48822 | AC496: 49026 | AD496: 49255 | AE496: 49411 | AF496: 49651
B497: 88240 | C497: 91384 | D497: 92326 | E497: 93274 | F497: 93636 | G497: 94581 | H497: 95340 | I497: 95602 | J497: 95965 | K497: 97137 | L497: 97524 | M497: 98290 | N497: 98622 | R497: 46776 | S497: 47016 | T497: 47229 | U497: 47357 | V497: 47471 | W497: 47598 | X497: 47868 | Y497: 47981 | Z497: 48453 | AA497: 48725 | AB497: 48829 | AC497: 49027 | AD497: 49256 | AE497: 49416 | AF497: 49653
B498: 88241 | C498: 91390 | D498: 92327 | E498: 93275 | F498: 93637 | G498: 94585 | H498: 95341 | I498: 95603 | J498: 95966 | K498: 97138 | L498: 97526 | M498: 98291 | N498: 98623 | R498: 46779 | S498: 47017 | T498: 47230 | U498: 47358 | V498: 47512 | W498: 47611 | X498: 47869 | Y498: 47982 | Z498: 48454 | AA498: 48726 | AB498: 48830 | AC498: 49028 | AD498: 49262 | AE498: 49419 | AF498: 49654
B499: 88244 | C499: 91901 | D499: 92344 | E499: 93292 | F499: 93638 | G499: 94599 | H499: 95344 | I499: 95604 | J499: 95967 | K499: 97146 | L499: 97527 | M499: 98292 | N499: 98626 | R499: 46785 | S499: 47018 | T499: 47231 | U499: 47359 | V499: 47513 | W499: 47612 | X499: 47871 | Y499: 47986 | Z499: 48456 | AA499: 48727 | AB499: 48831 | AC499: 49029 | AD499: 49263 | AE499: 49420 | AF499: 49655
... B501: 88265 | C501: 91931 | D501: 92358 | E501: 93412 | F501: 93648 | G501: 94938 | H501: 95348 | I501: 95619 | J501: 95969 | K501: 97333 | L501: 97533 | M501: 98312 | N501: 98671 | R501: 46792 | S501: 47024 | T501: 47234 | U501: 47366 | V501: 47515 | W501: 47616 | X501: 47874 | Y501: 47989 | Z501: 48466 | AA501: 48729 | AB501: 48834 | AC501: 49033 | AD501: 49266 | AE501: 49425 | AF501: 49659
R502: 49663 | S502: 49746 | T502: 49818 | U502: 49893 | V502: 49967 | W502: 50062 | X502: 50139 | Y502: 50222 | Z502: 50275 | AA502: 50471 | AB502: 50546 | AC502: 50603 | AD502: 50669 | AE502: 51003 | AF502: 51053
R503: 49664 | S503: 49747 | T503: 49819 | U503: 49895 | V503: 49968 | W503: 50064 | X503: 50140 | Y503: 50223 | Z503: 50276 | AA503: 50472 | AB503: 50551 | AC503: 50604 | AD503: 50670 | AE503: 51004 | AF503: 51055
R504: 49665 | S504: 49748 | T504: 49820 | U504: 49896 | V504: 49969 | W504: 50065 | X504: 50141 | Y504: 50225 | Z504: 50277 | AA504: 50473 | AB504: 50552 | AC504: 50605 | AD504: 50671 | AE504: 51005 | AF504: 51056
R505: 49666 | S505: 49749 | T505: 49821 | U505: 49901 | V505: 49970 | W505: 50066 | X505: 50142 | Y505: 50227 | Z505: 50278 | AA505: 50475 | AB505: 50554 | AC505: 50606 | AD505: 50672 | AE505: 51006 | AF505: 51058
R506: 49667 | S506: 49751 | T506: 49822 | U506: 49902 | V506: 49971 | W506: 50067 | X506: 50143 | Y506: 50228 | Z506: 50420 | AA506: 50476 | AB506: 50556 | AC506: 50607 | AD506: 50673 | AE506: 51007 | AF506: 51059
R507: 49668 | S507: 49752 | T507: 49825 | U507: 49903 | V507: 50001 | W507: 50068 | X507: 50144 | Y507: 50229 | Z507: 50421 | AA507: 50477 | AB507: 50557 | AC507: 50608 | AD507: 50674 | AE507: 51009 | AF507: 51060
R508: 49670 | S508: 49753 | T508: 49826 | U508: 49905 | V508: 50002 | W508: 50070 | X508: 50146 | Y508: 50230 | Z508: 50424 | AA508: 50478 | AB508: 50558 | AC508: 50609 | AD508: 50675 | AE508: 51010 | AF508: 51061
R509: 49673 | S509: 49755 | T509: 49827 | U509: 49908 | V509: 50005 | W509: 50071 | X509: 50147 | Y509: 50231 | Z509: 50426 | AA509: 50479 | AB509: 50559 | AC509: 50611 | AD509: 50676 | AE509: 51011 | AF509: 51062
R510: 49674 | S510: 49756 | T510: 49831 | U510: 49910 | V510: 50006 | W510: 50072 | X510: 50148 | Y510: 50232 | Z510: 50430 | AA510: 50480 | AB510: 50560 | AC510: 50612 | AD510: 50680 | AE510: 51012 | AF510: 51063
R511: 49679 | S511: 49757 | T511: 49833 | U511: 49911 | V511: 50007 | W511: 50073 | X511: 50149 | Y511: 50233 | Z511: 50431 | AA511: 50481 | AB511: 50561 | AC511: 50619 | AD511: 50681 | AE511: 51014 | AF511: 51201
R512: 49680 | S512: 49759 | T512: 49834 | U512: 49912 | V512: 50008 | W512: 50074 | X512: 50150 | Y512: 50234 | Z512: 50432 | AA512: 50482 | AB512: 50562 | AC512: 50621 | AD512: 50682 | AE512: 51016 | AF512: 51230
R513: 49682 | S513: 49760 | T513: 49835 | U513: 49913 | V513: 50020 | W513: 50075 | X513: 50151 | Y513: 50235 | Z513: 50433 | AA513: 50483 | AB513: 50563 | AC513: 50623 | AD513: 50801 | AE513: 51018 | AF513: 51231
... R1198: 95546 | S1198: 95637 | T1198: 95912 | U1198: 95981 | V1198: 96051 | W1198: 96110 | X1198: 97021 | Y1198: 97136 | Z1198: 97413 | AA1198: 97476 | AB1198: 97630 | AC1198: 97817 | AD1198: 97877 | AE1198: 98261 | AF1198: 98380
R1199: 98381 | S1199: 98582 | T1199: 98648 | U1199: 98862 | V1199: 99036 | W1199: 99148 | X1199: 99347
R1200: 98394 | S1200: 98583 | T1200: 98649 | U1200: 98920 | V1200: 99039 | W1200: 99149 | X1200: 99348
R1201: 98396 | S1201: 98585 | T1201: 98650 | U1201: 98921 | V1201: 99040 | W1201: 99150 | X1201: 99349
R1202: 98397 | S1202: 98586 | T1202: 98651 | U1202: 98922 | V1202: 99101 | W1202: 99151 | X1202: 99350
R1203: 98526 | S1203: 98587 | T1203: 98670 | U1203: 98925 | V1203: 99102 | W1203: 99152 | X1203: 99356
R1204: 98527 | S1204: 98588 | T1204: 98672 | U1204: 98926 | V1204: 99103 | W1204: 99153 | X1204: 99357
R1205: 98530 | S1205: 98589 | T1205: 98673 | U1205: 98929 | V1205: 99105 | W1205: 99154 | X1205: 99359
R1206: 98533 | S1206: 98590 | T1206: 98675 | U1206: 98930 | V1206: 99107 | W1206: 99155 | X1206: 99360
R1207: 98535 | S1207: 98591 | T1207: 98811 | U1207: 98932 | V1207: 99109 | W1207: 99156 | X1207: 99361
R1208: 98536 | S1208: 98592 | T1208: 98812 | U1208: 98933 | V1208: 99110 | W1208: 99157 | X1208: 99363
R1209: 98537 | S1209: 98593 | T1209: 98813 | U1209: 98935 | V1209: 99111 | W1209: 99158 | X1209: 99371
R1210: 98538 | S1210: 98595 | T1210: 98814 | U1210: 98936 | V1210: 99113 | W1210: 99159 | X1210: 99401
R1211: 98539 | S1211: 98596 | T1211: 98815 | U1211: 98937 | V1211: 99114 | W1211: 99160 | X1211: 99402
R1212: 98541 | S1212: 98601 | T1212: 98816 | U1212: 98938 | V1212: 99115 | W1212: 99161
R1213: 98542 | S1213: 98602 | T1213: 98817 | U1213: 98940 | V1213: 99116 | W1213: 99166
R1214: 98546 | S1214: 98603 | T1214: 98819 | U1214: 98941 | V1214: 99117 | W1214: 99167
R1215: 98547 | S1215: 98610 | T1215: 98821 | U1215: 98943 | V1215: 99118 | W1215: 99169
R1216: 98548 | S1216: 98611 | T1216: 98822 | U1216: 98946 | V1216: 99119 | W1216: 99170
R1217: 98550 | S1217: 98612 | T1217: 98826 | U1217: 98947 | V1217: 99122 | W1217: 99171
R1218: 98552 | S1218: 98613 | T1218: 98827 | U1218: 98948 | V1218: 99123 | W1218: 99173
R1219: 98554 | S1219: 98614 | T1219: 98830 | U1219: 98950 | V1219: 99124 | W1219: 99174
R1220: 98555 | S1220: 98616 | T1220: 98831 | U1220: 98952 | V1220: 99125 | W1220: 99176
R1221: 98557 | S1221: 98617 | T1221: 98832 | U1221: 99004 | V1221: 99126 | W1221: 99179
R1222: 98559 | S1222: 98619 | T1222: 98833 | U1222: 99006 | V1222: 99127 | W1222: 99180
R1223: 98560 | S1223: 98620 | T1223: 98834 | U1223: 99008 | V1223: 99128 | W1223: 99181
... R1239: 98581 | S1239: 98647 | T1239: 98860 | U1239: 99034 | V1239: 99147 | W1239: 99346

Sheet 夏威夷&阿拉斯加邮编无服务
B4: 浙江明日之星供应链管理(深圳分公司）有限公司
B6: 夏威夷&阿拉斯加邮编无服务
B8: Remote HI ZIP Codes | G8: Remote AK ZIP Codes
B9: 邮编 | C9: 邮编 | D9: 邮编 | E9: 邮编 | G9: 邮编 | H9: 邮编 | I9: 邮编 | J9: 邮编
B10: 96703 | C10: 96713 | D10: 96719 | E10: 96726 | G10: 99546 | H10: 99570 | I10: 99605 | J10: 99633
B11: 96704 | C11: 96714 | D11: 96720 | E11: 96727 | G11: 99547 | H11: 99571 | I11: 99606 | J11: 99634
B12: 96705 | C12: 96715 | D12: 96721 | E12: 96728 | G12: 99548 | H12: 99573 | I12: 99607 | J12: 99636
B13: 96708 | C13: 96716 | D13: 96722 | E13: 96729 | G13: 99549 | H13: 99574 | I13: 99608 | J13: 99637
B14: 96710 | C14: 96718 | D14: 96725 | E14: 96732 | G14: 99550 | H14: 99575 | I14: 99609 | J14: 99638
B15: 96733 | C15: 96742 | D15: 96748 | E15: 96753 | G15: 99551 | H15: 99576 | I15: 99612 | J15: 99640
B16: 96738 | C16: 96743 | D16: 96749 | E16: 96754 | G16: 99552 | H16: 99578 | I16: 99613 | J16: 99641
B17: 96739 | C17: 96745 | D17: 96750 | E17: 96755 | G17: 99553 | H17: 99579 | I17: 99614 | J17: 99642
B18: 96740 | C18: 96746 | D18: 96751 | E18: 96756 | G18: 99554 | H18: 99580 | I18: 99620 | J18: 99643
B19: 96741 | C19: 96747 | D19: 96752 | E19: 96757 | G19: 99555 | H19: 99581 | I19: 99621 | J19: 99644
B20: 96760 | C20: 96766 | D20: 96771 | E20: 96776 | G20: 99557 | H20: 99583 | I20: 99622 | J20: 99647
B21: 96761 | C21: 96767 | D21: 96772 | E21: 96777 | G21: 99558 | H21: 99584 | I21: 99623 | J21: 99648
... B26: 96783 | C26: 96793 | D26: 96784 | E26: 96796 | G26: 99564 | H26: 99590 | I26: 99628 | J26: 99655
G27: 99565 | H27: 99591 | I27: 99629 | J27: 99656
G28: 99566 | H28: 99602 | I28: 99630 | J28: 99657
G29: 99569 | H29: 99604 | I29: 99632 | J29: 99658
G30: 99659 | H30: 99684 | I30: 99726 | J30: 99748
G31: 99660 | H31: 99685 | I31: 99727 | J31: 99749
G32: 99661 | H32: 99686 | I32: 99729 | J32: 99750
G33: 99662 | H33: 99688 | I33: 99730 | J33: 99751
G34: 99663 | H34: 99689 | I34: 99731 | J34: 99752
G35: 99665 | H35: 99690 | I35: 99732 | J35: 99753
G36: 99666 | H36: 99691 | I36: 99733 | J36: 99754
G37: 99667 | H37: 99692 | I37: 99734 | J37: 99755
G38: 99668 | H38: 99693 | I38: 99736 | J38: 99756
... G61: 99780 | H61: 99781 | I61: 99782 | J61: 99783

Sheet 美国亚马逊仓库
B5: 浙江明日之星供应链管理有限公司(深圳分公司）
B8: 美国亚马逊仓库
B10: FBA Code | C10: 地 址 | D10: City | E10: State | F10: Zip | G10: Discharge Port 目的港 | H10: Pick Up City 内陆点
B11: MOB5 | C11: 6735 Trippel Road | D11: Mobile | E11: AL | F11: 36619 | G11: Los Angeles,CA | H11: Mobile, Alabama
B12: DPX1 | C12: 500 S. 48th Street | D12: Phoenix | E12: AZ | F12: 85034 | G12: Los Angeles,CA | H12: Los Angeles,CA
B13: PHX3 | C13: 6835 West Buckeye Road | D13: Pheonix | E13: AZ | F13: 85043 | G13: Los Angeles,CA | H13: Los Angeles,CA
B14: PHX5 | C14: 16980 W Commerce Drive | D14: Goodyear | E14: AZ | F14: 85338 | G14: Los Angeles,CA | H14: Los Angeles,CA
B15: PHX6 | C15: 4750 West Mohave St | D15: Pheonix | E15: AZ | F15: 85043 | G15: Los Angeles,CA | H15: Los Angeles,CA
B16: PHX7 | C16: 800 N 75th Ave | D16: Pheonix | E16: AZ | F16: 85043 | G16: Los Angeles,CA | H16: Los Angeles,CA
B17: PHX8 | C17: 800 N 75th Ave | D17: Phoenix | E17: AZ | F17: 85043 | G17: Los Angeles,CA | H17: Los Angeles,CA
B18: PHX9 | C18: 777 S 79th Ave | D18: Tolleson | E18: AZ | F18: 85353 | G18: Los Angeles,CA | H18: Los Angeles,CA
B19: TFC1 | C19: 5050 West Mohave St | D19: Pheonix | E19: AZ | F19: 85043 | G19: Los Angeles,CA | H19: Los Angeles,CA
B20: TUS1 | C20: 533 W Lower Buckey Road | D20: Phoenix | E20: AZ | F20: 85043 | G20: Los Angeles,CA | H20: Los Angeles,CA
B21: UAZ1 | D21: Phoenix | E21: AZ | F21: 85001 | G21: Los Angeles,CA | H21: Los Angeles,CA
B22: XUSH | C22: 7037 West Van Buren Street | D22: Pheonix | E22: AZ | F22: 85043 | G22: Los Angeles,CA | H22: Los Angeles,CA
B23: ABE7 | C23: 12510 Micro Dr | D23: Mira Loma | E23: CA | F23: 91752 | G23: Los Angeles,CA | H23: Los Angeles,CA
B24: DLA1 | C24: 900 W Florence Ave. | D24: Inglewood | E24: CA | F24: 90301 | G24: Los Angeles,CA | H24: Los Angeles,CA
B25: DLA2 | C25: 5650 Dolly Ave. | D25: Buena Park | E25: CA | F25: 90621 | G25: Los Angeles,CA | H25: Los Angeles,CA
B26: DLA3 | C26: 5829 Smithway St. | D26: Commerce | E26: CA | F26: 90040 | G26: Los Angeles,CA | H26: Los Angeles,CA
B27: DLA4 | C27: 9031 Lurline Ave. | D27: Chatsworth | E27: CA | F27: 91311 | G27: Los Angeles,CA | H27: Los Angeles,CA
B28: DLA5 | C28: 6250 Sycamore Canyon Blvd. | D28: Riverside | E28: CA | F28: 92507 | G28: Los Angeles,CA | H28: Los Angeles,CA
B29: DLA8 | C29: 2815 W. El Segundo Blvd. | D29: Hawthorne | E29: CA | F29: 90250 | G29: Los Angeles,CA | H29: Los Angeles,CA
B30: DSD1 | C30: 7130 Miramar Rd. 300A | D30: San Diego | E30: CA | F30: 92121 | G30: Los Angeles,CA | H30: Los Angeles,CA
B31: DSD2 | C31: 2777 Loker Ave W. | D31: Carlsbad | E31: CA | F31: 92010 | G31: Los Angeles,CA | H31: Los Angeles,CA
B32: FAT1 | C32: 3575 S Orange Ave | D32: Fresno | E32: CA | F32: 93725 | G32: Los Angeles,CA | H32: Los Angeles,CA
B33: HCA3 | C33: 3334 N SAN FERNANDO RD BLDG E | D33: Los Angeles | E33: CA | F33: 90065 | G33: Los Angeles,CA | H33: Los Angeles,CA
... B55: SNA9 | C55: 5250 Goodman Road | D55: Eastvale | E55: CA | F55: 92880 | G55: LOS ANGELES,CA | H55: LOS ANGELES,CA
B56: UCA2 | D56: Redondo Beach | E56: CA | F56: 90277 | G56: Los Angeles,CA | H56: Los Angeles,CA
B57: UCA3 | C57: 11800 W Olympic Blvd. | D57: Los Angeles | E57: CA | F57: 90064 | G57: Los Angeles,CA | H57: Los Angeles,CA
B58: UCA4 | C58: 2006 McGaw Ave. | D58: Irvine | E58: CA | F58: 92614 | G58: Los Angeles,CA | H58: Los Angeles,CA
B59: UCA5 | C59: Silver Lake | D59: Silver Lake | E59: CA | F59: 90001 | G59: Los Angeles,CA | H59: Los Angeles,CA
B60: UCA6 | C60: 2727 Kurtz St. | D60: San Diego | E60: CA | F60: 92110 | G60: Los Angeles,CA | H60: Los Angeles,CA
B61: VUBD | C61: 17182 Nevada Avenue | D61: Victorville | E61: CA | F61: 92345 | G61: Los Angeles,CA | H61: Los Angeles,CA
B62: VUGE | C62: 3450 DULLES DR | D62: Mira Loma | E62: CA | F62: 91752 | G62: Los Angeles,CA | H62: Los Angeles,CA
B63: VUKF | C63: 18120 Bishop Ave | D63: Carson | E63: CA | F63: 90746 | G63: Los Angeles,CA | H63: Los Angeles,CA
B64: VUMX | C64: 241 E Pacific Coast Hwy | D64: Wilmington | E64: CA | F64: 90744 | G64: Los Angeles,CA | H64: Los Angeles,CA
B65: VUPQ | C65: 9211 Kaiser Way | D65: Fontana | E65: CA | F65: 92335 | G65: Los Angeles,CA | H65: Los Angeles,CA
B66: VUTD | C66: 8291 Milliken Avenue | D66: Rancho Cucomonga | E66: CA | F66: 91730 | G66: Los Angeles,CA | H66: Los Angeles,CA
B67: XUSJ | C67: 1590 Tamarind Ave | D67: Rialto | E67: CA | F67: 92376 | G67: Los Angeles,CA | H67: Los Angeles,CA
B68: XUSV | C68: 2125 San Bernardino Ave | D68: San Bernardino | E68: CA | F68: 92408 | G68: Los Angeles,CA | H68: Los Angeles,CA
B69: LAX9 | C69: 11263 Oleander Ave | D69: FONTANA | E69: CA | F69: 92337 | G69: Los Angeles,CA
B70: XIX2 | C70: 2020 E CENTRAL AVE | D70: SAN Bernardino | E70: CA | F70: 92408 | G70: Los Angeles,CA
B71: DAV1 | C71: 1 Shields Ave, Room 182 | D71: Davis | E71: CA | F71: 95616 | G71: OAKLAND,CA | H71: OAKLAND,CA
B72: DSF1 | C72: 990 Beecher St. | D72: San Leandro | E72: CA | F72: 94577 | G72: OAKLAND,CA | H72: OAKLAND,CA
B73: DSF3 | C73: 1700 Montague Expy. | D73: San Jose | E73: CA | F73: 95131 | G73: OAKLAND,CA | H73: OAKLAND,CA
B74: DSF5 | C74: 250 Utah Avenue | D74: South San Francisco | E74: CA | F74: 94080 | G74: OAKLAND,CA | H74: OAKLAND,CA
B75: DSF6 | C75: 6015 Giant Road | D75: Richmond | E75: CA | F75: 94080 | G75: OAKLAND,CA | H75: OAKLAND,CA
B76: OAK3 | C76: 255 Park Center Drive | D76: Patterson | E76: CA | F76: 95363 | G76: OAKLAND,CA | H76: OAKLAND,CA
B77: OAK4 | C77: 1555 N. Chrisman Rd | D77: Tracy | E77: CA | F77: 95304 | G77: OAKLAND,CA | H77: OAKLAND,CA
B78: OAK5 | C78: 38811 Cherry Street | D78: Newark | E78: CA | F78: 94560 | G78: OAKLAND,CA | H78: OAKLAND,CA
B79: OAK6 | C79: 1350 N. MacArthur Drive | D79: Tracy | E79: CA | F79: 95304 | G79: OAKLAND,CA | H79: OAKLAND,CA
B80: OAK7 | C80: 38811 Cherry St | D80: Newark | E80: CA | F80: 94560 | G80: OAKLAND,CA | H80: OAKLAND,CA
B81: OAK8 | C81: 1 Middleton Way | D81: American Canyon | E81: CA | F81: 94503 | G81: OAKLAND,CA | H81: OAKLAND,CA
B82: PCA1 | C82: 1565 N MacArthur Drive | D82: Tracy | E82: CA | F82: 95376 | G82: OAKLAND,CA | H82: OAKLAND,CA
... B97: UCO1 | C97: 480 E 55th Ave Suite 100 | D97: Denver | E97: CO | F97: 80216 | G97: Los Angeles,CA | H97: Denver,CO
B98: BDL1 | C98: 200 Old Iron Ore Rd | D98: Windsor | E98: CT | F98: 06095 | G98: Connecticut,CT | H98: Connecticut,CT
B99: BDL2 | C99: 409 Washington Ave | D99: North Haven | E99: CT | F99: 06473 | G99: Connecticut,CT | H99: Connecticut,CT
B100: BDL5 | C100: 29 Research Parkway | D100: Wallingford | E100: CT | F100: 06492 | G100: Connecticut,CT | H100: Connecticut,CT
B101: PHL1 | C101: 1 Centerpoint Blvd. | D101: New Castle | E101: DE | F101: 19720 | G101: New York,NY | H101: New York,NY
B102: PHL3 | C102: 1600 Johnson Way | D102: New Castle | E102: DE | F102: 19720 | G102: New York,NY | H102: New York,NY
B103: PHL7 | C103: 560 Merrimac Ave | D103: Middletown | E103: DE | F103: 19709 | G103: New York,NY | H103: New York,NY
B104: PHL8 | C104: 727 N. Broad Street | D104: Middletown | E104: DE | F104: 19709 | G104: New York,NY | H104: New York,NY
B105: JAX1 | C105: 12900 Pecan Park Road | D105: Jacksonville | E105: FL | F105: 32218 | G105: Jacksonville | H105: Jacksonville
B106: JAX2 | C106: 12900 Pecan Park Road | D106: Jacksonville | E106: FL | F106: 32218 | G106: Jacksonville | H106: Jacksonville
B107: JAX3 | C107: 13333 103rd St | D107: Jacksonville | E107: FL | F107: 32221 | G107: Jacksonville | H107: Jacksonville
B108: JAX5 | C108: 4948 Bulls Bay Hwy | D108: Jacksonville | E108: FL | F108: 32219 | G108: Jacksonville | H108: Jacksonville
B109: MCO1 | C109: 12340 Boggy Creek Rd | D109: Orlando | E109: FL | F109: 32824 | G109: Jacksonville | H109: Jacksonville
B110: UFL4 | C110: 7469 Kingspointe Parkway | D110: Orlando | E110: FL | F110: 32819 | G110: Jacksonville | H110: Jacksonville
B111: XUSF | C111: 901 West Landstreet Road Suite C | D111: Orlando | E111: FL | F111: 32824 | G111: Jacksonville | H111: Jacksonville
B112: DJA1 | C112: 11084 Cabot Commerce Circle | D112: Jacksonville | E112: FL | F112: 32226 | G112: Jacksonville,FL | H112: Jacksonville,FL
... B140: SAV3 | C140: 7001 Skipper Rd | D140: Macon | E140: GA | F140: 31216 | G140: Atlanta,GA | H140: Atlanta,GA
B141: UGA1 | D141: Atlanta | E141: GA | F141: 30318 | G141: Atlanta,GA | H141: Atlanta,GA
B142: UGA2 | D142: Atlanta | E142: GA | F142: 30318 | G142: Atlanta,GA | H142: Atlanta,GA
B143: UGA3 | C143: 2160 Breckinridge Blvd Bldg 100 Suite 100 | D143: Lawrenceville | E143: GA | F143: 30043 | G143: Atlanta,GA | H143: Atlanta,GA
B144: VUAT | C144: 6855 Shannon Pkwy | D144: Union City | E144: GA | F144: 30291 | G144: Atlanta,GA | H144: Atlanta,GA
B145: VUKG | C145: 3201 Centre Parkway | D145: East Point | E145: GA | F145: 30344 | G145: Atlanta,GA | H145: Atlanta,GA
B146: VUOJ | C146: 250 Declaration Avenue, Suite 500 | D146: McDonough | E146: GA | F146: 30253 | G146: Atlanta,GA | H146: Atlanta,GA
B147: VUPK | C147: 6720 Oakley Industrial Blvd | D147: Union City | E147: GA | F147: 30291 | G147: Atlanta,GA | H147: Atlanta,GA
B148: VUPN | C148: 340 Westridge Parkway | D148: McDonough | E148: GA | F148: 30253 | G148: Atlanta,GA | H148: Atlanta,GA
B149: DCH1 | C149: 2801 S. Western Ave. | D149: Chicago | E149: IL | F149: 60608 | G149: Chicago,IL | H149: Chicago,IL
B150: DCH2 | C150: 8220 Austin Ave. | D150: Morton Grove | E150: IL | F150: 60053 | G150: Chicago,IL | H150: Chicago,IL
B151: DCH3 | C151: 4500 Western Ave. | D151: Lisle | E151: IL | F151: 60532 | G151: Chicago,IL | H151: Chicago,IL
B152: HIL1 | C152: 1111 Cherry Street | D152: Chicago | E152: IL | F152: 60642 | G152: Chicago,IL | H152: Chicago,IL
B153: HIL2 | C153: 1111 N Cherry Ave | D153: Chicago | E153: IL | F153: 60642 | G153: Chicago,IL | H153: Chicago,IL
B154: MDW1 | C154: Greater Chicago Area | D154: Joliet | E154: IL | F154: 60433 | G154: Chicago,IL | H154: Chicago,IL
... B189: XUSE | C189: 5460 Industial Court Suite 300 | D189: Whitestown | E189: IN | F189: 46075 | G189: Indianapolis | H189: Indianapolis
B190: IND9 | C190: 1151 S GRAHAM RD | D190: GREENWOOD | E190: IN | F190: 46143 | G190: Los Angeles,CA
B191: MCI1 | C191: 16851 W 113th St | D191: Lenexa | E191: KS | F191: 66219 | G191: Kansas city,KS | H191: Kansas city,KS
B192: MCI5 | C192: 16851 W 113th St. Lenexa Logistics Center | D192: Lenexa | E192: KS | F192: 66219 | G192: Kansas city,KS | H192: Kansas city,KS
B193: MCI7 | C193: 27200 W 157th St | D193: New Century | E193: KS | F193: 66031 | G193: Kansas city,KS | H193: Kansas city,KS
B194: MCIX | C194: 113th Street and Renner Boulevard | D194: Lenexa | E194: KS | F194: 66219 | G194: Kansas city,KS | H194: Kansas city,KS
B195: MKC4 | C195: 19645 Waverly Rd | D195: Edgerton | E195: KS | F195: 66021 | G195: Kansas city,KS | H195: Kansas city,KS
B196: MKC6 | C196: 6925 Riverview Ave | D196: Kansas City | E196: KS | F196: 66102 | G196: Kansas city,KS | H196: Kansas city,KS
B197: TUL1 | C197: 2654 North Highway 169 | D197: Coffeyville | E197: KS | F197: 67337 | G197: Kansas city,KS | H197: Kansas city,KS
B198: XUSK | C198: 31450 W 196th St. | D198: Edgerton | E198: KS | F198: 66021 | G198: Kansas city,KS | H198: Kansas city,KS
B199: CVG1 | C199: 1155 Worldwide Blvd. | D199: Hebron | E199: KY | F199: 41048 | G199: Cincinnati,OH | H199: Cincinnati,OH
B200: CVG2 | C200: 1600 Worldwide Blvd. | D200: Hebron | E200: KY | F200: 41048 | G200: Cincinnati,OH | H200: Cincinnati,OH
B201: CVG3 | C201: 3680 Langley Dr. | D201: Hebron | E201: KY | F201: 41048 | G201: Cincinnati,OH | H201: Cincinnati,OH
B202: CVG5 | C202: 2285 Litton Way | D202: Hebron | E202: KY | F202: 41048 | G202: Cincinnati,OH | H202: Cincinnati,OH
... B219: SDF9 | C219: 100 W. Thomas P. Echols Lane | D219: Shepherdsville | E219: KY | F219: 40165 | G219: Cincinnati,OH | H219: Cincinnati,OH
...

Sheet 发票模版
B4: 浙江明日之星供应链管理有限公司
B7: MRZX-发票模板
B9: 发件人信息 | H9: 收件人信息
B10: Ref./ 批次跟踪号: | F10: 箱数/件数: | H10: Consignee 收件人:
B11: Shipper 发件人: | H11: Company Name 公司名:
B12: Company Name 公司名: | H12: Country 国家/区域: | I12: 91730
B13: Address 地址: | H13: Address 地址:
B14: City 城市名: | F14: Province 省: | H14: City 城市名: | M14: Province 州省: | N14: CA/California
B15: Postal Code 邮编: | F15: Phone 电话: | H15: Phone 电话: | M15: FBA 仓库代码:
B16: 额外服务:
B17: 备注:
B19: FBA编号 | C19: Reference ID | D19: 材积CM (长*宽*高) | E19: 箱数 | F19: 单件毛重(KGS) | G19: 海关编码 HSCODE | H19: 中文品名 | I19: 英文品名 | J19: 数量 (PCS) | K19: 单价 (USD) | L19: 品牌 | M19: 规格型号 | N19: 材质 | O19: 用途 | P19: 产品图片
B20: 卡派必填 | C20: 卡派必填 | D20: 45.45.52 | E20: 20 | F20: 14 | G20: 必填 | H20: 必填 | I20: purning shears | J20: 400 | K20: 20 | N20: 塑料+钢 | O20: 剪树枝 | P20: 必填
