Workbook

Sheet 模板(版本20251230)
A1: 客户订单号 | B1: FBA198W1881X | E1: 带电* | F1: 否
A2: 服务* | B2: 丰速达20T卡派 | E2: 带磁* | F2: 否
A3: 地址库编码 | B3: MCC1 | E3: 液体* | F3: 否
A4: 收件人姓名* | B4: =IFERROR(VLOOKUP(B3,地址库!A1:$N$628,3,FALSE),"仓库代码无效，如是非亚马逊地址，删除所有公式后填写") | E4: 粉末* | F4: 否
A5: 收件人公司 | E5: 危险品* | F5: 否
A6: 收件人地址一* | B6: =VLOOKUP(B3,地址库!A1:$N$628,8,FALSE) | E6: 报关方式* | F6: 买单报关
A7: 收件人地址二 | E7: 清关方式 | F7: 一般贸易清关
A8: 收件人地址三 | E8: 交税方式 | F8: 包税
A9: 收件人城市* | B9: =VLOOKUP(B3,地址库!A1:$N$628,11,FALSE) | E9: 交货条款
A10: 收件人省份/州 | B10: =VLOOKUP(B3,地址库!A1:$N$628,12,FALSE) | E10: VAT号*
A11: 收件人邮编* | B11: =VLOOKUP(B3,地址库!A1:$N$628,14,FALSE) | E11: 参考号一
A12: 收件人国家代码(二字代码)* | B12: =VLOOKUP(B3,地址库!A1:$N$628,13,FALSE) | E12: 申报币种** | F12: 美元
A13: 收件人电话 | E13: 备注* | J13: 填入开船时间 | K13: 预计送仓天数 | L13: 预计送仓时间
A14: 收件人邮箱 | E14: 亚马逊预约配送时段* （必填） | J14: 年/月/日 | K14: =VLOOKUP(B2&B3,预计送仓数据!A1:$E$1000,4,FALSE) | L14: =K14+J14
A15: 所在货站 | B15: 深圳坂田仓库 | E15: 亚马逊上架总数量* （必填）
A16: 箱数* | B16: 1
A17: 货箱编号* | B17: PO Number* | C17: 货箱重量(KG) | D17: 货箱长度(CM) | E17: 货箱宽度(CM) | F17: 货箱高度(CM) | G17: 产品英文品名* | H17: 产品中文品名* | I17: 产品申报单价* | J17: 产品申报数量* （单箱产品个数） | K17: 产品材质* | L17: 产品海关编码* | M17: 产品用途* | N17: 产品品牌* | O17: 产品型号* | P17: 产品图片* | Q17: 产品销售链接*
A18: FBA198W1881XU000001-1 | B18: 1CNUE1YS | C18: 18.5 | D18: 1 | E18: 1 | F18: 1 | G18: nylon web belt | H18: 尼龙腰带 | I18: 3 | J18: 56 | K18: Nylon + alloy | L18: 6217.10.9530 | M18: wear | N18: N/A | O18: N/A | P18: 1 | Q18: 1

Sheet 报关方式
A1: 买单报关
A2: 报关退税
A3: 普通报关
A4: 9710
A5: 9810

Sheet 发货渠道
A1: 渠道名称 | B1: 板块
A2: 丰速达16T卡派 | B2: 美国海运
A3: 丰速达16T自税卡派 | B3: 美国海运
A4: 丰速达16T快递派 | B4: 美国海运
A5: 丰速达18T卡派 | B5: 美国海运
A6: 丰速达18T自税卡派 | B6: 美国海运
A7: 丰速达18T快递派 | B7: 美国海运
A8: 丰速达20T卡派 | B8: 美国海运
A9: 丰速达20T自税卡派 | B9: 美国海运
A10: 丰速达20T快递派 | B10: 美国海运
A11: 普船特惠卡派 | B11: 美国海运
A12: 纽约普船卡派 | B12: 美国海运
... A95: 墨西哥双清包税卡派 | B95: 墨西哥

Sheet 地址库
A1: 美国亚马逊地址
A2: 地址简称* | B2: 地址编码* | C2: FBA仓库代码 | D2: 联系人* | E2: 公司名 | F2: 联系电话 | G2: 联系手机 | H2: 地址一* | I2: 地址二 | J2: 地址三 | K2: 城市* | L2: 省/洲 | M2: 国家* | N2: 邮编*
A3: TEB9 | B3: TEB9 | C3: TEB9 | D3: TEB9 | E3: Amazon | F3: 1234567890 | H3: 601 Randolph Road | K3: SOMERSET | L3: NJ | M3: US | N3: 08873
A4: LGA9 | B4: LGA9 | C4: LGA9 | D4: LGA9 | E4: Amazon | F4: 1234567890 | H4: 2170 Route 27 | K4: Edison | L4: NJ | M4: US | N4: 08817
A5: EL96 | B5: EL96 | C5: EL96 | D5: EL96 | E5: Amazon | F5: 1234567890 | H5: 10 sigle lane, unit b | K5: Dayton | L5: NJ | M5: US | N5: 08810
A6: EWR4 | B6: EWR4 | C6: EWR4 | D6: EWR4 | E6: Amazon | F6: 1234567890 | H6: 50 New Canton Way | K6: Robbinsville | L6: NJ | M6: US | N6: 08691
A7: ABE8-401 | B7: ABE8-401 | C7: ABE8-401 | D7: ABE8-401 | E7: Amazon | F7: 1234567890 | H7: 401 Independence Road | K7: Florence | L7: NJ | M7: US | N7: 08518
A8: ABE8-309 | B8: ABE8-309 | C8: ABE8-309 | D8: ABE8-309 | E8: Amazon | F8: 1234567890 | H8: 309 Cedar Lane | K8: Florence | L8: NJ | M8: US | N8: 08518
A9: ABE8 | B9: ABE8 | C9: ABE8 | D9: ABE8 | E9: Amazon | F9: 1234567890 | H9: 401 Independence Road | K9: Florence | L9: NJ | M9: US | N9: 08518
A10: TEB6 | B10: TEB6 | C10: TEB6 | D10: TEB6 | E10: Amazon | F10: 1234567890 | H10: 22 Hightstown Cranbury State Road | K10: Cranbury | L10: NJ | M10: US | N10: 08512
A11: TTN2 | B11: TTN2 | C11: TTN2 | D11: TTN2 | E11: Amazon | F11: 1234567890 | H11: 343 HALF ACRE RD | K11: CRANBURY | L11: NJ | M11: US | N11: 08512
A12: TEB3 | B12: TEB3 | C12: TEB3 | D12: TEB3 | E12: Amazon | F12: 1234567890 | H12: 2651 Oldmans Creek Rd | K12: Logan Township | L12: NJ | M12: US | N12: 08085
A13: IVSD | B13: IVSD | C13: IVSD | D13: IVSD | E13: Amazon | F13: 1234567890 | H13: UNO - Swedesboro NJ 800 Arlington Blvd Swedesboro | K13: Swedesboro | L13: NJ | M13: US | N13: 08085
A14: TEB4 | B14: TEB4 | C14: TEB4 | D14: TEB4 | E14: Amazon | F14: 1234567890 | H14: 747 COURSES LANDING RD | K14: PENNS GROVE | L14: NJ | M14: US | N14: 08069
... A135: FTW9 | B135: FTW9 | C135: FTW9 | D135: FTW9 | E135: Amazon | F135: 1234567890 | H135: 944 West Sandy Lake Road | K135: COPPELL | L135: TX | M135: US | N135: 75019
A136: TUL2 | B136: TUL2 | C136: TUL2 | D136: TUL2 | E136: Amazon | H136: 4040 N 125th E Ave | K136: Tulsa | L136: OK | M136: US | N136: 74116
A137: OKC1 | B137: OKC1 | C137: OKC1 | D137: OKC1 | E137: Amazon | F137: 1234567890 | H137: 9201 S Portland Avenue | K137: OKLAHOMA CITY | L137: OK | M137: US | N137: 73159
A138: OKC2 | B138: OKC2 | C138: OKC2 | D138: OKC2 | E138: Amazon | F138: 1234567890 | H138: 8991 S Portland Avenue | K138: OKLAHOMA CITY | L138: OK | M138: US | N138: 73159
A139: LIT2 | B139: LIT2 | C139: LIT2 | D139: LIT2 | E139: Amazon | F139: 1234567890 | H139: 13001 HIGHWAY 70 | K139: North Little Rock | L139: AR | M139: US | N139: 72117
A140: LFT1 | B140: LFT1 | C140: LFT1 | D140: LFT1 | E140: Amazon | F140: 1234567890 | H140: 3550 NE EVANGELINE TRWY | K140: CARENCRO | L140: LA | M140: US | N140: 70520
A141: TUL1 | B141: TUL1 | C141: TUL1 | D141: TUL1 | E141: Amazon | F141: 1234567890 | H141: 2654 North Highway 169 | K141: Coffeyville | L141: KS | M141: US | N141: 67337
A142: ICT2 | B142: ICT2 | C142: ICT2 | D142: ICT2 | E142: Amazon | F142: 1234567890 | H142: 7130 N BROADWAY AVE | K142: PARK CITY | L142: KS | M142: US | N142: 67219
A143: MCI1 | B143: MCI1 | C143: MCI1 | D143: MCI1 | E143: Amazon | F143: 1234567890 | H143: 113th St & Renner Blvd. | K143: Lenexa | L143: KS | M143: US | N143: 66219
A144: FOE1 | B144: FOE1 | C144: FOE1 | D144: FOE1 | E144: Amazon | F144: 1234567890 | H144: 9400 LEAVENWORTH RD | K144: KANSAS CITY | L144: KS | M144: US | N144: 66109
A145: MKC6 | B145: MKC6 | C145: MKC6 | D145: MKC6 | E145: Amazon | F145: 1234567890 | H145: 6925 Riverview Avenue | K145: Kansas City | L145: KS | M145: US | N145: 66102
A146: MKC4 | B146: MKC4 | C146: MKC4 | D146: MKC4 | E146: Amazon | F146: 1234567890 | H146: 19645 Waverly Rd | K146: Edgerton | L146: KS | M146: US | N146: 66021
A147: STL3 | B147: STL3 | C147: STL3 | D147: STL3 | E147: Amazon | F147: 1234567890 | H147: 3200 E SAWYER RD | K147: REPUBLIC | L147: MO | M147: US | N147: 65738
A148: STL8 | B148: STL8 | C148: STL8 | D148: STL8 | E148: Amazon | F148: 1234567890 | H148: 4000 Premier Parkway SAINT PETERS | K148: SAINT PETERS | L148: MO | M148: US | N148: 63376
... A291: GGE7 | B291: GGE7 | C291: GGE7 | D291: GGE7 | E291: Amazon | F291: 1234567890 | H291: Muse Paintbar 329 Greenwich Street | K291: New York | L291: NY | M291: US | N291: 10013
A292: QXY9 | B292: QXY9 | C292: QXY9 | D292: QXY9 | F292: 1234567890 | H292: 36900 W FOURTH ST | K292: BEAUMONT | L292: CA | M292: US | N292: 92223
A293: ORF2-23297 | B293: ORF2-23297 | C293: ORF2-23297 | D293: ORF2-23297 | E293: Amazon.com Services Inc. | F293: 1234567890 | H293: 9603 Coach Road | K293: Richmond | L293: VA | M293: US | N293: 23297
A294: OLM1 | B294: OLM1 | C294: OLM1 | D294: OLM1 | F294: 1234567890 | H294: 3300 HOGUM BAY RD NE | K294: OLYMPIA | L294: WA | M294: US | N294: 98516-3111
A295: MCE1 | B295: MCE1 | C295: MCE1 | D295: MCE1 | F295: 1234567890 | H295: 3200 Fulkerth Road | K295: TURLOCK | L295: CA | M295: US | N295: 95380
A296: VGT2 | B296: VGT2 | C296: VGT2 | D296: VGT2 | F296: 1234567890 | H296: 6401 Howdy Wells Ave | K296: LAS VEGAS | L296: NV | M296: US | N296: 89115
A297: CHO1 | B297: CHO1 | C297: CHO1 | D297: CHO1 | F297: 1234567890 | H297: 32 Trader Rd | K297: Fishersville | L297: VA | M297: US | N297: 22939
A298: MDT4 | B298: MDT4 | C298: MDT4 | D298: MDT4 | F298: 1234567890 | H298: 5125 Commerce Dr | K298: York | L298: PA | M298: US | N298: 17408
A299: AMA1 | B299: AMA1 | C299: AMA1 | D299: AMA1 | F299: 1234567890 | H299: 8590 NE 24th Avenue | K299: AMARILLO | L299: TX | M299: US | N299: 79108
A300: BFL2 | B300: BFL2 | C300: BFL2 | D300: BFL2 | F300: 1234567890 | H300: 4500 Express Ave | K300: Shafter | L300: CA | M300: US | N300: 93263
A301: SWF2 | B301: SWF2 | C301: SWF2 | D301: SWF2 | F301: 1234567890 | H301: 76 Patriot Way | K301: Hopewell Junction | L301: NY | M301: US | N301: 12533
A302: IUSJ | B302: IUSJ | C302: IUSJ | D302: IUSJ | F302: 1234567890 | H302: 6900 West 4th Street | K302: BEAUMONT | L302: CA | M302: US | N302: 92223
A303: IAH3 | B303: IAH3 | C303: IAH3 | D303: IAH3 | F303: 1234567890 | H303: 15525 Milner Road | K303: HOUSTON | L303: TX | M303: US | N303: 77032
A304: SCK8 | B304: SCK8 | C304: SCK8 | D304: SCK8 | F304: 1234567890 | H304: 4700 WILBUR AVE | K304: OAKLEY | L304: CA | M304: US | N304: 94561
A305: RDU2 | B305: RDU2 | C305: RDU2 | D305: RDU2 | F305: 1234567890 | H305: 2150 US HWY 70 Business West | K305: SMITHFIELD | L305: NC | M305: US | N305: 27577
A306: ORF2 | B306: ORF2 | C306: ORF2 | D306: ORF2 | F306: 1234567890 | H306: 5045 Portsmouth Blvd | K306: Chesapeake | L306: VA | M306: US | N306: 23321
A307: RMN3 | B307: RMN3 | C307: RMN3 | D307: RMN3 | F307: 1234567890 | H307: 220 Centreport Parkway | K307: FREDERICKSBURG | L307: VA | M307: US | N307: 22406
A308: CLT6 | B308: CLT6 | C308: CLT6 | D308: CLT6 | F308: 1234567890 | H308: Carolina Logistics Dr | K308: Pineville | L308: NC | M308: US | N308: 28134
A309: MCI3 | B309: MCI3 | C309: MCI3 | D309: MCI3 | F309: 1234567890 | H309: 2361 S Withers Rd | K309: Liberty | L309: MO | M309: US | N309: 64068
A310: RIC3-23234 | B310: RIC3-23234 | C310: RIC3-23234 | D310: RIC3-23234 | F310: 1234567890 | H310: 4949 Commerce Rd RICHMOND | K310: Chesterfield | L310: VA | M310: US | N310: 23234
A311: RDU4 | B311: RDU4 | C311: RDU4 | D311: RDU4 | F311: 1234567890 | H311: 6309 Bragg Blvd | K311: FAYETTEVILLE | L311: NC | M311: US | N311: 28303
A312: LBE1 | B312: LBE1 | C312: LBE1 | D312: LBE1 | F312: 1234567890 | H312: 165 GLENN FOX RD | K312: NEW STANTON | L312: PA | M312: US | N312: 15672
A313: LAN2 | B313: LAN2 | C313: LAN2 | D313: LAN2 | F313: 1234567890 | H313: 6500 W Mt Hope Hwy | K313: LANSING | L313: MI | M313: US | N313: 48917
A314: AKR1 | B314: AKR1 | C314: AKR1 | D314: AKR1 | F314: 1234567890 | H314: 4747 Rebar Ave NE | K314: CANTON | L314: OH | M314: US | N314: 44705
A315: ABQ2 | B315: ABQ2 | C315: ABQ2 | D315: ABQ2 | F315: 1234567890 | H315: 6251 Pioneer Trail NW | K315: LOS LUNAS | L315: NM | M315: US | N315: 87031
A316: TMB8 | B316: TMB8 | C316: TMB8 | D316: TMB8 | F316: 1234567890 | H316: 27505 SW 132nd AVE | K316: HOMESTEAD | L316: FL | M316: US | N316: 33032
... A320: PSC2-97242 | B320: PSC2-97242 | C320: PSC2-97242 | D320: PSC2-97242 | F320: 1234567890 | H320: 9930 NE Alderwood Rd | K320: Portland | L320: OR | M320: US | N320: 97242
A321: PBI3 | B321: PBI3 | C321: PBI3 | D321: PBI3 | F321: 1234567890 | H321: 7600 LTC Parkway | K321: PORT SAINT LUCIE | L321: FL | M321: US | N321: 34986
A322: RYY2 | B322: RYY2 | C322: RYY2 | D322: RYY2 | F322: 1234567890 | H322: 1250 Cassville White Road | K322: White | L322: GA | M322: US | N322: 30184
A323: HGR6 | B323: HGR6 | C323: HGR6 | D323: HGR6 | F323: 1234567890 | H323: 55 West Oak Ridge Drive | K323: HAGERSTOWN | L323: MD | M323: US | N323: 21740
A324: HIA1 | B324: HIA1 | C324: HIA1 | D324: HIA1 | F324: 1234567890 | H324: 3327 E Harrisburg Pik | K324: MIDDLETOWN | L324: PA | M324: US | N324: 17057
A325: MIT2 | B325: MIT2 | C325: MIT2 | D325: MIT2 | F325: 1234567890 | H325: 5408 Express Avenue | K325: SHAFTER | L325: CA | M325: US | N325: 93263
A326: GEU3 | B326: GEU3 | C326: GEU3 | D326: GEU3 | F326: 1234567890 | H326: 18900 W McDowell Road | K326: BUCKEYE | L326: AZ | M326: US | N326: 85396
A327: XLX1 | B327: XLX1 | C327: XLX1 | D327: XLX1 | F327: 1234567890 | H327: 1115 Wesel Blvd | K327: HAGERSTOWN | L327: MD | M327: US | N327: 21740
A328: XLG1 | B328: XLG1 | C328: XLG1 | D328: XLG1 | F328: 1234567890 | H328: 1901 California St | K328: Redlands | L328: CA | M328: US | N328: 92374
A329: JOT1 | B329: JOT1 | C329: JOT1 | D329: JOT1 | F329: 1234567890 | H329: 1494 S WATERMAN AVE | K329: SAN BERNARDINO | L329: CA | M329: US | N329: 92408
A330: QXY5 | B330: QXY5 | C330: QXY5 | D330: QXY5 | F330: 1234567890 | H330: 4532 NEWCASTLE RD | K330: STOCKTON | L330: CA | M330: US | N330: 95215
A331: IUSQ | B331: IUSQ | C331: IUSQ | D331: IUSQ | F331: 1234567890 | H331: 2125 W San Bernardino Ave | K331: REDLANDS | L331: CA | M331: US | N331: 92374
A332: GEU5 | B332: GEU5 | C332: GEU5 | D332: GEU5 | F332: 1234567890 | H332: 4660 North Cotton Lane | K332: GOODYEAR | L332: AZ | M332: US | N332: 85395
A333: GEU2 | B333: GEU2 | C333: GEU2 | D333: GEU2 | F333: 1234567890 | H333: 15301 West Northern Avenue | K333: Glendale | L333: AZ | M333: US | N333: 85340
A334: IUSF | B334: IUSF | C334: IUSF | D334: IUSF | F334: 1234567890 | H334: 3351 Balmorhea Dr | K334: DALLAS | L334: TX | M334: US | N334: 75241
A335: LAN2-49509 | B335: LAN2-49509 | C335: LAN2-49509 | D335: LAN2-49509 | F335: 1234567890 | H335: 5801 Clyde Park Ave Sw | K335: Wyoming | L335: MI | M335: US | N335: 49509
A336: BNA6-37207 | B336: BNA6-37207 | C336: BNA6-37207 | D336: BNA6-37207 | F336: 1234567890 | H336: 3207 Whites Creek Pike | K336: Nashville | L336: TN | M336: US | N336: 37207
A337: RFD2 | B337: RFD2 | C337: RFD2 | D337: RFD2 | F337: 1234567890 | H337: 11500 Freeman Road | K337: HUNTLEY | L337: IL | M337: US | N337: 60142
A338: RFD4 | B338: RFD4 | C338: RFD4 | D338: RFD4 | F338: 1234567890 | H338: 11400 Venture Court | K338: HUNTLEY | L338: IL | M338: US | N338: 60142
A339: MEM8 | B339: MEM8 | C339: MEM8 | D339: MEM8 | F339: 1234567890 | H339: 850 GATEWAY GLOBAL DR | K339: BYHALIA | L339: MS | M339: US | N339: 38611
A340: GEU2-85307 | B340: GEU2-85307 | C340: GEU2-85307 | D340: GEU2-85307 | F340: 1234567890 | H340: 15301 WEST NORTHERN AVENUE | K340: GLENDALE | L340: AZ | M340: US | N340: 85307
A341: PBI3-32206 | B341: PBI3-32206 | C341: PBI3-32206 | D341: PBI3-32206 | F341: 1234567890 | H341: 21 Jump Street | K341: Jacksonville | L341: FL | M341: US | N341: 32206
A342: RYY2-30325 | B342: RYY2-30325 | C342: RYY2-30325 | D342: RYY2-30325 | F342: 1234567890 | H342: 1250 Cassville White Road | K342: Atlanta | L342: GA | M342: US | N342: 30325
A343: IUSP | B343: IUSP | C343: IUSP | D343: IUSP | F343: 1234567890 | H343: 8140 Caliente Rd | K343: HESPERIA | L343: CA | M343: US | N343: 92344
A344: RYY2-30325 | B344: RYY2-30325 | C344: RYY2-30325 | D344: RYY2-30325 | F344: 1234567890 | H344: 1250 Cassville White Road | K344: Atlanta | L344: GA | M344: US | N344: 30325
A345: PBI3-32206 | B345: PBI3-32206 | C345: PBI3-32206 | D345: PBI3-32206 | F345: 1234567890 | H345: 21 Jump Street | K345: Jacksonville | L345: FL | M345: US | N345: 32206
A346: GEU2-85307 | B346: GEU2-85307 | C346: GEU2-85307 | D346: GEU2-85307 | F346: 1234567890 | H346: 15301 WEST NORTHERN AVENUE | K346: GLENDALE | L346: AZ | M346: US | N346: 85307
A347: MEM8 | B347: MEM8 | C347: MEM8 | D347: MEM8 | F347: 1234567890 | H347: 850 GATEWAY GLOBAL DR | K347: BYHALIA | L347: MS | M347: US | N347: 38611
A348: RFD4 | B348: RFD4 | C348: RFD4 | D348: RFD4 | F348: 1234567890 | H348: 11400 Venture Court | K348: HUNTLEY | L348: IL | M348: US | N348: 60142
A349: PPO4 | B349: PPO4 | C349: PPO4 | D349: PPO4 | F349: 1234567890 | H349: 9850 Mississippi Street | K349: Crown Point | L349: IN | M349: US | N349: 46307
A350: TMB8-33055 | B350: TMB8-33055 | C350: TMB8-33055 | D350: TMB8-33055 | F350: 1234567890 | H350: 8675309 Jenny Lane | K350: Miami Gardens | L350: FL | M350: US | N350: 33055
A351: POC1 | B351: POC1 | C351: POC1 | D351: POC1 | F351: 1234567890 | H351: 4121 LYTLE CREEK RD | K351: FONTANA | L351: CA | M351: US | N351: 92336
A352: POC3 | B352: POC3 | C352: POC3 | D352: POC3 | F352: 1234567890 | H352: 6120 Clinker Drive | K352: JURUPA VALLEY | L352: CA | M352: US | N352: 92509
A353: LAX1 | B353: LAX1 | C353: LAX1 | D353: LAX1 | F353: 1234567890 | H353: 6750 Kimball Ave | K353: Chino | L353: CA | M353: US | N353: 91708
A354: LAX2 | B354: LAX2 | C354: LAX2 | D354: LAX2 | F354: 1234567890 | H354: 6730 Kimball Ave | K354: Chino | L354: CA | M354: US | N354: 91708
A355: ABQ2-85395 | B355: ABQ2-85395 | C355: ABQ2-85395 | D355: ABQ2-85395 | F355: 1234567890 | H355: 16601 W. SELLS DRIVE | K355: GOODYEAR | L355: AZ | M355: US | N355: 85395
A356: VGT2-92518 | B356: VGT2-92518 | C356: VGT2-92518 | D356: VGT2-92518 | F356: 1234567890 | H356: 20701 Krameria Avenue | K356: March Air Reserve Base | L356: CA | M356: US | N356: 92518
A357: RMN3-17057 | B357: RMN3-17057 | C357: RMN3-17057 | D357: RMN3-17057 | F357: 1234567890 | H357: 2112 N Union Street | K357: Middletown | L357: PA | M357: US | N357: 17057
A358: LBE1-15605 | B358: LBE1-15605 | C358: LBE1-15605 | D358: LBE1-15605 | F358: 1234567890 | H358: 165 Glen Fox Road, | K358: Greensburg | L358: PA | M358: US | N358: 15605
A359: WBW2-18348 | B359: WBW2-18348 | C359: WBW2-18348 | D359: WBW2-18348 | F359: 1234567890 | H359: 1300 Corporate Way | K359: Pocono Lake Preserve | L359: PA | M359: US | N359: 18348
A360: MIT2-93291 | B360: MIT2-93291 | C360: MIT2-93291 | D360: MIT2-93291 | F360: 1234567890 | H360: 3256 N Plaza Dr | K360: Visalia | L360: CA | M360: US | N360: 93291
A361: POC3-92508 | B361: POC3-92508 | C361: POC3-92508 | D361: POC3-92508 | F361: 1234567890 | H361: 6120 Clinker Dr | K361: Riverside | L361: CA | M361: US | N361: 92508
... A363: TCY2 | B363: TCY2 | C363: TCY2 | D363: TCY2 | F363: 1234567890 | H363: 6201 Newcastle Rd | K363: STOCKTON | L363: CA | M363: US | N363: 95215
A364: TCY1 | B364: TCY1 | C364: TCY1 | D364: TCY1 | F364: 1234567890 | H364: 2690 East Arch Airport Road | K364: STOCKTON | L364: CA | M364: US | N364: 95206
A365: IUSR | B365: IUSR | C365: IUSR | D365: IUSR | F365: 1234567890 | H365: 1120 Mt Olive Rd | K365: COWPENS | L365: SC | M365: US | N365: 29330
A366: IUST | B366: IUST | C366: IUST | D366: IUST | F366: 1234567890 | H366: 15651 Greenmount Rd | K366: GREENCASTLE | L366: PA | M366: US | N366: 17225
...

Sheet 预计送仓数据
B1: 渠道 | C1: FBA仓库代码 | D1: 预计送仓时效 | E1: 区域
A2: =B2&C2 | B2: 丰速达16T卡派 | C2: ONT8 | D2: 16 | E2: 一区
A3: =B3&C3 | B3: 丰速达16T卡派 | C3: LGB8 | D3: 16 | E3: 一区
A4: =B4&C4 | B4: 丰速达16T卡派 | C4: LAX9 | D4: 16 | E4: 一区
A5: =B5&C5 | B5: 丰速达16T卡派 | C5: SBD1 | D5: 16 | E5: 一区
A6: =B6&C6 | B6: 丰速达16T卡派 | C6: POC1 | D6: 16 | E6: 一区
A7: =B7&C7 | B7: 丰速达16T卡派 | C7: POC2 | D7: 16 | E7: 一区
A8: =B8&C8 | B8: 丰速达16T卡派 | C8: POC3 | D8: 16 | E8: 一区
A9: =B9&C9 | B9: 丰速达16T卡派 | C9: IUSP | D9: 16 | E9: 二区
A10: =B10&C10 | B10: 丰速达16T卡派 | C10: IUSQ | D10: 16 | E10: 二区
A11: =B11&C11 | B11: 丰速达16T卡派 | C11: IUSJ | D11: 16 | E11: 二区
A12: =B12&C12 | B12: 丰速达16T卡派 | C12: IUTI | D12: 16 | E12: 二区
A13: =B13&C13 | B13: 丰速达16T卡派 | C13: IUSW | D13: 16 | E13: 二区
... A76: =B76&C76 | B76: 丰速达16T卡派 | C76: RMN3 | D76: 19 | E76: 十区
B78: 渠道 | C78: FBA仓库代码 | D78: 预计送仓时效 | E78: 区域
A79: =B79&C79 | B79: 丰速达20T卡派 | C79: ONT8 | D79: 18 | E79: 一区
A80: =B80&C80 | B80: 丰速达20T卡派 | C80: LGB8 | D80: 18 | E80: 一区
A81: =B81&C81 | B81: 丰速达20T卡派 | C81: LAX9 | D81: 18 | E81: 一区
A82: =B82&C82 | B82: 丰速达20T卡派 | C82: SBD1 | D82: 18 | E82: 一区
A83: =B83&C83 | B83: 丰速达20T卡派 | C83: POC1 | D83: 18 | E83: 一区
A84: =B84&C84 | B84: 丰速达20T卡派 | C84: POC2 | D84: 18 | E84: 一区
A85: =B85&C85 | B85: 丰速达20T卡派 | C85: POC3 | D85: 18 | E85: 一区
A86: =B86&C86 | B86: 丰速达20T卡派 | C86: IUSP | D86: 18 | E86: 二区
A87: =B87&C87 | B87: 丰速达20T卡派 | C87: IUSQ | D87: 18 | E87: 二区
A88: =B88&C88 | B88: 丰速达20T卡派 | C88: IUSJ | D88: 18 | E88: 二区
A89: =B89&C89 | B89: 丰速达20T卡派 | C89: IUTI | D89: 18 | E89: 二区
A90: =B90&C90 | B90: 丰速达20T卡派 | C90: IUSW | D90: 18 | E90: 二区
... A153: =B153&C153 | B153: 丰速达20T卡派 | C153: RMN3 | D153: 21 | E153: 十区
B155: 渠道 | C155: FBA仓库代码 | D155: 预计送仓时效 | E155: 区域
A156: =B156&C156 | B156: 美森CLX正班卡派 | C156: ONT8 | D156: 15 | E156: 一区
A157: =B157&C157 | B157: 美森CLX正班卡派 | C157: LGB8 | D157: 15 | E157: 一区
A158: =B158&C158 | B158: 美森CLX正班卡派 | C158: LAX9 | D158: 15 | E158: 一区
A159: =B159&C159 | B159: 美森CLX正班卡派 | C159: SBD1 | D159: 15 | E159: 一区
A160: =B160&C160 | B160: 美森CLX正班卡派 | C160: POC1 | D160: 15 | E160: 一区
A161: =B161&C161 | B161: 美森CLX正班卡派 | C161: POC2 | D161: 15 | E161: 一区
A162: =B162&C162 | B162: 美森CLX正班卡派 | C162: POC3 | D162: 15 | E162: 一区
A163: =B163&C163 | B163: 美森CLX正班卡派 | C163: IUSP | D163: 15 | E163: 二区
A164: =B164&C164 | B164: 美森CLX正班卡派 | C164: IUSQ | D164: 15 | E164: 二区
A165: =B165&C165 | B165: 美森CLX正班卡派 | C165: IUSJ | D165: 15 | E165: 二区
A166: =B166&C166 | B166: 美森CLX正班卡派 | C166: IUTI | D166: 15 | E166: 二区
A167: =B167&C167 | B167: 美森CLX正班卡派 | C167: IUSW | D167: 15 | E167: 二区
... A230: =B230&C230 | B230: 美森CLX正班卡派 | C230: RMN3 | D230: 18 | E230: 十区
B232: 渠道 | C232: FBA仓库代码 | D232: 预计送仓时效 | E232: 区域
A233: =B233&C233 | B233: 美森加班卡派 | C233: ONT8 | D233: 15 | E233: 一区
A234: =B234&C234 | B234: 美森加班卡派 | C234: LGB8 | D234: 15 | E234: 一区
A235: =B235&C235 | B235: 美森加班卡派 | C235: LAX9 | D235: 15 | E235: 一区
A236: =B236&C236 | B236: 美森加班卡派 | C236: SBD1 | D236: 15 | E236: 一区
A237: =B237&C237 | B237: 美森加班卡派 | C237: POC1 | D237: 15 | E237: 一区
A238: =B238&C238 | B238: 美森加班卡派 | C238: POC2 | D238: 15 | E238: 一区
A239: =B239&C239 | B239: 美森加班卡派 | C239: POC3 | D239: 15 | E239: 一区
A240: =B240&C240 | B240: 美森加班卡派 | C240: IUSP | D240: 15 | E240: 二区
A241: =B241&C241 | B241: 美森加班卡派 | C241: IUSQ | D241: 15 | E241: 二区
A242: =B242&C242 | B242: 美森加班卡派 | C242: IUSJ | D242: 15 | E242: 二区
A243: =B243&C243 | B243: 美森加班卡派 | C243: IUTI | D243: 15 | E243: 二区
A244: =B244&C244 | B244: 美森加班卡派 | C244: IUSW | D244: 15 | E244: 二区
... A307: =B307&C307 | B307: 美森加班卡派 | C307: RMN3 | D307: 18 | E307: 十区
B309: 渠道 | C309: FBA仓库代码 | D309: 预计送仓时效 | E309: 区域
A310: =B310&C310 | B310: 丰速达18T卡派 | C310: ONT8 | D310: 17 | E310: 一区
A311: =B311&C311 | B311: 丰速达18T卡派 | C311: LGB8 | D311: 17 | E311: 一区
A312: =B312&C312 | B312: 丰速达18T卡派 | C312: LAX9 | D312: 17 | E312: 一区
A313: =B313&C313 | B313: 丰速达18T卡派 | C313: SBD1 | D313: 17 | E313: 一区
A314: =B314&C314 | B314: 丰速达18T卡派 | C314: POC1 | D314: 17 | E314: 一区
A315: =B315&C315 | B315: 丰速达18T卡派 | C315: POC2 | D315: 17 | E315: 一区
A316: =B316&C316 | B316: 丰速达18T卡派 | C316: POC3 | D316: 17 | E316: 一区
A317: =B317&C317 | B317: 丰速达18T卡派 | C317: IUSP | D317: 17 | E317: 二区
A318: =B318&C318 | B318: 丰速达18T卡派 | C318: IUSQ | D318: 17 | E318: 二区
A319: =B319&C319 | B319: 丰速达18T卡派 | C319: IUSJ | D319: 17 | E319: 二区
A320: =B320&C320 | B320: 丰速达18T卡派 | C320: IUTI | D320: 17 | E320: 二区
A321: =B321&C321 | B321: 丰速达18T卡派 | C321: IUSW | D321: 17 | E321: 二区
... A384: =B384&C384 | B384: 丰速达18T卡派 | C384: RMN3 | D384: 20 | E384: 十区
